Workbook

Sheet Data Collection Sheet
C1: YoY growth = | D1: 1.15 | E1: % | G1: Month | I1: Jan'22 | J1: Feb'22 | K1: Mar'22 | L1: Apr'22 | M1: May'22 | N1: Jun'22 | O1: Jul'22 | P1: Aug'22 | Q1: Sep'22 | R1: Oct'22 | S1: Nov'22 | T1: Dec'22 | U1: Jan'23 | V1: Feb'23 | W1: Mar'23 | X1: Apr'23 | Y1: May'23 | Z1: Jun'23 | AA1: Jul'23 | AB1: Aug'23 | AC1: Sep'23 | AD1: Oct'23 | AE1: Nov'23 | AF1: Dec'23 | AG1: Jan'24 | AH1: Feb'24 | AI1: Mar'24 | AJ1: Apr'24 | AK1: May'24 | AL1: Jun'24 | AM1: Jul'24 | AN1: Aug'24 | AO1: Sep'24 | AP1: Oct'24 | AQ1: Nov'24 | AR1: Dec'24 | AS1: Jan'25 | AT1: Feb'25 | AU1: Mar'25 | AV1: Apr'25 | AW1: May'25 | AX1: Jun'25 | AY1: Jul'25 | AZ1: Aug'25 | BA1: Sep'25 | BB1: Oct'25 | BC1: Nov'25 | BD1: Dec'25 | BE1: Jan'26 | BF1: Feb'26 | BG1: Mar'26 | BH1: Apr'26 | BI1: May'26 | BJ1: Jun'26 | BK1: Jul'26 | BL1: Aug'26
D2: 4 | G2: TOTAL CAPACITY ON ARRAY (TB) | I2: =$G$25+$G$55+$G$69+$G$92+$G$100+$G$109 -> 337.81 | J2: =$G$25+$G$55+$G$69+$G$92+$G$100+$G$109 -> 337.81 | K2: =$G$25+$G$55+$G$69+$G$92+$G$100+$G$109 -> 337.81 | L2: =$G$25+$G$55+$G$69+$G$92+$G$100+$G$109 -> 337.81 | M2: =$G$25+$G$55+$G$69+$G$92+$G$100+$G$109 -> 337.81 | N2: =$G$25+$G$55+$G$69+$G$92+$G$100+$G$109 -> 337.81 | O2: =$G$25+$G$55+$G$69+$G$92+$G$100+$G$109 -> 337.81 | P2: =$G$25+$G$55+$G$69+$G$92+$G$100+$G$109 -> 337.81 | ... AF2: =$G$25+$G$55+$G$69+$G$92+$G$100+$G$109 -> 337.81 | AG2: =$G$25+$G$55+$G$69+$G$92+$G$109 -> 325.1 | AH2: =$G$25+$G$55+$G$69+$G$92+$G$109 -> 325.1 | AI2: =$G$25+$G$55+$G$69+$G$92+$G$109 -> 325.1 | AJ2: =$G$25+$G$55+$G$69+$G$92+$G$109 -> 325.1 | AK2: =$G$25+$G$55+$G$69+$G$92+$G$109 -> 325.1 | AL2: =$G$25+$G$55+$G$69+$G$92+$G$109 -> 325.1 | AM2: =$G$25+$G$55+$G$69+$G$92+$G$109 -> 325.1 | AN2: =$G$25+$G$55+$G$69+$G$92+$G$109 -> 325.1 | ... AQ2: =$G$25+$G$55+$G$69+$G$92+$G$109 -> 325.1 | AR2: =$G$25+$G$55+$G$69+$G$92+$G$109+$G$118+$G$125+$G$132+$G$138+$G$144+$G$150+$G$156+$G$162 -> 611.2 | AS2: =$G$25+$G$55+$G$69+$G$92+$G$109+$G$118+$G$125+$G$132+$G$138+$G$144+$G$150+$G$156+$G$162 -> 611.2 | AT2: =$G$25+$G$55+$G$69+$G$92+$G$109+$G$118+$G$125+$G$132+$G$138+$G$144+$G$150+$G$156+$G$162 -> 611.2 | AU2: =$G$25+$G$55+$G$69+$G$92+$G$109+$G$118+$G$125+$G$132+$G$138+$G$144+$G$150+$G$156+$G$162 -> 611.2 | AV2: =$G$25+$G$55+$G$69+$G$92+$G$109+$G$118+$G$125+$G$132+$G$138+$G$144+$G$150+$G$156+$G$162 -> 611.2 | AW2: =$G$25+$G$55+$G$69+$G$92+$G$109+$G$118+$G$125+$G$132+$G$138+$G$144+$G$150+$G$156+$G$162 -> 611.2 | AX2: =$G$25+$G$55+$G$69+$G$92+$G$109+$G$118+$G$125+$G$132+$G$138+$G$144+$G$150+$G$156+$G$162 -> 611.2 | AY2: =$G$25+$G$55+$G$69+$G$92+$G$109+$G$118+$G$125+$G$132+$G$138+$G$144+$G$150+$G$156+$G$162 -> 611.2 | ... BG2: =$G$25+$G$55+$G$69+$G$92+$G$109+$G$118+$G$125+$G$132+$G$138+$G$144+$G$150+$G$156+$G$162 -> 611.2 | BH2: =$G$25+$G$55+$G$69+$G$92+$G$109+$G$118+$G$125+G132+G138+G144+G150+G156+G162 -> 611.2 | BI2: =$G$25+$G$55+$G$69+$G$92+$G$109+$G$118+$G$125+G132+G138+G144+G150+G156+G162 -> 611.2 | BJ2: =$G$25+$G$55+$G$69+$G$78+$G$92+$G$109+$G$118+$G$125+G132+G138+G144+G150+G156+G162 -> 809.2 | BK2: =$G$25+$G$55+$G$69+$G$78+$G$92+$G$109+$G$118+$G$125+H132+H138+H144+H150+H156+H162 -> 574.5 | BL2: =$G$25+$G$55+$G$69+$G$78+$G$92+$G$109+$G$118+$G$125+I132+I138+I144+I150+I156+I162 -> 917.8
G3: TOTAL IN-USE ON ARRAY | I3: =I24+I54+I68+I91+I99+I108+I118+I124+I131+I137+I143+I149+I155+I161 -> 296.46124 | J3: =J24+J54+J68+J91+J99+J108+J118+J124+J131+J137+J143+J149+J155+J161 -> 295.8236 | K3: =K24+K54+K68+K91+K99+K108+K118+K124+K131+K137+K143+K149+K155+K161 -> 360.6608 | L3: =L24+L54+L68+L91+L99+L108+L118+L124+L131+L137+L143+L149+L155+L161 -> 354.481 | M3: =M24+M54+M68+M91+M99+M108+M118+M124+M131+M137+M143+M149+M155+M161 -> 353.823 | N3: =N24+N54+N68+N91+N99+N108+N118+N124+N131+N137+N143+N149+N155+N161 -> 328.31 | O3: =O24+O54+O68+O91+O99+O108+O118+O124+O131+O137+O143+O149+O155+O161 -> 333.107 | P3: =P24+P54+P68+P91+P99+P108+P118+P124+P131+P137+P143+P149+P155+P161 -> 309.91 | ... BI3: =BI24+BI54+BI68+BI91+BI99+BI108+BI118+BI124+BI131+BI137+BI143+BI149+BI155+BI161 -> 413.58 | BJ3: =BJ24+BJ54+BJ68+BJ77+BJ91+BJ99+BJ108+BJ118+BJ124+BJ131+BJ137+BJ143+BJ149+BJ155+BJ161 -> 493.44 | BK3: =BK24+BK54+BK68+BK77+BK91+BK99+BK108+BK118+BK124+BK131+BK137+BK143+BK149+BK155+BK161 -> 495.69 | BL3: =BL24+BL54+BL68+BL77+BL91+BL99+BL108+BL118+BL124+BL131+BL137+BL143+BL149+BL155+BL161 -> 494.79
G4: TOTAL AVAILABLE ON ARRAY | I4: =I25+I55+I69+I92+I100+I109 -> 125.73876 | J4: =J25+J55+J69+J92+J100+J109 -> 127.4204 | K4: =K25+K55+K69+K92+K100+K109 -> 106.2784 | L4: =L25+L55+L69+L92+L100+L109 -> 120.66 | M4: =M25+M55+M69+M92+M100+M109 -> 106.727 | N4: =N25+N55+N69+N92+N100+N109 -> 87.79 | O4: =O25+O55+O69+O92+O100+O109 -> 80.593 | P4: =P25+P55+P69+P92+P100+P109 -> 102.79 | ... BI4: =BI25+BI55+BI69+BI92+BI100+BI109 -> 67.25 | BJ4: =BJ25+BJ55+BJ69+BJ92+BJ100+BJ109+BJ118+BJ125+BJ132+BJ138+BJ144+BJ150+BJ156+BJ162 -> 414.02 | BK4: =BK25+BK55+BK69+BK92+BK100+BK109+BK118+BK125+BK132+BK138+BK144+BK150+BK156+BK162 -> 412.89 | BL4: =BL25+BL55+BL69+BL92+BL100+BL109+BL118+BL125+BL132+BL138+BL144+BL150+BL156+BL162 -> 412.7
B8: Site | C8: Storage Unit | D8: Host group | E8: Workload type (Volume Group) | G8: 1. From ARRAY Level 2. Total USABLE data 3. before data-reduc. 4. in Tbyte | BN8: 1. Looking on Compute level 2. Data-actual in-use 3. After data-redu. 4. in Tbyte
I9: Jan'22 | J9: Feb'22 | K9: Mar'22 | L9: Apr'22 | M9: May'22 | N9: Jun'22 | O9: Jul'22 | P9: Aug'22 | Q9: Sep'22 | R9: Oct'22 | S9: Nov'22 | T9: Dec'22 | U9: Jan'23 | V9: Feb'23 | W9: Mar'23 | X9: Apr'23 | Y9: May'23 | Z9: Jun'23 | AA9: Jul'23 | AB9: Aug'23 | AC9: Sep'23 | AD9: Oct'23 | AE9: Nov'23 | AF9: Dec'23 | AG9: Jan'24 | AH9: Feb'24 | AI9: Mar'24 | AJ9: Apr'24 | AK9: May'24 | AL9: Jun'24 | AM9: Jul'24 | AN9: Aug'24 | AO9: Sep'24 | AP9: Oct'24 | AQ9: Nov'24 | AR9: Dec'24 | AS9: Jan'25 | AT9: Feb'25 | AU9: Mar'25 | AV9: Apr'25 | AW9: May'25 | AX9: Jun'25 | AY9: Jul'25 | AZ9: Aug'25 | BA9: Sep'25 | BB9: Oct'25 | BC9: Nov'25 | BD9: Dec'25 | BE9: Jan'26 | BF9: Feb'26 | BG9: Mar'26 | BH9: Apr'26 | BI9: May'26 | BJ9: Jun'26 | BK9: Jul'26 | BL9: Aug'26 | BN9: Jan'22 | BO9: Feb'22 | BP9: Mar'22 | BQ9: Apr'22 | BR9: May'22 | BS9: Jun'22 | BT9: Jul'22 | BU9: Aug'22 | BV9: Sep'22 | BW9: Oct'22 | BX9: Nov'22 | BY9: Dec'22 | BZ9: Jan'23 | CA9: Feb'23 | CB9: Mar'23 | CC9: Apr'23 | CD9: May'23 | CE9: Jun'23 | CF9: Jul'23 | CG9: Aug'23 | CH9: Sep'23 | CI9: Oct'23 | CJ9: Nov'23 | CK9: Dec'23 | CL9: Jan'24 | CM9: Feb'24 | CN9: Mar'24 | CO9: Apr'24 | CP9: May'24 | CQ9: Jun'24 | CR9: July'24 | CS9: Aug'24 | CT9: Sep'24 | CU9: Oct'24 | CV9: Nov'24 | CW9: Dec'24 | CX9: Jan'25
B10: MacPark | C10: M20 | D10: CISCO-FlashStack (VMware) | E10: Vmware-FILESERVER | I10: 0.4 | J10: 0.345 | K10: 0.32 | L10: 0.33 | M10: 0.36 | N10: 0.22 | O10: 0.21 | P10: 0.23 | Q10: 0.2 | R10: 0.24 | S10: 0.26 | AV10: 8.56 | AW10: 8.59 | AX10: 8.67 | AY10: 8.74 | AZ10: 8.77 | BA10: 8.79 | BB10: 8.65 | BC10: 8.66 | BD10: 8.66 | BE10: 8.69 | BF10: 8.76 | BG10: 8.79 | BH10: 9.03 | BI10: 0.02 | BJ10: 0 | BK10: 0 | BL10: 0
B11: aum-pc-prd01 | E11: VMware - SQL - RDM | I11: 0.7 | J11: 0.745 | K11: 0.74 | L11: 0.74 | M11: 1.04 | N11: 0.06 | O11: 0.058 | P11: 0.06 | Q11: 0.06 | R11: 0.06 | S11: 0.06 | T11: 0.26 | AF11: 0.45 | AG11: 0.47 | AH11: 0.48 | AI11: 0.47 | AJ11: 0.5 | AK11: 0.61 | AL11: 0.67 | AM11: 0.74 | AN11: 0.77 | AO11: 0.82 | AP11: 0.83 | AQ11: 0.77 | AR11: 0.84 | AS11: 0.81 | AT11: 1.23 | AU11: 1.23 | AV11: 1.37 | AW11: 1.45 | AX11: 1.51 | AY11: 1.45 | AZ11: 1.49 | BA11: 1.53 | BB11: 1.56 | BC11: 1.6 | BD11: 1.57 | BE11: 1.59 | BF11: 1.69 | BG11: 1.78 | BH11: 1.85 | BI11: 1.79 | BJ11: 1.7 | BK11: 1.75 | BL11: 1.76
E12: VMware - SRM | I12: 26.6 | J12: 22.08 | K12: 23.63 | L12: 22.73 | M12: 11.25 | N12: 13.45 | O12: 13.02 | P12: 12.67 | Q12: 12.56 | R12: 11.09 | S12: 11.46 | T12: 0.056 | U12: 0.06 | V12: 0.06 | W12: 0.06 | X12: 0.06 | Y12: 0.06 | Z12: 0.06 | AA12: 0.06 | AB12: 0.06 | AC12: 0.06 | AD12: 0.06 | AE12: 0.06 | AF12: 0.07 | AG12: 0.07 | AH12: 0.07 | AI12: 0.07 | AJ12: 0.07 | AK12: 0.07 | AL12: 0.06 | AM12: 0.06 | AN12: 0.06 | AO12: 0.06 | AP12: 0.06 | AQ12: 0.06 | AR12: 0.06 | AS12: 0.06 | AT12: 0.06 | AU12: 0.06 | AV12: 0.06 | AW12: 0.06 | AX12: 0.06 | AY12: 0.06 | AZ12: 0.06 | BA12: 0.06 | BB12: 0.06 | BC12: 0.06 | BD12: 0.06 | BE12: 0.06 | BF12: 0.06 | BG12: 0.06 | BH12: 0.06 | BI12: 0.06 | BJ12: 0.06 | BK12: 0.06 | BL12: 0.06
E13: VMware - VMFS | T13: 11.9 | U13: 12.06 | V13: 21.55 | W13: 21.95 | X13: 23.55 | Y13: 14.5 | Z13: 15.24 | AA13: 15.64 | AB13: 16.49 | AC13: 16.17 | AD13: 16.35 | AE13: 16.77 | AF13: 16.43 | AG13: 16.44 | AH13: 17.55 | AI13: 17.1 | AJ13: 17.72 | AK13: 17.09 | AL13: 25.03 | AM13: 25.8 | AN13: 26.12 | AO13: 26.11 | AP13: 24.71 | AQ13: 24.64 | AR13: 24.6 | AS13: 25.41 | AT13: 24.91 | AU13: 24.91 | AV13: 24.71 | AW13: 24.89 | AX13: 25.54 | AY13: 25.66 | AZ13: 25.94 | BA13: 25.35 | BB13: 25.64 | BC13: 25.07 | BD13: 25.19 | BE13: 25.99 | BF13: 26.2 | BG13: 27.04 | BH13: 26.8 | BI13: 28.43 | BJ13: 28 | BK13: 27.6 | BL13: 26
D14: CISCO-FlashStack (x86 RAC) | E14: X86-ORACLE-RAC-NWC-DR | I14: 0.216 | J14: 0.218 | K14: 0.19 | L14: 0.19 | M14: 0.19 | N14: 0.21 | O14: 0.208 | P14: 0.21 | Q14: 0.21 | R14: 0.21 | S14: 0.21 | T14: 0.207 | U14: 0.19 | V14: 0.19 | W14: 0.19 | X14: 0.19 | Y14: 0.2 | Z14: 0.21 | AA14: 0.22 | AB14: 0.23 | AC14: 0.23 | AD14: 0.23 | AE14: 0.24 | AF14: 0.24 | AG14: 0.2 | AH14: 0.21 | AI14: 0.22 | AJ14: 0.22 | AK14: 0.23 | AL14: 0.23 | AM14: 0.23 | AN14: 0.23 | AO14: 0.23 | AP14: 0.22 | AQ14: 0.21 | AR14: 0.21 | AS14: 0.22 | AT14: 0.23 | AU14: 0.23 | AV14: 0.24 | AW14: 0.24 | AX14: 0.24 | AY14: 0.24 | AZ14: 0.23 | BA14: 0.22 | BB14: 0.22 | BC14: 0.21 | BD14: 0.21 | BE14: 0.21 | BF14: 0.21 | BG14: 0.21 | BH14: 0.21 | BI14: 0.21 | BJ14: 0.21 | BK14: 0.21 | BL14: 0.22 | BO14: 0.42 | BP14: 0.43 | BQ14: 0.4 | BR14: 0.4 | BS14: 0.4 | BT14: 0.4 | BU14: 0.4 | BV14: 0.4 | BW14: 0.4 | BX14: 0.48 | BY14: 0.52 | BZ14: 0.5 | CA14: 0.5 | CB14: 0.5 | CC14: 0.5 | CD14: 0.5 | CE14: 0.5 | CF14: 0.5 | CG14: 0.5 | CH14: 0.5 | CI14: 0.5 | CJ14: 0.5 | CK14: 0.5 | CL14: 0.5 | CM14: 0.5 | CN14: 0.5 | CO14: 0.5 | CP14: 0.5 | CQ14: 0.5 | CR14: 0.5 | CS14: 0.5
E15: X86-ORACLE-RAC-NWC-NPRD | I15: 0.56 | J15: 0.557 | K15: 0.558 | L15: 0.56 | M15: 0.5 | N15: 0.51 | O15: 0.437 | P15: 0.42 | Q15: 0.45 | R15: 0.44 | S15: 0.44 | T15: 0.44 | U15: 0.45 | V15: 0.44 | W15: 0.45 | X15: 0.44 | Y15: 0.45 | Z15: 0.46 | AA15: 0.47 | AB15: 0.48 | AC15: 0.49 | AD15: 0.49 | AE15: 0.49 | AF15: 0.5 | AG15: 0.49 | AH15: 0.52 | AI15: 0.53 | AJ15: 0.51 | AK15: 0.52 | AL15: 0.52 | AM15: 0.52 | AN15: 0.52 | AO15: 0.53 | AP15: 0.51 | AQ15: 0.5 | AR15: 0.5 | AS15: 0.5 | AT15: 0.5 | AU15: 0.5 | AV15: 0.53 | AW15: 0.48 | AX15: 0.49 | AY15: 0.47 | AZ15: 0.49 | BA15: 0.49 | BB15: 0.49 | BC15: 0.47 | BD15: 0.47 | BE15: 0.45 | BF15: 0.49 | BG15: 0.48 | BH15: 0.46 | BI15: 0.4 | BJ15: 0.4 | BK15: 0.4 | BL15: 0.43 | BO15: 1.13 | BP15: 1.13 | BQ15: 1.5 | BR15: 1.5 | BS15: 1.14 | BT15: 1.65 | BU15: 1.7 | BV15: 1.7 | BW15: 1.7 | BX15: 1.61 | BY15: 1.12 | BZ15: 1.2 | CA15: 1.2 | CB15: 1.1 | CC15: 1.1 | CD15: 1.1 | CE15: 1.1 | CF15: 1.1 | CG15: 1.1 | CH15: 1.2 | CI15: 1.2 | CJ15: 1.2 | CK15: 1.2 | CL15: 1.2 | CM15: 1.2 | CN15: 1.2 | CO15: 1.2 | CP15: 1.2 | CQ15: 1.2 | CR15: 1.2 | CS15: 1.2
E16: X86-ORACLE-RAC-OS-APP-NPRD | I16: 0.22 | J16: 0.228 | K16: 0.232 | L16: 0.23 | M16: 0.23 | N16: 0.24 | O16: 0.251 | P16: 0.25 | Q16: 0.25 | R16: 0.25 | S16: 0.26 | T16: 0.256 | U16: 0.26 | V16: 0.26 | W16: 0.26 | X16: 0.26 | Y16: 0.27 | Z16: 0.27 | AA16: 0.27 | AB16: 0.28 | AC16: 0.28 | AD16: 0.28 | AE16: 0.28 | AF16: 0.29 | AG16: 0.29 | AH16: 0.29 | AI16: 0.29 | AJ16: 0.29 | AK16: 0.29 | AL16: 0.29 | AM16: 0.29 | AN16: 0.29 | AO16: 0.29 | AP16: 0.28 | AQ16: 0.27 | AR16: 0.28 | AS16: 0.28 | AT16: 0.28 | AU16: 0.28 | AV16: 0.29 | AW16: 0.3 | AX16: 0.3 | AY16: 0.3 | AZ16: 0.3 | BA16: 0.3 | BB16: 0.3 | BC16: 0.3 | BD16: 0.31 | BE16: 0.31 | BF16: 0.31 | BG16: 0.31 | BH16: 0.31 | BI16: 0.31 | BJ16: 0.31 | BK16: 0.31 | BL16: 0.31 | BO16: 2.8 | BP16: 2.9 | BV16: 2.9 | BW16: 2.9 | BX16: 2.9 | BY16: 2.9
E17: X86-ORACLE-RAC-WC-DEV | I17: 0.15 | J17: 0.157 | K17: 0.205 | L17: 0.22 | M17: 0.01 | N17: 0.01 | O17: 0.0145 | P17: 0.04 | Q17: 0.04 | R17: 0.04 | S17: 0.04 | T17: 0.044 | U17: 0.05 | V17: 0.05 | W17: 0.05 | X17: 0.05 | Y17: 0.05 | Z17: 0.02 | AA17: 0.06 | AB17: 0.23 | AC17: 0.02 | AD17: 0.03 | AE17: 0 | AF17: 0.68 | AG17: 0.72 | AH17: 0.74 | AI17: 0.76 | AJ17: 0.78 | AK17: 0.8 | AL17: 0.8 | AM17: 0.99 | AN17: 1 | AO17: 1 | AP17: 0 | AQ17: 0 | AR17: 0 | AS17: 0 | AT17: 0 | AU17: 0 | AV17: 0 | AW17: 0 | AX17: 0 | AY17: 0 | AZ17: 0 | BA17: 0 | BB17: 0 | BC17: 0 | BD17: 0 | BE17: 0 | BF17: 0 | BG17: 0 | BH17: 0 | BI17: 0 | BJ17: 0 | BK17: 0 | BL17: 0 | BO17: 10.98 | BP17: 10.98 | BQ17: 12.7 | BR17: 12.7 | BS17: 12.75 | BT17: 12.75 | BU17: 12.77 | BV17: 12.77 | BW17: 12.77 | BX17: 12.77 | BY17: 12.8 | BZ17: 13.4 | CA17: 13.4 | CB17: 12.8 | CC17: 12.8 | CD17: 12.8 | CE17: 14.9 | CF17: 14.9 | CG17: 14.9 | CH17: 15.3 | CI17: 15.4 | CJ17: 15.5 | CK17: 15.5 | CL17: 15.5 | CM17: 15.5 | CN17: 15.5 | CO17: 15.5 | CP17: 15.5 | CQ17: 15.5 | CR17: 15.5 | CS17: 15.5
E18: X86-ORACLE-RAC-WC-DR | I18: 1.6 | J18: 1.67 | K18: 1.77 | L18: 1.83 | M18: 0.03 | N18: 0.18 | O18: 0.271 | P18: 0.48 | Q18: 0.58 | R18: 0.69 | S18: 0.97 | T18: 1.011 | U18: 1.07 | V18: 1.13 | W18: 1.38 | X18: 1.36 | Y18: 1.42 | Z18: 0.03 | AA18: 0.1 | AB18: 0.17 | AC18: 0.03 | AD18: 0.1 | AE18: 0.14 | AF18: 0.21 | AG18: 0.25 | AH18: 0.18 | AI18: 0.33 | AJ18: 0.4 | AK18: 0.44 | AL18: 0.88 | AM18: 0.01 | AN18: 0.02 | AO18: 0.03 | AP18: 0 | AQ18: 0 | AR18: 0 | AS18: 0 | AT18: 0 | AU18: 0 | AV18: 0 | AW18: 0 | AX18: 0 | AY18: 0 | AZ18: 0 | BA18: 0 | BB18: 0 | BC18: 0 | BD18: 0 | BE18: 0 | BF18: 0 | BG18: 0 | BH18: 0 | BI18: 0 | BJ18: 0 | BK18: 0 | BL18: 0 | BO18: 12 | BP18: 12.47 | BQ18: 13 | BR18: 13.1 | BS18: 12.98 | BT18: 13 | BU18: 13 | BV18: 13.59 | BW18: 13.89 | BX18: 14.01 | BY18: 14.11 | BZ18: 14.9 | CA18: 15 | CB18: 14.5 | CC18: 14.6 | CD18: 14.8 | CE18: 14.9 | CF18: 15.1 | CG18: 15.1 | CH18: 15.4 | CI18: 15.5 | CJ18: 15.7 | CK18: 15.7 | CL18: 16 | CM18: 16 | CN18: 16.3 | CO18: 16.3 | CP18: 16.3 | CQ18: 17 | CR18: 17.3 | CS18: 17.3
E19: X86-ORACLE-RAC-WC-TST | I19: 0.15 | J19: 0.162 | K19: 0.18 | L19: 0.18 | M19: 0.01 | N19: 0.01 | O19: 0.012 | P19: 0.02 | Q19: 0.03 | R19: 0.03 | S19: 0.03 | T19: 0.0326 | U19: 0.04 | V19: 0.04 | W19: 0.04 | X19: 0.04 | Y19: 0.04 | Z19: 0.004 | AA19: 0.01 | AB19: 0.01 | AC19: 0.01 | AD19: 0.01 | AE19: 0.01 | AF19: 0.01 | AG19: 0.01 | AH19: 0.1 | AI19: 0.11 | AJ19: 0.12 | AK19: 0.12 | AL19: 0.19 | AM19: 0.32 | AN19: 0.33 | AO19: 0.33 | AP19: 0 | AQ19: 0 | AR19: 0 | AS19: 0 | AT19: 0 | AU19: 0 | AV19: 0 | AW19: 0 | AX19: 0 | AY19: 0 | AZ19: 0 | BA19: 0 | BB19: 0 | BC19: 0 | BD19: 0 | BE19: 0 | BF19: 0 | BG19: 0 | BH19: 0 | BI19: 0 | BJ19: 0 | BK19: 0 | BL19: 0 | BO19: 11.57 | BP19: 11.57 | BQ19: 11,6 | BR19: 12.7 | BS19: 12.75 | BT19: 12.75 | BU19: 12.75 | BV19: 12.75 | BW19: 12.75 | BX19: 12.75 | BY19: 12.79 | BZ19: 13.4 | CA19: 13.4 | CB19: 12.8 | CC19: 12.8 | CD19: 12.8 | CE19: 14.9 | CF19: 14.9 | CG19: 14.9 | CH19: 14.9 | CI19: 14.9 | CJ19: 14.9 | CK19: 14.9 | CL19: 15.5 | CM19: 15.5 | CN19: 15.5 | CO19: 15.5 | CP19: 15.5 | CQ19: 15.5 | CR19: 15.5 | CS19: 15.5
E20: X86-ORACLE-RAC-WC-UAT | I20: 0.12 | J20: 0.128 | K20: 0.138 | L20: 0.15 | M20: 0.02 | N20: 0.05 | O20: 0.0485 | P20: 0.05 | Q20: 0.05 | R20: 0.05 | S20: 0.05 | T20: 0.053 | U20: 0.05 | V20: 0.06 | W20: 0.06 | X20: 0.06 | Y20: 0.06 | Z20: 0.004 | AA20: 0.01 | AB20: 0.01 | AC20: 0.01 | AD20: 0.01 | AE20: 0.01 | AF20: 0.01 | AG20: 0.01 | AH20: 0.11 | AI20: 0.11 | AJ20: 0.11 | AK20: 0.26 | AL20: 0.29 | AM20: 0.08 | AN20: 0.02 | AO20: 0.03 | AP20: 0 | AQ20: 0 | AR20: 0 | AS20: 0 | AT20: 0 | AU20: 0 | AV20: 0 | AW20: 0 | AX20: 0 | AY20: 0 | AZ20: 0 | BA20: 0 | BB20: 0 | BC20: 0 | BD20: 0 | BE20: 0 | BF20: 0 | BG20: 0 | BH20: 0 | BI20: 0 | BJ20: 0 | BK20: 0 | BL20: 0 | BO20: 11.62 | BP20: 11.62 | BQ20: 11.6 | BR20: 11.6 | BS20: 12.8 | BT20: 12.8 | BU20: 12.8 | BV20: 12.8 | BW20: 12.8 | BX20: 12.8 | BY20: 12.84 | BZ20: 13.4 | CA20: 13.5 | CB20: 12.8 | CC20: 12.8 | CD20: 12.8 | CE20: 14.9 | CF20: 14.9 | CG20: 14.9 | CH20: 14.9 | CI20: 14.9 | CJ20: 14.9 | CK20: 14.9 | CL20: 14.9 | CM20: 14.9 | CN20: 14.9 | CO20: 14.9 | CP20: 14.9 | CQ20: 14.9 | CR20: 14.9 | CS20: 14.9
E22: SHARED | I22: 13.51 | J22: 13.6 | K22: 13.74 | L22: 14.64 | M22: 13.6 | N22: 13.11 | O22: 12.96 | P22: 13.42 | Q22: 13.53 | R22: 14.66 | S22: 14.95 | T22: 15.14 | U22: 14.65 | V22: 15.27 | W22: 15.43 | X22: 15.35 | Y22: 16.08 | Z22: 16.87 | AA22: 16.63 | AB22: 16.94 | AC22: 16.92 | AD22: 17.99 | AE22: 17.42 | AF22: 16.77 | AG22: 17.15 | AH22: 16.27 | AI22: 14.6 | AJ22: 14.59 | AK22: 14.34 | AL22: 14.22 | AM22: 14.82 | AN22: 14.99 | AO22: 15.04 | AP22: 4.31 | AQ22: 4.21 | AR22: 4.23 | AS22: 4.24 | AT22: 3.62 | AU22: 3.62 | AV22: 4.01 | AW22: 3.62 | AX22: 3.6 | AY22: 3.59 | AZ22: 3.39 | BA22: 3.54 | BB22: 3.39 | BC22: 3.54 | BD22: 3.23 | BE22: 3.67 | BF22: 3.6 | BG22: 3.08 | BH22: 3.19 | BI22: 2.87 | BJ22: 2.87 | BK22: 2.7 | BL22: 4.1
E23: SNAPSHOTS | I23: 0.52 | J23: 0.395 | K23: 0.405 | L23: 0.41 | M23: 0.37 | N23: 0.03 | O23: 0.031 | P23: 0.01 | Q23: 0.03 | R23: 0.04 | S23: 0.04 | T23: 0.043 | U23: 0.05 | V23: 0.05 | W23: 0.05 | X23: 0.08 | Y23: 0.08 | Z23: 0.09 | AA23: 0.12 | AB23: 0.12 | AC23: 0.13 | AD23: 0.02 | AE23: 0.02 | AF23: 0.02 | AG23: 0.02 | AH23: 0.02 | AI23: 0.02 | AJ23: 0.02 | AK23: 0.05 | AL23: 0.06 | AM23: 0.08 | AN23: 0.09 | AO23: 0.09 | AP23: 0.02 | AQ23: 0.2 | AR23: 0.03 | AS23: 0.03 | AT23: 0.03 | AU23: 0.03 | AV23: 0.03 | AW23: 0.03 | AX23: 0.03 | AY23: 0.14 | AZ23: 0.01 | BA23: 0.01 | BB23: 0.01 | BC23: 0.01 | BD23: 0.01 | BE23: 0.01 | BF23: 0.01 | BG23: 0.01 | BH23: 0.01 | BI23: 0.01 | BJ23: 0.01 | BK23: 0.01 | BL23: 0.01
E24: TOTAL IN-USE | I24: =SUM(I10:I23) -> 44.746 | J24: =SUM(J10:J23) -> 40.285 | K24: =SUM(K10:K23) -> 42.108 | L24: =SUM(L10:L23) -> 42.21 | M24: =SUM(M10:M23) -> 27.61 | N24: =SUM(N10:N23) -> 28.08 | O24: =SUM(O10:O23) -> 27.521 | P24: =SUM(P10:P23) -> 27.86 | ... BL24: =SUM(BL10:BL23) -> 32.89 | CE24: Story:
E25: TOTAL AVAILABLE | G25: 51.39 | I25: =49.13-I24 -> 4.384 | J25: =49.13-J24 -> 8.845 | K25: =49.13-K24 -> 7.022 | L25: =49.13-L24 -> 6.92 | M25: =49.13-M24 -> 21.52 | N25: =49.13-N24 -> 21.05 | O25: =49.13-O24 -> 21.609 | P25: =49.13-P24 -> 21.27 | ... R25: =49.13-R24 -> 21.33 | S25: =$G25-S24 -> 22.62 | T25: =$G25-T24 -> 21.9474 | U25: =$G25-U24 -> 22.46 | V25: =$G25-V24 -> 12.29 | W25: =$G25-W24 -> 11.47 | X25: =$G25-X24 -> 9.95 | Y25: =$G25-Y24 -> 18.18 | Z25: =$G25-Z24 -> 18.132 | ... BL25: =$G25-BL24 -> 18.5 | CE25: * Dedup-rate isn't 4.5 due to "shared storage" Excluded. Including shared storage dedup-rate is 2.5
E26: % IN-USE Capacity | I26: =I24/49.13 -> 0.91076735 | J26: =J24/49.13 -> 0.81996743 | K26: =K24/49.13 -> 0.85707307 | L26: =L24/49.13 -> 0.8591492 | M26: =M24/49.13 -> 0.56197842 | N26: =N24/49.13 -> 0.57154488 | O26: =O24/49.13 -> 0.5601669 | P26: =P24/49.13 -> 0.56706697 | ... R26: =R24/49.13 -> 0.56584572 | S26: =S24/$G$25 -> 0.55983654 | T26: =T24/$G$25 -> 0.57292469 | U26: =U24/$G$25 -> 0.56294999 | V26: =V24/$G$25 -> 0.76084841 | W26: =W24/$G$25 -> 0.77680483 | X26: =X24/$G$25 -> 0.80638256 | Y26: =Y24/$G$25 -> 0.64623468 | Z26: =Z24/$G$25 -> 0.64716871 | ... BL26: =BL24/$G$25 -> 0.64000778 | CE26: * Cherwell UniCode - Environment required (CMS - SQL)
CE27: * File-Services growing ==> Read-Only and put new new stuff in TEAMS
B28: MacPark | C28: X50 | D28: ORACLE-T8s | E28: ORACLE-ERPDEV01 | I28: 1.01 | J28: 1.02 | K28: 0.38 | L28: 0.91 | M28: 0.96 | N28: 0.28 | O28: 0.669 | P28: 0.71 | Q28: 0.16 | R28: 0.81 | S28: 0.99 | T28: 1.26 | U28: 1.26 | V28: 1.66 | W28: 1.62 | X28: 0.36 | Y28: 0.64 | Z28: 0.68 | AA28: 0.41 | AB28: 0.84 | AC28: 0.86 | AD28: 0.62 | AE28: 0.6 | AF28: 0.73 | AG28: 0.73 | AH28: 0.46 | AI28: 0.64 | AJ28: 0.43 | AK28: 0.47 | AL28: 0.71 | AM28: 0.99 | AN28: 0.9 | AO28: 1.18 | AP28: 1.34 | AQ28: 1.47 | AR28: 1.57 | AS28: 1.62 | AT28: 1.68 | AU28: 1.68 | AV28: 0.24 | AW28: 0.93 | AX28: 1.07 | AY28: 1.14 | AZ28: 1.17 | BA28: 1.21 | BB28: 0.88 | BC28: 1.02 | BD28: 1.12 | BE28: 1.44 | BF28: 1.51 | BG28: 0.77 | BH28: 0.93 | BI28: 1.11 | BJ28: 1.05 | BK28: 0.75 | BL28: 0.8 | BO28: 14.10411 | BP28: 15.32212 | BQ28: 15.3 | BR28: 14.97 | BS28: 15.48 | BT28: 15.66 | BU28: 15.5 | BV28: 15.54 | BW28: 16.05 | BX28: 16.36 | BY28: 16.57 | BZ28: 17.7 | CA28: 17.7 | CB28: 16.7 | CC28: 17.1 | CD28: 17.2 | CE28: 17.2 | CF28: 17.8 | CG28: 17.8 | CH28: 17.9 | CI28: 18 | CJ28: 18.4 | CK28: 18.4 | CL28: 19 | CM28: 19 | CN28: 19
B29: aum-pc-prd02 | D29: ORACLE-T7s | E29: ORACLE-ERPDR01 | I29: 0.07135 | J29: 0.386 | K29: 0.28 | L29: 0.31 | M29: 0.04 | N29: 0.3 | O29: 0.295 | P29: 0.04 | Q29: 0.29 | R29: 0.33 | S29: 0.27 | T29: 0.108 | U29: 0.61 | V29: 0.14 | W29: 0.29 | X29: 0.28 | Y29: 0.28 | Z29: 0.26 | AA29: 0.36 | AB29: 0.27 | AC29: 0.45 | AD29: 0.4 | AE29: 0.39 | AF29: 0.4 | AG29: 0.3 | AH29: 0.29 | AI29: 0.3 | AJ29: 0.24 | AK29: 0.05 | AL29: 0.41 | AM29: 0.25 | AN29: 0.3 | AO29: 1.18 | AP29: 0.35 | AQ29: 0.34 | AR29: 0.43 | AS29: 0.44 | AT29: 0.06 | AU29: 0.06 | AV29: 0.42 | AW29: 0.32 | AX29: 0.36 | AY29: 0.42 | AZ29: 0.37 | BA29: 0.34 | BB29: 0.08 | BC29: 0.05 | BD29: 0.5 | BE29: 0.17 | BF29: 0.32 | BG29: 0.32 | BH29: 0.52 | BI29: 0.68 | BJ29: 0.27 | BK29: 0.51 | BL29: 0.57 | BO29: 14.97683 | BP29: 15.32339 | BQ29: 15.6 | BR29: 15.6 | BS29: 15.5 | BT29: 15.8 | BU29: 15.76 | BV29: 15.94 | BW29: 16.12 | BX29: 16.34 | BY29: 16.8 | BZ29: 17.8 | CA29: 16.9 | CB29: 17.1 | CC29: 17.4 | CD29: 17.5 | CE29: 17.8 | CF29: 17.9 | CG29: 17.9 | CH29: 18.4 | CI29: 18.4 | CJ29: 18.8 | CK29: 18.8 | CL29: 19.3 | CM29: 19.3 | CN29: 19.8
D30: ORACLE-T8s | E30: ORACLE-ERPEPE01 | I30: 0.06638 | J30: 0.456 | K30: 0.34 | L30: 0.33 | M30: 0.05 | N30: 0.12 | O30: 0.516 | P30: 0.34 | Q30: 0.14 | R30: 0.6 | S30: 0.28 | T30: 0.165 | U30: 1.06 | V30: 0.2 | W30: 0.36 | X30: 0.3 | Y30: 0.36 | Z30: 0.3 | AA30: 0.66 | AB30: 0.57 | AC30: 0.41 | AD30: 0.23 | AE30: 0.41 | AF30: 0.18 | AG30: 0.32 | AH30: 0.34 | AI30: 0.33 | AJ30: 0.44 | AK30: 0.04 | AL30: 1.1 | AM30: 0.46 | AN30: 0.37 | AO30: 0.62 | AP30: 0.79 | AQ30: 0.4 | AR30: 0.43 | AS30: 0.46 | AT30: 0.45 | AU30: 0.45 | AV30: 0.34 | AW30: 0.34 | AX30: 0.42 | AY30: 0.42 | AZ30: 0.43 | BA30: 0.4 | BB30: 0.11 | BC30: 0.54 | BD30: 0.39 | BE30: 0.2 | BF30: 0.31 | BG30: 0.59 | BH30: 0.55 | BI30: 0.57 | BJ30: 0.26 | BK30: 0.43 | BL30: 0.47 | BO30: 14.96425 | BP30: 15.32111 | BQ30: 15.6 | BR30: 15.37 | BS30: 15.49 | BT30: 15.82 | BU30: 15.75 | BV30: 15.93 | BW30: 16.12 | BX30: 16.34 | BY30: 16.8 | BZ30: 17.8 | CA30: 17.9 | CB30: 17.1 | CC30: 17.4 | CD30: 17.5 | CE30: 17.8 | CF30: 17.9 | CG30: 17.9 | CH30: 18.3 | CI30: 18.3 | CJ30: 18.8 | CK30: 18.8 | CL30: 19.3 | CM30: 19.3 | CN30: 19.8
D31: ORACLE-T8s | E31: ORACLE-ERPHRS01 | I31: 0.11458 | J31: 0.466 | K31: 0.788 | L31: 0.7 | M31: 0.76 | N31: 1.05 | O31: 0.631 | P31: 0.67 | Q31: 0.7 | R31: 0.59 | S31: 0.72 | T31: 0.769 | U31: 0.86 | V31: 0.88 | W31: 0.49 | X31: 0.6 | Y31: 0.8 | Z31: 0.86 | AA31: 0.35 | AB31: 0.68 | AC31: 0.72 | AD31: 0.87 | AE31: 0.88 | AF31: 0.99 | AG31: 1.02 | AH31: 1.03 | AI31: 0 | BO31: 14.7137 | BP31: 15.23781 | BQ31: 15.3 | BR31: 15.03 | BS31: 15.03 | BT31: 15.68 | BU31: 15.5 | BV31: 15.5 | BW31: 15.96 | BX31: 15.96 | BY31: 16.14 | BZ31: 16.9 | CA31: 16.9 | CB31: 17.1 | CC31: 17.1 | CD31: 17.1 | CE31: 17.8 | CF31: 17.8 | CG31: 17.8 | CH31: 17.8 | CI31: 17.8 | CJ31: 17.8 | CK31: 17.8 | CL31: 17.8 | CM31: 17.8 | CN31: 17.8
D32: ORACLE-T8s | E32: ORACLE-ERPHRS02 | I32: 0.82088 | J32: 0.796 | K32: 1.13 | L32: 1.2 | M32: 0.48 | N32: 0.54 | O32: 0.506 | P32: 0.8 | Q32: 0.56 | R32: 0.82 | S32: 0.87 | T32: 0.888 | U32: 0.92 | V32: 1 | W32: 1.05 | X32: 0.35 | Y32: 0.74 | Z32: 0.84 | AA32: 1.02 | AB32: 1.05 | AC32: 0.9 | AD32: 1 | AE32: 1.01 | AF32: 1.02 | AG32: 1.04 | AH32: 1.15 | AI32: 1.22 | AJ32: 1.26 | AK32: 1.99 | BO32: 14.94874 | BP32: 14.94903 | BQ32: 14.9 | BR32: 15.32 | BS32: 15.43 | BT32: 15.8 | BU32: 15.63 | BV32: 15.78 | BW32: 15.78 | BX32: 15.78 | BY32: 15.95 | BZ32: 16.7 | CA32: 16.7 | CB32: 15.8 | CC32: 17.2 | CD32: 17.2 | CE32: 17.2 | CF32: 17.2 | CG32: 17.2 | CH32: 18.2 | CI32: 18.2 | CJ32: 18.2 | CK32: 18.2 | CL32: 18.2 | CM32: 18.2 | CN32: 18.2
D33: ORACLE-T8s | E33: ORACLE-ERPPRJ01 | I33: 0.91256 | J33: 0.98 | K33: 1.05 | L33: 1.06 | M33: 0.56 | N33: 0.82 | O33: 0.913 | P33: 0.79 | Q33: 0.91 | R33: 0.94 | S33: 0.96 | T33: 0.72 | U33: 1.05 | V33: 0.59 | W33: 0.92 | X33: 0.98 | Y33: 1.42 | Z33: 0.39 | AA33: 0.68 | AB33: 0.78 | AC33: 0.82 | AD33: 0.96 | AE33: 0.96 | AF33: 0.18 | AG33: 0.55 | AH33: 0.81 | AI33: 0.84 | AJ33: 0.95 | AK33: 0.15 | AL33: 0.2 | AM33: 0.52 | AN33: 0.56 | AO33: 0.62 | AP33: 0.67 | AQ33: 0.74 | AR33: 0.76 | AS33: 0.83 | AT33: 0.86 | AU33: 0.86 | AV33: 1 | AW33: 1.04 | AX33: 0.86 | AY33: 0.95 | AZ33: 1.19 | BA33: 1.24 | BB33: 1.33 | BC33: 0.04 | BD33: 0.75 | BE33: 0.8 | BF33: 0.86 | BG33: 1.1 | BH33: 1.12 | BI33: 0.63 | BJ33: 1.02 | BK33: 2.65 | BL33: 2.73 | BO33: 14.32524 | BP33: 14.32524 | BQ33: 14.3 | BR33: 15.32 | BS33: 15.32 | BT33: 15.66 | BU33: 15.32 | BV33: 15.32 | BW33: 15.32 | BX33: 15.32 | BY33: 16.57 | BZ33: 17.4 | CA33: 17.9 | CB33: 16.9 | CC33: 16.9 | CD33: 16.9 | CE33: 17.7 | CF33: 17.8 | CG33: 17.8 | CH33: 17.8 | CI33: 17.8 | CJ33: 17.8 | CK33: 17.8 | CL33: 18.8 | CM33: 18.8 | CN33: 18.8
D34: ORACLE-T8s | E34: ORACLE-ERPPRJ02 | I34: 0.82765 | J34: 0.861 | K34: 1.06 | L34: 1.08 | M34: 1.98 | N34: 0.71 | O34: 0.817 | P34: 0.05 | Q34: 0.99 | R34: 0.57 | S34: 0.75 | T34: 0.811 | U34: 0.86 | V34: 0.9 | W34: 0.97 | X34: 1.38 | Y34: 0.41 | Z34: 0.52 | AA34: 0.6 | AB34: 0.63 | AC34: 0.66 | AD34: 0.71 | AE34: 1.11 | AF34: 1.17 | AG34: 1.19 | AH34: 1.34 | AI34: 1.58 | AJ34: 1.62 | AK34: 0.14 | AL34: 0.2 | AM34: 0.21 | AN34: 0.56 | AO34: 0.61 | AP34: 0.73 | AQ34: 0.8 | AR34: 0.85 | AS34: 1 | AT34: 1 | AU34: 1 | AV34: 1.07 | AW34: 1.2 | AX34: 2.55 | AY34: 2.58 | AZ34: 2.61 | BA34: 2.61 | BB34: 0 | BC34: 0 | BD34: 0 | BE34: 0 | BF34: 0 | BG34: 0 | BH34: 0 | BI34: 0 | BJ34: 0 | BK34: 0.62 | BL34: 0.88 | BO34: 13.89231 | BP34: 13.8924 | BQ34: 13.8 | BR34: 15.36 | BS34: 15.36 | BT34: 15.7 | BU34: 15.36 | BV34: 12.31 | BW34: 16.01 | BX34: 16.01 | BY34: 16.18 | BZ34: 16.9 | CA34: 16.9 | CB34: 16.1 | CC34: 16 | CD34: 17.5 | CE34: 17.5 | CF34: 17.5 | CG34: 17.5 | CH34: 17.5 | CI34: 17.5 | CJ34: 17.6 | CK34: 17.6 | CL34: 17.7 | CM34: 17.7 | CN34: 17.7 | CO34: 17.7 | CP34: 17.7 | CQ34: 17.8 | CR34: 17.8 | CS34: 17.9
D35: ORACLE-T8s | E35: ORACLE-ERPRES01 (Commvault ERP test lun) | N35: 3.28 | O35: 3.51 | P35: 0.88 | Q35: 0.72 | R35: 0.85 | S35: 0.85 | T35: 0.845 | U35: 0.83 | V35: 0.05 | W35: 0.03 | X35: 0.04 | Y35: 0.04 | Z35: 0.39 | AA35: 0.85 | AB35: 1.61 | AC35: 1.87 | AD35: 0 | AE35: 0 | AF35: 0 | AG35: 0 | AH35: 0 | AI35: 0 | AJ35: 0 | AK35: 0 | AL35: 0 | AM35: 0 | AN35: 0 | AO35: 0 | AP35: 0 | AQ35: 0 | AR35: 0 | AS35: 0 | AT35: 0 | AU35: 0 | AV35: 0 | AW35: 0 | AX35: 0 | AY35: 0 | AZ35: 0 | BA35: 0 | BB35: 0 | BC35: 0 | BD35: 0 | BE35: 0 | BF35: 0 | BG35: 0 | BH35: 0 | BI35: 0 | BJ35: 0 | BK35: 0 | BL35: 0
D36: ORACLE-T8s | E36: ORACLE-ERPRIM01 | I36: 0.12765 | J36: 0.471 | K36: 0.68 | L36: 0.45 | M36: 0.37 | N36: 0.29 | O36: 0.593 | P36: 0.51 | Q36: 0.56 | R36: 0.39 | S36: 0.44 | T36: 0.453 | U36: 0.76 | V36: 0.8 | W36: 0.7 | X36: 0.35 | Y36: 0.37 | Z36: 0.39 | AA36: 0.38 | AB36: 0.41 | AC36: 0.38 | AD36: 0.24 | AE36: 1 | AF36: 0.73 | AG36: 0.8 | AH36: 0.46 | AI36: 0.43 | AJ36: 0.55 | AK36: 0.45 | AL36: 0.61 | AM36: 0.68 | AN36: 0.8 | AO36: 0.36 | AP36: 0.48 | AQ36: 0.49 | AR36: 0.99 | AS36: 1.01 | AT36: 0.92 | AU36: 0.92 | AV36: 0.82 | AW36: 0.68 | AX36: 0.55 | AY36: 0.56 | AZ36: 0.54 | BA36: 0.9 | BB36: 0.97 | BC36: 1.57 | BD36: 0.13 | BE36: 0.54 | BF36: 0.45 | BG36: 0.64 | BH36: 0.71 | BI36: 0.78 | BJ36: 0.74 | BK36: 0.74 | BL36: 1.07 | BO36: 14.81985 | BP36: 15.27437 | BQ36: 15.4 | BR36: 15.26 | BS36: 15.48 | BT36: 15.8 | BU36: 15.7 | BV36: 15.88 | BW36: 16.05 | BX36: 16.24 | BY36: 16.58 | BZ36: 17.7 | CA36: 17.8 | CB36: 17.1 | CC36: 17.4 | CD36: 17.5 | CE36: 17.7 | CF36: 17.9 | CG36: 17.9 | CH36: 18.3 | CI36: 18.3 | CJ36: 18.7 | CK36: 18.7 | CL36: 19.3 | CM36: 19.3 | CN36: 19.5 | CO36: 19.5 | CP36: 19.6 | CQ36: 19.7 | CR36: 19.8 | CS36: 19.8
D37: ORACLE-T8s | E37: ORACLE-ERPRIM02 | M37: 0 | N37: 0.14 | O37: 0.321 | P37: 0.33 | Q37: 0.44 | R37: 0.56 | S37: 0.56 | T37: 0.608 | U37: 0.61 | V37: 0.57 | W37: 0.67 | X37: 0.69 | Y37: 0.47 | Z37: 0.54 | AA37: 0.68 | AB37: 0.69 | AC37: 0.78 | AD37: 0.82 | AE37: 0.83 | AF37: 0.84 | AG37: 0.86 | AH37: 0.46 | AI37: 0.46 | AJ37: 0.38 | AK37: 0.31 | AL37: 0.45 | AM37: 0.57 | AN37: 0.69 | AO37: 0.73 | AP37: 0 | AQ37: 0 | AR37: 0 | AS37: 0 | AT37: 0 | AU37: 0 | AV37: 0 | AW37: 0 | AX37: 0 | AY37: 0 | AZ37: 0 | BA37: 0 | BB37: 0 | BC37: 0 | BD37: 0 | BE37: 0 | BF37: 0 | BG37: 0 | BH37: 0 | BI37: 0 | BJ37: 0 | BK37: 0 | BL37: 0 | BT37: 15.66 | BU37: 15.49 | BV37: 15.49 | BW37: 15.49 | BX37: 15.49 | BY37: 15.66 | BZ37: 16.4 | CA37: 17.8 | CB37: 16.9 | CC37: 16.8 | CD37: 17.4 | CE37: 17.4 | CF37: 17.4 | CG37: 17.4 | CH37: 17.4 | CI37: 17.4 | CJ37: 17.4 | CK37: 17.4 | CL37: 19.2 | CM37: 19.2 | CN37: 19.4 | CO37: 19.5 | CP37: 19.5 | CQ37: 19.5 | CR37: 19.5 | CS37: 19.6
D38: ORACLE-T8s | E38: ORACLE-ERPSBX01 | I38: 0.08015 | J38: 0.458 | K38: 0.45 | L38: 0.35 | M38: 0.35 | N38: 0.36 | O38: 0.393 | P38: 0.4 | Q38: 0.38 | R38: 0.41 | S38: 0.4 | T38: 0.521 | U38: 0.7 | V38: 0.55 | W38: 0.39 | X38: 0.31 | Y38: 0.4 | Z38: 0.39 | AA38: 0.43 | AB38: 0.43 | AC38: 0.42 | AD38: 0.53 | AE38: 0.5 | AF38: 0.54 | AG38: 0.62 | AH38: 0.49 | AI38: 0.4 | AJ38: 0.64 | AK38: 0.37 | AL38: 0.57 | AM38: 1.05 | AN38: 0.43 | AO38: 0.96 | AP38: 0.92 | AQ38: 0.58 | AR38: 0.89 | AS38: 0.89 | AT38: 0.07 | AU38: 0.07 | AV38: 0.2 | AW38: 0.43 | AX38: 0.7 | AY38: 0.52 | AZ38: 0.55 | BA38: 0.58 | BB38: 0.59 | BC38: 0.65 | BD38: 0.15 | BE38: 0.42 | BF38: 0.87 | BG38: 1.39 | BH38: 1.42 | BI38: 1.54 | BJ38: 1.46 | BK38: 1.36 | BL38: 1.38 | BO38: 14.83561 | BP38: 15.30703 | BQ38: 15.4 | BR38: 15.32 | BS38: 15.45 | BT38: 15.78 | BU38: 15.73 | BV38: 15.92 | BW38: 16.07 | BX38: 16.24 | BY38: 16.76 | BZ38: 17.6 | CA38: 17.9 | CB38: 17.1 | CC38: 17.4 | CD38: 17.5 | CE38: 17.7 | CF38: 17.9 | CG38: 17.9 | CH38: 17.9 | CI38: 17.9 | CJ38: 18.7 | CK38: 18.7 | CL38: 19.2 | CM38: 19.2 | CN38: 19.6 | CO38: 19.6 | CP38: 19.6 | CQ38: 19.6 | CR38: 19.6 | CS38: 19.6
D39: ORACLE-T8s | E39: ORACLE-ERPTST01 | AL39: 0 | AM39: 0.16 | AN39: 0.18 | AO39: 0.61 | AP39: 1.03 | AQ39: 0.71 | AR39: 0.78 | AS39: 1.03 | AT39: 1.31 | AU39: 1.31 | AV39: 0.35 | AW39: 0.74 | AX39: 0.83 | AY39: 0.89 | AZ39: 0.93 | BA39: 0.94 | BB39: 1.17 | BC39: 1.22 | BD39: 0 | BE39: 0 | BF39: 0 | BG39: 0 | BH39: 0 | BI39: 0 | BJ39: 0 | BK39: 0 | BL39: 0
D40: ORACLE-T8s | E40: ORACLE-ERPUAT01 | AW40: 0.7 | AX40: 0.83 | AY40: 0.56 | AZ40: 0.66 | BA40: 0.73 | BB40: 0.76 | BC40: 0.9 | BD40: 1.43 | BE40: 1 | BF40: 1.43 | BG40: 1.61 | BH40: 1.66 | BI40: 1.72 | BJ40: 1.63 | BK40: 1.52 | BL40: 1.55
D41: ORACLE-T8s | E41: ORACLE-NON-ERP-DEV | I41: 3.62 | J41: 3.79 | K41: 3.89 | L41: 3.93 | M41: 3.98 | N41: 3.99 | O41: 4.14 | P41: 2.67 | Q41: 2.54 | R41: 2.58 | S41: 2.39 | T41: 3.08 | U41: 4.24 | V41: 3.61 | W41: 2.86 | X41: 2.93 | Y41: 3.02 | Z41: 3.04 | AA41: 3.09 | AB41: 3.03 | AC41: 3.03 | AD41: 2.95 | AE41: 2.91 | AF41: 2.91 | AG41: 2.91 | AH41: 2.93 | AI41: 2.91 | AJ41: 2.93 | AK41: 3.03 | AL41: 2.48 | AM41: 2.52 | AN41: 2.53 | AO41: 2.22 | AP41: 2.16 | AQ41: 2.21 | AR41: 2.23 | AS41: 2.18 | AT41: 2.19 | AU41: 2.19 | AV41: 2.15 | AW41: 2.16 | AX41: 2.16 | AY41: 2.17 | AZ41: 2.16 | BA41: 2.14 | BB41: 2.15 | BC41: 2.11 | BD41: 2.1 | BE41: 2.1 | BF41: 2.08 | BG41: 2.05 | BH41: 2.04 | BI41: 2.03 | BJ41: 1.69 | BK41: 1.71 | BL41: 1.71 | BO41: 8.1 | BP41: 7.8 | BQ41: 7.8 | BR41: 7.8 | BS41: 7.8 | BT41: 8.4 | BU41: 8.4 | BV41: 8.4 | BW41: 8.14 | BX41: 8.14 | BY41: 9.99 | BZ41: 10.1 | CA41: 10.1 | CB41: 7.9 | CC41: 7.9 | CD41: 7.9 | CE41: 12.2 | CF41: 12.2 | CG41: 12.2 | CH41: 12.2 | CI41: 12.2 | CJ41: 7.9 | CK41: 7.9 | CL41: 7.9 | CM41: 7.9 | CN41: 7.9 | CO41: 7.9 | CP41: 7.9 | CQ41: 7.9 | CR41: 7.9 | CS41: 7.9
D42: ORACLE-T7s | E42: ORACLE-NON-ERP-DR01 | I42: 0.30237 | J42: 0.274 | K42: 0.29 | L42: 0.29 | M42: 0.28 | N42: 0.3 | O42: 0.292 | P42: 0.27 | Q42: 0.26 | R42: 0.26 | S42: 0.26 | T42: 0.306 | U42: 0.32 | V42: 0.29 | W42: 0.26 | X42: 0.27 | Y42: 0.29 | Z42: 0.29 | AA42: 0.3 | AB42: 0.3 | AC42: 0.3 | AD42: 0.3 | AE42: 0.3 | AF42: 0.3 | AG42: 0.3 | AH42: 0.3 | AI42: 0.31 | AJ42: 0.3 | AK42: 0.32 | AL42: 0.33 | AM42: 0.3 | AN42: 0.32 | AO42: 0.3 | AP42: 0.3 | AQ42: 0.31 | AR42: 0.32 | AS42: 0.34 | AT42: 0.33 | AU42: 0.33 | AV42: 0.32 | AW42: 0.31 | AX42: 0.31 | AY42: 0.31 | AZ42: 0.31 | BA42: 0.32 | BB42: 0.31 | BC42: 0.31 | BD42: 0.29 | BE42: 0.28 | BF42: 0.29 | BG42: 0.32 | BH42: 0.38 | BI42: 0.39 | BJ42: 0.35 | BK42: 0.32 | BL42: 0.31 | BO42: 4.7 | BP42: 4.7 | BQ42: 4.7 | BR42: 4.7 | BS42: 4.87 | BT42: 0.31 | BU42: 0.3 | BV42: 0.3 | BW42: 0.3 | BX42: 0.3 | BY42: 0.3 | BZ42: 0.5 | CA42: 0.3 | CB42: 0.5 | CC42: 0.3 | CD42: 0.2 | CE42: 0.2 | CF42: 0.2 | CG42: 0.2 | CH42: 0.2 | CI42: 0.2 | CJ42: 0.2 | CK42: 0.2 | CL42: 0.2 | CM42: 0.2 | CN42: 0.2 | CO42: 0.2 | CP42: 0.2 | CQ42: 0.2 | CR42: 0.2 | CS42: 0.2
D43: ORACLE-T7s | E43: ORACLE-NON-ERP-DR02 | I43: 1.93 | J43: 2.04 | K43: 2.22 | L43: 2.25 | M43: 2.34 | N43: 2.35 | O43: 1.96 | P43: 1.33 | Q43: 1.31 | R43: 1.28 | S43: 1.31 | T43: 1.33 | U43: 2.4 | V43: 1.92 | W43: 1.69 | X43: 1.73 | Y43: 1.81 | Z43: 1.34 | AA43: 1.36 | AB43: 1.37 | AC43: 0.95 | AD43: 2.03 | AE43: 2.03 | AF43: 2.03 | AG43: 2.03 | AH43: 2.06 | AI43: 2.06 | AJ43: 2.07 | AK43: 2 | AL43: 1.65 | AM43: 1.6 | AN43: 1.6 | AO43: 1.69 | AP43: 1.61 | AQ43: 1.72 | AR43: 1.78 | AS43: 1.83 | AT43: 1.86 | AU43: 1.86 | AV43: 1.82 | AW43: 1.87 | AX43: 1.9 | AY43: 1.91 | AZ43: 1.91 | BA43: 1.92 | BB43: 1.94 | BC43: 1.95 | BD43: 1.98 | BE43: 2 | BF43: 2 | BG43: 2 | BH43: 2 | BI43: 2.02 | BJ43: 1.73 | BK43: 1.65 | BL43: 1.64 | BO43: 4.7 | BP43: 4.7 | BQ43: 4.7 | BR43: 4.7 | BS43: 4.9 | BT43: 1.6 | BU43: 1.6 | BV43: 1.6 | BW43: 1.6 | BX43: 1.6 | BY43: 1.73 | BZ43: 1.8 | CA43: 1.9 | CB43: 1.9 | CC43: 1.8 | CD43: 1.9 | CE43: 1.9 | CF43: 1.9 | CG43: 1.9 | CH43: 2 | CI43: 2 | CJ43: 2 | CK43: 2 | CL43: 2.1 | CM43: 2.1 | CN43: 2.1 | CO43: 2.1 | CP43: 2.1 | CQ43: 2.1 | CR43: 2.1 | CS43: 2.1
D44: ORACLE-T7s | E44: ORACLE-T74-OS-APP | J44: 0.716 | K44: 0.75 | L44: 0.77 | M44: 0.79 | N44: 0.74 | O44: 0.765 | P44: 0.63 | Q44: 0.65 | R44: 0.67 | S44: 0.69 | T44: 0.707 | U44: 0.71 | V44: 0.74 | W44: 0.73 | X44: 0.75 | Y44: 0.78 | Z44: 0.78 | AA44: 0.8 | AB44: 0.8 | AC44: 0.82 | AD44: 0.81 | AE44: 0.82 | AF44: 0.82 | AG44: 0.83 | AH44: 0.84 | AI44: 0.85 | AJ44: 0.86 | AK44: 0.87 | AL44: 0.88 | AM44: 0.86 | AN44: 0.86 | AO44: 0.88 | AP44: 0.86 | AQ44: 0.87 | AR44: 0.88 | AS44: 0.88 | AT44: 0.89 | AU44: 0.89 | AV44: 0.85 | AW44: 0.85 | AX44: 0.86 | AY44: 0.86 | AZ44: 0.86 | BA44: 0.86 | BB44: 0.86 | BC44: 0.87 | BD44: 0.87 | BE44: 0.88 | BF44: 0.88 | BG44: 0.87 | BH44: 0.87 | BI44: 0.87 | BJ44: 0.74 | BK44: 0.69 | BL44: 0.68 | BO44: 7.4 | BP44: 7.4 | BV44: 7.3 | BW44: 7.3 | BX44: 7.3 | BY44: 7.3
D45: ORACLE-T7s | E45: ORACLE-T84-OS-APP | I45: 0.52773 | J45: 0.524 | K45: 0.541 | L45: 0.55 | M45: 0.57 | N45: 0.74 | O45: 0.799 | P45: 0.71 | Q45: 0.7 | R45: 0.71 | S45: 0.7 | T45: 0.782 | U45: 0.81 | V45: 0.82 | W45: 0.7 | X45: 0.72 | Y45: 0.76 | Z45: 1.13 | AA45: 1.29 | AB45: 1.37 | AC45: 1.4 | AD45: 1.44 | AE45: 1.46 | AF45: 1.43 | AG45: 1.51 | AH45: 1.54 | AI45: 1.58 | AJ45: 1.63 | AK45: 1.68 | AL45: 1.78 | AM45: 1.73 | AN45: 1.7 | AO45: 1.69 | AP45: 1.65 | AQ45: 1.66 | AR45: 1.65 | AS45: 1.65 | AT45: 1.66 | AU45: 1.66 | AV45: 1.57 | AW45: 1.53 | AX45: 1.52 | AY45: 1.53 | AZ45: 1.51 | BA45: 1.46 | BB45: 1.48 | BC45: 1.52 | BD45: 1.55 | BE45: 1.55 | BF45: 1.51 | BG45: 1.52 | BH45: 1.48 | BI45: 1.5 | BJ45: 1.24 | BK45: 1.13 | BL45: 1.12 | BO45: 5.7 | BP45: 5.7 | BV45: 5.7 | BW45: 5.7 | BX45: 5.7 | BY45: 5.7
D46: CISCO-FlashStack (VMware) | E46: VMWare - FILESERVERS | I46: 8.56 | J46: 8.43 | K46: 15.09 | L46: 15.36 | M46: 15.3 | N46: 14.5 | O46: 15.69 | P46: 3.6 | Q46: 4.32 | R46: 5.55 | S46: 6.81 | T46: 19.65 | U46: 17.94 | V46: 24.06 | W46: 23.97 | X46: 23.87 | Y46: 24.95 | Z46: 25.1 | AA46: 25.52 | AB46: 25.6 | AC46: 26.51 | AD46: 26.69 | AE46: 26.93 | AF46: 26.35 | AG46: 26.79 | AH46: 27.63 | AI46: 32.27 | AJ46: 32.79 | AK46: 33.24 | AL46: 24.13 | AM46: 23.68 | AN46: 23.84 | AO46: 23.56 | AP46: 23.8 | AQ46: 24.43 | AR46: 25.72 | AS46: 25.38 | AT46: 25.62 | AU46: 25.62 | AV46: 19.59 | AW46: 19.76 | AX46: 19.93 | AY46: 19.98 | AZ46: 20.16 | BA46: 20.26 | BB46: 20.35 | BC46: 20.87 | BD46: 21.21 | BE46: 21.46 | BF46: 21.66 | BG46: 21.7 | BH46: 21.84 | BI46: 18.71 | BJ46: 0 | BK46: 0 | BL46: 0
E47: Vmware - RDM | AL47: 0 | AM47: 0 | AN47: 0 | AO47: 0 | AP47: 0 | AQ47: 0 | AR47: 0 | AS47: 0 | AT47: 0 | AU47: 0 | AV47: 0 | AW47: 0 | AX47: 0 | AY47: 0 | AZ47: 0 | BA47: 0 | BB47: 0 | BC47: 0.02 | BD47: 0 | BE47: 0.04 | BF47: 0.05 | BG47: 0.4 | BH47: 0.4 | BI47: 0.41 | BJ47: 0.04 | BK47: 0.03 | BL47: 0.03
E48: VMware - SRM | I48: 0.001 | J48: 0.049 | K48: 0.012 | L48: 0.04 | M48: 0.07 | N48: 0.08 | O48: 0.081 | P48: 0.06 | Q48: 0.06 | R48: 0.2 | S48: 0.21 | T48: 0.201 | U48: 0.19 | V48: 0.24 | W48: 0.24 | X48: 0.24 | Y48: 0.34 | Z48: 0.58 | AA48: 0.6 | AB48: 0.61 | AC48: 0.51 | AD48: 0.55 | AE48: 0.55 | AF48: 0.66 | AG48: 0.67 | AH48: 0.68 | AI48: 0.69 | AJ48: 0.7 | AK48: 0.72 | AL48: 0.83 | AM48: 0.6 | AN48: 0.71 | AO48: 0.72 | AP48: 0.79 | AQ48: 0.82 | AR48: 0.77 | AS48: 2.77 | AT48: 0.84 | AU48: 0.84 | AV48: 0.6 | AW48: 0.67 | AX48: 0.48 | AY48: 0.49 | AZ48: 0.49 | BA48: 0.49 | BB48: 0.47 | BC48: 0.77 | BD48: 0.56 | BE48: 0.62 | BF48: 0.39 | BG48: 0.66 | BH48: 0.49 | BI48: 0.49 | BJ48: 0.55 | BK48: 0.52 | BL48: 0.52
E49: VMWare - VMFS | I49: 22.45 | J49: 22.36 | K49: 22.79 | L49: 22.97 | M49: 22.62 | N49: 16.19 | O49: 16.22 | P49: 13.83 | Q49: 11.1 | R49: 9.06 | S49: 8.18 | T49: 8.11 | U49: 7.71 | V49: 0.63 | W49: 0.61 | X49: 0.61 | Y49: 0.63 | Z49: 0.62 | AA49: 0.63 | AB49: 0.63 | AC49: 0.67 | AD49: 0.5 | AE49: 0.47 | AF49: 0.47 | AG49: 0.47 | AH49: 0.47 | AI49: 0.47 | AJ49: 0.47 | AK49: 0.47 | AL49: 0.03 | AM49: 0.01 | AN49: 0.01 | AO49: 0.01 | AP49: 0.01 | AQ49: 0.01 | AR49: 0.01 | AS49: 0.01 | AT49: 0.02 | AU49: 0.02 | AV49: 0.02 | AW49: 0.02 | AX49: 0.02 | AY49: 0.03 | AZ49: 0.03 | BA49: 0.03 | BB49: 0.03 | BC49: 0.03 | BD49: 0.03 | BE49: 0.03 | BF49: 0.03 | BG49: 0.03 | BH49: 0.03 | BI49: 0.03 | BJ49: 0.56 | BK49: 0.13 | BL49: 0.13
D50: X50 | E50: DIRECT-FILESYSTEM (Software share + tests) | I50: 0.6875 | J50: 0.735 | K50: 0.75 | L50: 0.79 | M50: 0.83 | N50: 0.85 | O50: 0.87 | P50: 0.7 | Q50: 0.71 | R50: 0.74 | S50: 0.76 | T50: 0.784 | U50: 0.83 | V50: 0.9 | W50: 0.91 | X50: 0.92 | Y50: 0.94 | Z50: 0.94 | AA50: 0.96 | AB50: 0.96 | AC50: 0.96 | AD50: 0.98 | AE50: 0.98 | AF50: 0.98 | AG50: 0.36 | AH50: 0.36 | AI50: 0 | AJ50: 0 | AK50: 0 | AL50: 0 | AM50: 0 | AN50: 0 | AO50: 0 | AP50: 0 | AQ50: 0 | AR50: 0 | AS50: 0 | AT50: 0 | AU50: 0 | AV50: 0 | AW50: 0 | AX50: 0 | AY50: 0 | AZ50: 0 | BA50: 0 | BB50: 0 | BC50: 0 | BD50: 0 | BE50: 0 | BF50: 0 | BG50: 0 | BH50: 0 | BI50: 0 | BJ50: 0 | BK50: 0 | BL50: 0
E52: SHARED | I52: 14.68 | J52: 13.92 | K52: 15.44 | L52: 15.72 | M52: 16.03 | N52: 15.84 | O52: 16.19 | P52: 16.97 | Q52: 20.76 | R52: 22.44 | S52: 24.1 | T52: 25.87 | U52: 27.28 | V52: 20.36 | W52: 18.78 | X52: 19.26 | Y52: 19.39 | Z52: 20.27 | AA52: 20.26 | AB52: 20.15 | AC52: 20.84 | AD52: 20 | AE52: 20.42 | AF52: 20.48 | AG52: 21.03 | AH52: 21.43 | AI52: 16.25 | AJ52: 16.33 | AK52: 16.31 | AL52: 23 | AM52: 22.17 | AN52: 22 | AO52: 22.93 | AP52: 23.49 | AQ52: 24.04 | AR52: 24.94 | AS52: 24.86 | AT52: 26.52 | AU52: 26.52 | AV52: 25.28 | AW52: 26.05 | AX52: 23.7 | AY52: 23.15 | AZ52: 23.17 | BA52: 25.31 | BB52: 25.91 | BC52: 26.51 | BD52: 28.03 | BE52: 27.84 | BF52: 28 | BG52: 28.53 | BH52: 27.41 | BI52: 31.79 | BJ52: 25.36 | BK52: 23.73 | BL52: 24.06
E53: SNAPSHOTS | I53: 2.2 | J53: 1.54 | K53: 2.24 | L53: 1.69 | M53: 2.15 | N53: 1.7 | O53: 1.67 | P53: 2.01 | Q53: 1.1 | R53: 1.28 | S53: 1.4 | T53: 2.45 | U53: 1.22 | V53: 1.82 | W53: 1.33 | X53: 1.25 | Y53: 0.94 | Z53: 0.86 | AA53: 0.93 | AB53: 0.87 | AC53: 0.84 | AD53: 0.93 | AE53: 0.97 | AF53: 0.97 | AG53: 1.01 | AH53: 1.1 | AI53: 1.47 | AJ53: 1.52 | AK53: 1.83 | AL53: 1.32 | AM53: 0.95 | AN53: 1.26 | AO53: 1.47 | AP53: 1.54 | AQ53: 1.22 | AR53: 1.06 | AS53: 1.92 | AT53: 2.66 | AU53: 2.66 | AV53: 2.76 | AW53: 3.02 | AX53: 4.13 | AY53: 4.07 | AZ53: 4.33 | BA53: 2.86 | BB53: 4.06 | BC53: 4.58 | BD53: 1.45 | BE53: 2.25 | BF53: 2.2 | BG53: 2.09 | BH53: 2.03 | BI53: 2.22 | BJ53: 2.22 | BK53: 2.44 | BL53: 2.28
E54: TOTAL IN-USE | I54: =SUM(I28:I53) -> 58.9898 | J54: =SUM(J28:J53) -> 60.272 | K54: =SUM(K28:K53) -> 70.171 | L54: =SUM(L28:L53) -> 70.75 | M54: =SUM(M28:M53) -> 70.51 | N54: =SUM(N28:N53) -> 65.17 | O54: =SUM(O28:O53) -> 67.841 | P54: =SUM(P28:P53) -> 48.3 | ... BL54: =SUM(BL28:BL53) -> 41.93 | BZ54: =BN54*D1 -> 0
E55: TOTAL AVAILABLE | G55: 79.11 | I55: =G55-I54 -> 20.1202 | J55: =$G$55-J54 -> 18.838 | K55: =$G$55-K54 -> 8.939 | L55: =$G$55-L54 -> 8.36 | M55: =$G$55-M54 -> 8.6 | N55: =$G$55-N54 -> 13.94 | O55: =$G$55-O54 -> 11.269 | P55: =$G$55-P54 -> 30.81 | Q55: =$G$55-Q54 -> 29.75 | ... BL55: =$G$55-BL54 -> 37.18
E56: % IN-USE Capacity | I56: =I54/$G$55 -> 0.74566806 | J56: =J54/$G$55 -> 0.76187587 | K56: =K54/$G$55 -> 0.88700544 | L56: =L54/$G$55 -> 0.89432436 | M56: =M54/$G$55 -> 0.89129061 | N56: =N54/$G$55 -> 0.82378966 | O56: =O54/$G$55 -> 0.85755277 | P56: =P54/$G$55 -> 0.61054228 | ... BL56: =BL54/$G$55 -> 0.53002149
B58: MacPark (old NR) | C58: M20 | D58: CISCO-FlashStack (VMWare) | E58: Vmware - FILESERVER | AL58: 15.1 | AM58: 15.44 | AN58: 15.45 | AO58: 15.49 | AP58: 15.61 | AQ58: 15.66 | AR58: 15.79 | AS58: 15.95 | AT58: 15.93 | AU58: 15.93 | AV58: 15.91 | AW58: 15.92 | AX58: 15.96 | AY58: 15.98 | AZ58: 16.01 | BA58: 16.08 | BB58: 16.12 | BC58: 16.13 | BD58: 16.16 | BE58: 16.14 | BF58: 16.16 | BG58: 16.17 | BH58: 15.83 | BI58: 15.83 | BJ58: 0 | BK58: 0 | BL58: 0
B59: aum-pc-prd03 | E59: VMWare - SQL - RDM | I59: 0.27332 | J59: 0.291 | K59: 0.29 | L59: 0 | M59: 0 | N59: 0 | O59: 0 | P59: 0 | Q59: 0 | R59: 0 | S59: 0 | T59: 0 | U59: 0 | V59: 0 | W59: 0 | X59: 0 | Y59: 0 | Z59: 0 | AA59: 0 | AB59: 0 | AC59: 0 | AD59: 0.1 | AE59: 0.01 | AF59: 7.77 | AG59: =8.09 -> 8.09 | AH59: 0 | AI59: 0 | AJ59: 0 | AK59: 0.01 | AL59: 0.01 | AM59: 0.01 | AN59: 0.01 | AO59: 0.01 | AP59: 0.01 | AQ59: 0.01 | AR59: 0.02 | AS59: 0.02 | AT59: 0.02 | AU59: 0.02 | AV59: 0.02 | AW59: 0.02 | AX59: 0.21 | AY59: 0.21 | AZ59: 0.21 | BA59: 0.21 | BB59: 0.2 | BC59: 0.24 | BD59: 0.25 | BE59: 0.24 | BF59: 0.24 | BG59: 0.24 | BH59: 0.24 | BI59: 0.25 | BJ59: 0.2 | BK59: 0.2 | BL59: 0.21
B60: Moved to MacPark in April | E60: VMware - SRM | I60: 1.14 | J60: 1.01 | K60: 0.73 | L60: 0 | M60: 0 | N60: 0 | O60: 0 | P60: 0 | Q60: 0 | R60: 0 | S60: 0 | T60: 0 | U60: 0 | V60: 0 | W60: 0 | X60: 0 | Y60: 0 | Z60: 0 | AA60: 0 | AB60: 0 | AC60: 0 | AD60: 0 | AE60: 0 | AF60: 0 | AG60: 0 | AH60: 0 | AI60: 0 | AJ60: 0 | AK60: 0 | AL60: 0 | AM60: 0 | AN60: 0 | AO60: 0 | AP60: 0 | AQ60: 0 | AR60: 0 | AS60: 0 | AT60: 0 | AU60: 0 | AV60: 0 | AW60: 0 | AX60: 0 | AY60: 0 | AZ60: 0 | BA60: 0 | BB60: 0 | BC60: 0 | BD60: 0 | BE60: 0 | BF60: 0 | BG60: 0 | BH60: 0 | BI60: 0 | BJ60: 0 | BK60: 0 | BL60: 0
E61: VMware - VMFS | I61: 2.6 | J61: 2.51 | K61: 2.76 | L61: 0 | M61: 7.53 | N61: 14.92 | O61: 14.3 | P61: 14.12 | Q61: 14.07 | R61: 14.13 | S61: 14.05 | T61: 14.13 | U61: 15.7 | V61: 25.03 | W61: 25.64 | X61: 26.07 | Y61: 15.33 | Z61: 14.37 | AA61: 14.44 | AB61: 13.67 | AC61: 13.8 | AD61: 14.09 | AE61: 14.84 | AF61: 14.29 | AG61: 14.4 | AH61: 13.63 | AI61: 13.73 | AJ61: 13.75 | AK61: 13.78 | AL61: 2.59 | AM61: 3.58 | AN61: 3.89 | AO61: 3.88 | AP61: 3.11 | AQ61: 4.16 | AR61: 4.29 | AS61: 3.97 | AT61: 3.09 | AU61: 3.09 | AV61: 3.77 | AW61: 4.61 | AX61: 4.02 | AY61: 4.34 | AZ61: 4.06 | BA61: 4.08 | BB61: 4.06 | BC61: 4.3 | BD61: 4.29 | BE61: 3.56 | BF61: 3.5 | BG61: 3.55 | BH61: 3.53 | BI61: 3.36 | BJ61: 3.43 | BK61: 3.4 | BL61: 3.61
D62: CISCO-FlashStack (X86 RAC) | E62: X86-ORACLE-RAC-NWC-PRD | I62: 0.2269 | J62: 0.229 | K62: 0.23 | L62: 0 | M62: 0 | N62: 0 | O62: 0 | P62: 0 | Q62: 0 | R62: 0 | S62: 0 | T62: 0 | U62: 0 | V62: 0 | W62: 0 | X62: 0 | Y62: 0 | Z62: 0 | AA62: 0 | AB62: 0 | AC62: 0 | AD62: 0 | AE62: 0 | AF62: 0 | AG62: 0 | AH62: 0 | AI62: 0 | AJ62: 0 | AK62: 0 | AL62: 0 | AM62: 0 | AN62: 0 | AO62: 0 | AP62: 0 | AQ62: 0 | AR62: 0 | AS62: 0 | AT62: 0 | AU62: 0 | AV62: 0 | AW62: 0 | AX62: 0 | AY62: 0 | AZ62: 0 | BA62: 0 | BB62: 0 | BC62: 0 | BD62: 0 | BE62: 0 | BF62: 0 | BG62: 0 | BH62: 0 | BI62: 0 | BJ62: 0 | BK62: 0 | BL62: 0
E63: X86-ORACLE-RAC-OS-APP-PRD | I63: 0.23863 | J63: 0.245 | K63: 0.19 | L63: 0 | M63: 0 | N63: 0 | O63: 0 | P63: 0 | Q63: 0 | R63: 0 | S63: 0 | T63: 0 | U63: 0 | V63: 0 | W63: 0 | X63: 0 | Y63: 0 | Z63: 0 | AA63: 0 | AB63: 0 | AC63: 0 | AD63: 0 | AE63: 0 | AF63: 0 | AG63: 0 | AH63: 0 | AI63: 0 | AJ63: 0 | AK63: 0 | AL63: 0 | AM63: 0 | AN63: 0 | AO63: 0 | AP63: 0 | AQ63: 0 | AR63: 0 | AS63: 0 | AT63: 0 | AU63: 0 | AV63: 0 | AW63: 0 | AX63: 0 | AY63: 0 | AZ63: 0 | BA63: 0 | BB63: 0 | BC63: 0 | BD63: 0 | BE63: 0 | BF63: 0 | BG63: 0 | BH63: 0 | BI63: 0 | BJ63: 0 | BK63: 0 | BL63: 0
E64: X86-ORACLE-RAC-WC-PRD | I64: 6.98 | J64: 7.05 | K64: 7.05 | L64: 0 | M64: 0 | N64: 0 | O64: 0 | P64: 0 | Q64: 0 | R64: 0 | S64: 0 | T64: 0 | U64: 0 | V64: 0 | W64: 0 | X64: 0 | Y64: 0 | Z64: 0 | AA64: 0 | AB64: 0 | AC64: 0 | AD64: 0 | AE64: 0 | AF64: 0 | AG64: 0 | AH64: 0 | AI64: 0 | AJ64: 0 | AK64: 0 | AL64: 0 | AM64: 0 | AN64: 0 | AO64: 0 | AP64: 0 | AQ64: 0 | AR64: 0 | AS64: 0 | AT64: 0 | AU64: 0 | AV64: 0 | AW64: 0 | AX64: 0 | AY64: 0 | AZ64: 0 | BA64: 0 | BB64: 0 | BC64: 0 | BD64: 0 | BE64: 0 | BF64: 0 | BG64: 0 | BH64: 0 | BI64: 0 | BJ64: 0 | BK64: 0 | BL64: 0
E66: SHARED | I66: 3.66 | J66: 3.64 | K66: 3.85 | L66: 0 | M66: 5.47 | N66: 2.37 | O66: 1.89 | P66: 1.97 | Q66: 1.97 | R66: 1.89 | S66: 1.93 | T66: 1.9 | U66: 2 | V66: 2.04 | W66: 1.16 | X66: 1.28 | Y66: 1.1 | Z66: 1.13 | AA66: 1.2 | AB66: 1.2 | AC66: 1.22 | AD66: 1.21 | AE66: 2 | AF66: 1.97 | AG66: 2.01 | AH66: 9.92 | AI66: 10.03 | AJ66: 10.17 | AK66: 10 | AL66: 9.65 | AM66: 9.54 | AN66: 9.52 | AO66: 9.88 | AP66: 10.9 | AQ66: 9.83 | AR66: 9.85 | AS66: 9.78 | AT66: 9.75 | AU66: 9.75 | AV66: 9.7 | AW66: 9.73 | AX66: 9.73 | AY66: 9.7 | AZ66: 9.76 | BA66: 9.69 | BB66: 9.68 | BC66: 9.65 | BD66: 9.66 | BE66: 9.83 | BF66: 9.8 | BG66: 9.8 | BH66: 9.8 | BI66: 9.8 | BJ66: 9.8 | BK66: 9.91 | BL66: 9.9
E67: SNAPSHOTS | I67: 0.92941 | J67: 0.941 | K67: 0.83 | L67: 0 | M67: 0 | N67: 0 | O67: 0 | P67: 0 | Q67: 0 | R67: 0 | S67: 0 | T67: 0 | U67: 0 | V67: 0 | W67: 0 | X67: 0 | Y67: 0 | Z67: 0 | AA67: 0 | AB67: 0 | AC67: 0 | AD67: 0 | AE67: 0 | AF67: 0 | AG67: 0 | AH67: 0 | AI67: 0 | AJ67: 0 | AK67: 0 | AL67: 0 | AM67: 0 | AN67: 0 | AO67: 0 | AP67: 0 | AQ67: 0 | AR67: 0 | AS67: 0 | AT67: 0 | AU67: 0 | AV67: 0 | AW67: 0 | AX67: 0 | AY67: 0 | AZ67: 0 | BA67: 0 | BB67: 0 | BC67: 0 | BD67: 0 | BE67: 0 | BF67: 0 | BG67: 0 | BH67: 0 | BI67: 0.01 | BJ67: 0.01 | BK67: 0.01 | BL67: 0.01
E68: TOTAL IN-USE | I68: =SUM(I59:I67) -> 16.04826 | J68: =SUM(J59:J67) -> 15.916 | K68: =SUM(K59:K67) -> 15.93 | L68: =SUM(L59:L67) -> 0 | M68: =SUM(M59:M67) -> 13 | N68: =SUM(N59:N67) -> 17.29 | O68: =SUM(O59:O67) -> 16.19 | P68: =SUM(P59:P67) -> 16.09 | ... AK68: =SUM(AK59:AK67) -> 23.79 | AL68: =SUM(AL58:AL67) -> 27.35 | AM68: =SUM(AM58:AM67) -> 28.57 | AN68: =SUM(AN58:AN67) -> 28.87 | AO68: =SUM(AO58:AO67) -> 29.26 | AP68: =SUM(AP58:AP67) -> 29.63 | AQ68: =SUM(AQ58:AQ67) -> 29.66 | AR68: =SUM(AR58:AR67) -> 29.95 | AS68: =SUM(AS58:AS67) -> 29.72 | ... BL68: =SUM(BL58:BL67) -> 13.73
E69: TOTAL AVAILABLE | G69: 37.55 | I69: =36.85-I68 -> 20.80174 | J69: =36.85-J68 -> 20.934 | K69: =36.85-K68 -> 20.92 | L69: =36.85-L68 -> 36.85 | M69: =36.85-M68 -> 23.85 | N69: =36.85-N68 -> 19.56 | O69: =36.85-O68 -> 20.66 | P69: =36.85-P68 -> 20.76 | ... R69: =36.85-R68 -> 20.83 | S69: =$G$69-S68 -> 21.57 | T69: =$G$69-T68 -> 21.52 | U69: =$G$69-U68 -> 19.85 | V69: =$G$69-V68 -> 10.48 | W69: =$G$69-W68 -> 10.75 | X69: =$G$69-X68 -> 10.2 | Y69: =$G$69-Y68 -> 21.12 | Z69: =$G$69-Z68 -> 22.05 | ... BL69: =$G$69-BL68 -> 23.82
E70: % IN-USE Capacity | I70: =I68/36.85 -> 0.43550231 | J70: =J68/36.85 -> 0.43191316 | K70: =K68/36.85 -> 0.43229308 | L70: =L68/36.85 -> 0 | M70: =M68/36.85 -> 0.35278155 | N70: =N68/36.85 -> 0.46919946 | O70: =O68/36.85 -> 0.43934871 | P70: =P68/36.85 -> 0.43663501 | ... R70: =R68/36.85 -> 0.43473541 | S70: =S68/$G$69 -> 0.42556591 | T70: =(T68/$G$69) -> 0.42689747 | U70: =(U68/$G$69) -> 0.4713715 | V70: =(V68/$G$69) -> 0.72090546 | W70: =(W68/$G$69) -> 0.71371505 | X70: =(X68/$G$69) -> 0.72836218 | Y70: =(Y68/$G$69) -> 0.43754993 | Z70: =(Z68/$G$69) -> 0.41278296 | AA70: =(AA68/$G$69) -> 0.41651132 | ... BL70: =(BL68/$G$69) -> 0.36564581
B72: MacPark | C72: C40 | D72: CISCO-FlashStack (VMWare) | E72: Vmware - FILESERVER | BJ72: 121.57 | BK72: 121.87 | BL72: 121.09
B73: aum-pc-prd05 | I73: 0.27332 | J73: 0.291 | K73: 0.29 | L73: 0 | M73: 0 | N73: 0 | O73: 0 | P73: 0 | Q73: 0 | R73: 0 | S73: 0
E75: SHARED | I75: 3.66 | J75: 3.64 | K75: 3.85 | L75: 0 | M75: 5.47 | N75: 2.37 | O75: 1.89 | P75: 1.97 | Q75: 1.97 | R75: 1.89 | S75: 1.93 | BJ75: 0 | BK75: 0 | BL75: 0
E76: SNAPSHOTS | I76: 0.92941 | J76: 0.941 | K76: 0.83 | L76: 0 | M76: 0 | N76: 0 | O76: 0 | P76: 0 | Q76: 0 | R76: 0 | S76: 0 | BJ76: 0.89 | BK76: 1.87 | BL76: 1.72
E77: TOTAL IN-USE | I77: =SUM(I73:I76) -> 4.86273 | J77: =SUM(J73:J76) -> 4.872 | K77: =SUM(K73:K76) -> 4.97 | L77: =SUM(L73:L76) -> 0 | M77: =SUM(M73:M76) -> 5.47 | N77: =SUM(N73:N76) -> 2.37 | O77: =SUM(O73:O76) -> 1.89 | P77: =SUM(P73:P76) -> 1.97 | ... S77: =SUM(S73:S76) -> 1.93 | BJ77: =SUM(BJ72:BJ76) -> 122.46 | BK77: =SUM(BK72:BK76) -> 123.74 | BL77: =SUM(BL72:BL76) -> 122.81
E78: TOTAL AVAILABLE | G78: 198 | I78: =36.85-I77 -> 31.98727 | J78: =36.85-J77 -> 31.978 | K78: =36.85-K77 -> 31.88 | L78: =36.85-L77 -> 36.85 | M78: =36.85-M77 -> 31.38 | N78: =36.85-N77 -> 34.48 | O78: =36.85-O77 -> 34.96 | P78: =36.85-P77 -> 34.88 | ... R78: =36.85-R77 -> 34.96 | S78: =$G$69-S77 -> 35.62 | BJ78: =$G$78-BJ77 -> 75.54 | BK78: =$G$78-BK77 -> 74.26 | BL78: =$G$78-BL77 -> 75.19
E79: % IN-USE Capacity | I79: =I77/36.85 -> 0.13196011 | J79: =J77/36.85 -> 0.13221167 | K79: =K77/36.85 -> 0.1348711 | L79: =L77/36.85 -> 0 | M79: =M77/36.85 -> 0.14843962 | N79: =N77/36.85 -> 0.06431479 | O79: =O77/36.85 -> 0.051289009 | P79: =P77/36.85 -> 0.053459973 | ... R79: =R77/36.85 -> 0.051289009 | S79: =S77/$G$69 -> 0.051398136 | BJ79: =(BJ77/$G$78) -> 0.61848485 | BK79: =(BK77/$G$78) -> 0.62494949 | BL79: =(BL77/$G$78) -> 0.62025253
B81: EQUINIX | C81: X20 | D81: CISCO-FlashStack (VMware) | E81: VMWare - RDM | AK81: 0 | AL81: 7.36 | AM81: 0.03 | AN81: 0.08 | AO81: 0.12 | AP81: 0.18 | AQ81: 0.26 | AR81: 0.03 | AS81: 0.08 | AT81: 0.12 | AU81: 0.12 | AV81: 0.31 | AW81: 0.01 | AX81: 0.08 | AY81: 0.14 | AZ81: 0.22 | BA81: 0.32 | BB81: 0.37 | BC81: 0.23 | BD81: 0.25 | BE81: 0.31 | BF81: 0.16 | BG81: 0.18 | BH81: 0.25 | BI81: 0.33 | BJ81: 0.4 | BK81: 0.48 | BL81: 0.54
B82: aus-pc-prd01 | E82: VMWare - SQL - RDM | I82: 0.18419 | J82: 0.757 | K82: 0.7 | L82: 0.72 | M82: 0.74 | N82: 0.68 | O82: 0.851 | P82: 0.85 | Q82: 0.86 | R82: 0.94 | S82: 0.87 | T82: 0.919 | U82: 1 | V82: 0.91 | W82: 1.06 | X82: 1.02 | Y82: 1.05 | Z82: 1.21 | AA82: 1.21 | AB82: 1.26 | AC82: 1.28 | AD82: 1.19 | AE82: 1.18 | AF82: 0.82 | AG82: 1.01 | AH82: 1.05 | AI82: 1.14 | AJ82: 0.93 | AK82: 0.7 | AL82: 0.81 | AM82: 0.74 | AN82: 0.85 | AO82: 0.86 | AP82: 0.89 | AQ82: 1.04 | AR82: 1.01 | AS82: 1.05 | AT82: 1.1 | AU82: 1.1 | AV82: 1.02 | AW82: 0.94 | AX82: 1.02 | AY82: 1.09 | AZ82: 1.17 | BA82: 1.18 | BB82: 1.15 | BC82: 1.15 | BD82: 1.35 | BE82: 1.16 | BF82: 1.15 | BG82: 1.24 | BH82: 1.2 | BI82: 1.18 | BJ82: 1.24 | BK82: 1.27 | BL82: 1.33
E83: VMware - SRM | I83: 0.72158 | J83: 0.782 | K83: 1.75 | L83: 1.45 | M83: 1.5 | N83: 1.47 | O83: 1.58 | P83: 1.6 | Q83: 1.38 | R83: 1.55 | S83: 1.58 | T83: 1.65 | U83: 1.49 | V83: 1.51 | W83: 1.53 | X83: 1.52 | Y83: 1.06 | Z83: 1.05 | AA83: 1.08 | AB83: 1.08 | AC83: 1 | AD83: 1.04 | AE83: 1.14 | AF83: 1.13 | AG83: 1.14 | AH83: 1.22 | AI83: 1.6 | AJ83: 1.77 | AK83: 1.55 | AL83: 1.43 | AM83: 1 | AN83: 1.44 | AO83: 1.71 | AP83: 1.44 | AQ83: 0.95 | AR83: 1.06 | AS83: 1.04 | AT83: 1.4 | AU83: 1.4 | AV83: 1.8 | AW83: 2.1 | AX83: 2.21 | AY83: 2.2 | AZ83: 2.89 | BA83: 2 | BB83: 2.14 | BC83: 2.11 | BD83: 1.34 | BE83: 1.42 | BF83: 1.35 | BG83: 1.49 | BH83: 1.49 | BI83: 1.67 | BJ83: 1.87 | BK83: 1.9 | BL83: 1.85
E84: VMware - VMFS | I84: 3.12 | J84: 3.25 | K84: 1.06 | L84: 1.14 | M84: 1.76 | N84: 1.91 | O84: 1.99 | P84: 2.01 | Q84: 1.94 | R84: 2.13 | S84: 2.06 | T84: 2.08 | U84: 2.27 | V84: 2.25 | W84: 2.28 | X84: 2.47 | Y84: 2.57 | Z84: 2.36 | AA84: 2.47 | AB84: 3.53 | AC84: 5.05 | AD84: 5.37 | AE84: 5.58 | AF84: 5.66 | AG84: 5.42 | AH84: 5.39 | AI84: 5.72 | AJ84: 5.63 | AK84: 5.75 | AL84: 6.55 | AM84: 7.7 | AN84: 7.51 | AO84: 7.57 | AP84: 7.55 | AQ84: 8.08 | AR84: 8 | AS84: 8.5 | AT84: 8.62 | AU84: 8.62 | AV84: 9.07 | AW84: 9.4 | AX84: 9.34 | AY84: 9.93 | AZ84: 10.16 | BA84: 10.1 | BB84: 10.27 | BC84: 10.26 | BD84: 10.17 | BE84: 10.15 | BF84: 9.36 | BG84: 9.61 | BH84: 9.94 | BI84: 10.29 | BJ84: 10.47 | BK84: 10.76 | BL84: 10.33
E85: X86-ORACLE-RAC-NWC-PRD | K85: 0.183 | L85: 0.19 | M85: 0.21 | N85: 0.21 | O85: 0.215 | P85: 0.22 | Q85: 0.22 | R85: 0.23 | S85: 0.23 | T85: 0.227 | U85: 0.23 | V85: 0.22 | W85: 0.23 | X85: 0.23 | Y85: 0.24 | Z85: 0.23 | AA85: 0.24 | AB85: 0.31 | AC85: 0.32 | AD85: 0.33 | AE85: 0.33 | AF85: 0.34 | AG85: 0.33 | AH85: 0.34 | AI85: 0.34 | AJ85: 0.32 | AK85: 0.33 | AL85: 0.34 | AM85: 0.36 | AN85: 0.36 | AO85: 0.35 | AP85: 0.35 | AQ85: 0.35 | AR85: 0.33 | AS85: 0.32 | AT85: 0.34 | AU85: 0.34 | AV85: 0.37 | AW85: 0.37 | AX85: 0.39 | AY85: 0.39 | AZ85: 0.39 | BA85: 0.36 | BB85: 0.38 | BC85: 0.38 | BD85: 0.38 | BE85: 0.38 | BF85: 0.38 | BG85: 0.38 | BH85: 0.38 | BI85: 0.39 | BJ85: 0.39 | BK85: 0.39 | BL85: 0.39 | BO85: 0.4 | BP85: 0.4 | BQ85: 0.4 | BR85: 0.4 | BS85: 0.47 | BT85: 0.45 | BU85: 0.5 | BV85: 0.48 | BW85: 0.48 | BX85: 0.48 | BY85: 0.5 | BZ85: 0.5 | CA85: 0.5 | CB85: 0.5 | CC85: 0.5 | CD85: 0.5 | CE85: 0.5 | CF85: 0.5 | CG85: 0.5 | CH85: 0.5 | CI85: 0.5 | CJ85: 0.5 | CK85: 0.5 | CL85: 0.5 | CM85: 0.5 | CN85: 0.5 | CO85: 0.5 | CP85: 0.5 | CQ85: 0.5 | CR85: 0.5 | CS85: 0.5
E86: X86-ORACLE-RAC-OS-AP-PRD | K86: 0.041 | L86: 0.04 | M86: 0.11 | N86: 0.12 | O86: 0.126 | P86: 0.14 | Q86: 0.145 | R86: 0.15 | S86: 0.16 | T86: 0.159 | U86: 0.16 | V86: 0.16 | W86: 0.17 | X86: 0.17 | Y86: 0.17 | Z86: 0.17 | AA86: 0.18 | AB86: 0.18 | AC86: 0.21 | AD86: 0.23 | AE86: 0.24 | AF86: 0.24 | AG86: 0.24 | AH86: 0.25 | AI86: 0.25 | AJ86: 0.24 | AK86: 0.25 | AL86: 0.26 | AM86: 0.27 | AN86: 0.28 | AO86: 0.28 | AP86: 0.28 | AQ86: 0.28 | AR86: 0.26 | AS86: 0.26 | AT86: 0.27 | AU86: 0.27 | AV86: 0.27 | AW86: 0.28 | AX86: 0.28 | AY86: 0.28 | AZ86: 0.28 | BA86: 0.29 | BB86: 0.29 | BC86: 0.28 | BD86: 0.28 | BE86: 0.27 | BF86: 0.27 | BG86: 0.27 | BH86: 0.27 | BI86: 0.28 | BJ86: 0.28 | BK86: 0.28 | BL86: 0.28 | BO86: 3 | BP86: 3 | BQ86: 3 | BR86: 3 | BS86: 3 | BT86: 3 | BU86: 3 | BV86: 3 | BW86: 3 | BX86: 3 | BY86: 3
E87: X86-ORACLE-RAC-WC-PRD | I87: 3.12 | J87: 3.25 | K87: 7.01 | L87: 6.99 | M87: 6.98 | N87: 6.99 | O87: 7.06 | P87: 7.19 | Q87: 7.26 | R87: 7.38 | S87: 7.58 | T87: 7.62 | U87: 7.71 | V87: 7.76 | W87: 7.82 | X87: 7.87 | Y87: 7.94 | Z87: 7.94 | AA87: 7.99 | AB87: 8.03 | AC87: 8.09 | AD87: 8.08 | AE87: 8.11 | AF87: 8.17 | AG87: 8.2 | AH87: 8.24 | AI87: 8.31 | AJ87: 9.1 | AK87: 8.47 | AL87: 8.94 | AM87: 8.98 | AN87: 8.96 | AO87: 8.98 | AP87: 9.02 | AQ87: 9.04 | AR87: 0 | AS87: 0 | AT87: 0 | AU87: 0 | AV87: 0 | AW87: 0 | AX87: 0 | AY87: 0 | AZ87: 0 | BA87: 0 | BB87: 0 | BC87: 0 | BD87: 0 | BE87: 0 | BF87: 0 | BG87: 0 | BH87: 0 | BI87: 0 | BJ87: 0 | BK87: 0 | BL87: 0 | BO87: 12.2 | BP87: 12.4 | BQ87: 12.5 | BR87: 12.7 | BS87: 12.98 | BT87: 13.22 | BU87: 13.45 | BV87: 13.59 | BW87: 13.89 | BX87: 14.01 | BY87: 14.15 | BZ87: 14.9 | CA87: 15.1 | CB87: 15.3 | CC87: 14.6 | CD87: 14.8 | CE87: 14.9 | CF87: 15.1 | CG87: 15.27 | CH87: 15.4 | CI87: 15.56 | CJ87: 15.7 | CK87: 15.7 | CL87: 16 | CM87: 16.05 | CN87: 16.29 | CO87: 16.42 | CP87: 16.54 | CQ87: 16.47 | CR87: 16.47 | CS87: 16.47
E89: SHARED | I89: 1.74 | J89: 1.78 | K89: 2.44 | L89: 2.89 | M89: 2.47 | N89: 2.7 | O89: 2.66 | P89: 2.57 | Q89: 3.83 | R89: 3.66 | S89: 3.59 | T89: 3.62 | U89: 3.69 | V89: 3.69 | W89: 3.68 | X89: 3.61 | Y89: 4.19 | Z89: 4.04 | AA89: 3.98 | AB89: 4.1 | AC89: 4.27 | AD89: 4.23 | AE89: 4.46 | AF89: 4.63 | AG89: 4.73 | AH89: 4.85 | AI89: 4.81 | AJ89: 5.13 | AK89: 6.51 | AL89: 6.51 | AM89: 14.22 | AN89: 13.67 | AO89: 13.61 | AP89: 14.2 | AQ89: 14.33 | AR89: 12.48 | AS89: 13.64 | AT89: 13.7 | AU89: 13.7 | AV89: 14.67 | AW89: 14.96 | AX89: 15.37 | AY89: 15.26 | AZ89: 14.85 | BA89: 15.66 | BB89: 15.95 | BC89: 16.16 | BD89: 17.04 | BE89: 16.79 | BF89: 16.9 | BG89: 17.05 | BH89: 17.21 | BI89: 17.3 | BJ89: 17.3 | BK89: 16.84 | BL89: 16.86
E90: SNAPSHOTS | I90: 0.02391 | J90: 0.048 | K90: 0.07 | L90: 0.27 | M90: 0.11 | N90: 0.12 | O90: 0.122 | P90: 0.13 | Q90: 0.14 | R90: 0.33 | S90: 0.34 | T90: 0.355 | U90: 0.36 | V90: 0.39 | W90: 0.39 | X90: 0.39 | Y90: 0.51 | Z90: 0.79 | AA90: 0.81 | AB90: 0.89 | AC90: 0.84 | AD90: 0.82 | AE90: 0.87 | AF90: 0.93 | AG90: 0.93 | AH90: 1.03 | AI90: 1.07 | AJ90: 1.04 | AK90: 1.02 | AL90: 0.92 | AM90: 0.72 | AN90: 0.71 | AO90: 0.82 | AP90: 0.88 | AQ90: 0.9 | AR90: 0.88 | AS90: 3.02 | AT90: 1.01 | AU90: 1.01 | AV90: 0.87 | AW90: 0.97 | AX90: 0.81 | AY90: 0.78 | AZ90: 0.68 | BA90: 0.69 | BB90: 0.71 | BC90: 1.1 | BD90: 0.91 | BE90: 0.95 | BF90: 0.72 | BG90: 0.72 | BH90: 0.92 | BI90: 0.96 | BJ90: 0.96 | BK90: 1 | BL90: 1.01
E91: TOTAL IN-USE | I91: =SUM(I81:I90) -> 8.90968 | J91: =SUM(J81:J90) -> 9.867 | K91: =SUM(K81:K90) -> 13.254 | L91: =SUM(L81:L90) -> 13.69 | M91: =SUM(M81:M90) -> 13.88 | N91: =SUM(N81:N90) -> 14.2 | O91: =SUM(O81:O90) -> 14.604 | P91: =SUM(P81:P90) -> 14.71 | ... BL91: =SUM(BL81:BL90) -> 32.59
E92: TOTAL AVAILABLE | G92: =35.55+15.9 -> 51.45 | I92: =G92-I91 -> 42.54032 | J92: =G92-J91 -> 41.583 | K92: =$G$92-K91 -> 38.196 | L92: =$G$92-L91 -> 37.76 | M92: =$G$92-M91 -> 37.57 | N92: =17.2-N91 -> 3 | O92: =17.2-O91 -> 2.596 | P92: =17.2-P91 -> 2.49 | Q92: =$G$92-Q91 -> 35.675 | R92: =$G$92-R91 -> 35.08 | S92: =$G$92-S91 -> 35.04 | T92: =$G$92-T91 -> 34.82 | U92: =$G$92-U91 -> 34.54 | V92: =$G$92-V91 -> 34.56 | W92: =$G$92-W91 -> 34.29 | X92: =$G$92-X91 -> 34.17 | ... BL92: =$G$92-BL91 -> 18.86
E93: % IN-USE Capacity | G93: Sep'22 > from 17.2TiB to 35.50TiB | I93: =I91/17.2 -> 0.51800465 | J93: =J91/17.2 -> 0.57366279 | K93: =K91/17.2 -> 0.7705814 | L93: =L91/17.2 -> 0.79593023 | M93: =M91/17.2 -> 0.80697674 | N93: =N91/17.2 -> 0.8255814 | O93: =O91/17.2 -> 0.84906977 | P93: =P91/17.22 -> 0.85423926 | Q93: =Q91/35.5 -> 0.4443662 | R93: =R91/35.5 -> 0.46112676 | S93: =S91/35.5 -> 0.46225352 | T93: =T91/35.5 -> 0.4684507 | U93: =U91/35.5 -> 0.47633803 | V93: =V91/35.5 -> 0.47577465 | W93: =W91/35.5 -> 0.48338028 | X93: =X91/35.5 -> 0.48676056 | ... AJ93: =AJ91/35.5 -> 0.68056338 | AK93: =AK91/$G$92 -> 0.47774538 | AL93: =AL91/$G$92 -> 0.64373178 | AM93: =AM91/$G$92 -> 0.66122449 | AN93: =AN91/$G$92 -> 0.65811467 | AO93: =AO91/$G$92 -> 0.66666667 | AP93: =AP91/$G$92 -> 0.67619048 | AQ93: =AQ91/$G$92 -> 0.68474247 | AR93: =AR91/$G$92 -> 0.46744412 | ... BL93: =BL91/$G$92 -> 0.63343052
B95: EQUINIX | C95: M20 | D95: CISCO-FlashStack | E95: VMware - VMFS | K95: 5.03 | L95: 4.23 | M95: 4.23 | N95: 4.21 | O95: 4.29 | P95: 4.31 | Q95: 4.31 | R95: 4.3 | S95: 4.36 | T95: 4.58 | U95: 4.39 | V95: 4.26 | W95: 4.31 | X95: 4.39 | Y95: 4.4 | Z95: 4.26 | AA95: 4.3 | AB95: 2.99 | AC95: 0 | AD95: 0 | AE95: 0
B97: aus-ps1 | E97: SHARED | K97: 0.393 | L97: 0.12 | M97: 0.12 | N97: 0.14 | O97: 0.141 | P97: 0.14 | Q97: 0.13 | R97: 0.14 | S97: 0.15 | T97: 0.14 | U97: 0.18 | V97: 0.34 | W97: 0.37 | X97: 0.38 | Y97: 0.35 | Z97: 0.31 | AA97: 0.33 | AB97: 0.47 | AC97: 0 | AD97: 0 | AE97: 0
B98: (retired on Nov'23) | E98: SNAPSHOTS | K98: 0 | L98: 0 | M98: 0 | N98: 0 | O98: 0 | P98: 0 | Q98: 0 | R98: 0 | S98: 0 | T98: 0 | U98: 0 | V98: 0 | W98: 0 | X98: 0 | Y98: 0 | Z98: 0 | AA98: 0 | AB98: 0 | AC98: 0 | AD98: 0 | AE98: 0
E99: TOTAL IN-USE | I99: =SUM(I95:I98) -> 0 | J99: =SUM(J95:J98) -> 0 | K99: =SUM(K95:K98) -> 5.423 | L99: =SUM(L95:L98) -> 4.35 | M99: =SUM(M95:M98) -> 4.35 | N99: =SUM(N95:N98) -> 4.35 | O99: =SUM(O95:O98) -> 4.431 | P99: =SUM(P95:P98) -> 4.45 | ... AE99: =SUM(AE95:AE98) -> 0
E100: TOTAL AVAILABLE | G100: 12.71 | I100: =G100-I99 -> 12.71 | J100: =G100-J99 -> 12.71 | K100: =$G$100-K99 -> 7.287 | L100: =$G$100-L99 -> 8.36 | M100: =$G$100-M99 -> 8.36 | N100: =$G$100-N99 -> 8.36 | O100: =$G$100-O99 -> 8.279 | P100: =$G$100-P99 -> 8.26 | Q100: =$G$100-Q99 -> 8.27 | R100: =$G$100-R99 -> 8.27 | ... AE100: =$G$100-AE99 -> 12.71
E101: % IN-USE Capacity | I101: =I99/G100 -> 0 | J101: =J99/G100 -> 0 | K101: =K99/$G$100 -> 0.42667191 | L101: =L99/$G$100 -> 0.3422502 | M101: =M99/$G$100 -> 0.3422502 | N101: =N99/$G$100 -> 0.3422502 | O101: =O99/$G$100 -> 0.34862313 | P101: =P99/$G$100 -> 0.35011802 | Q101: =Q99/$G$100 -> 0.34933124 | R101: =R99/$G$100 -> 0.34933124 | ... AE101: =AE99/$G$100 -> 0
B103: EQUINIX | C103: SuperCluster | D103: ORACLE M7 | E103: ORACLE ERP NON-PROD ausc01-dbdev01/02 (Max = 97TB) | G103: =73*0.7 -> 51.1 | I103: =97*0.6127 -> 59.4319 | J103: =97*0.616 -> 59.752 | K103: =97*0.62 -> 60.14 | L103: =97*0.63 -> 61.11 | M103: =97*0.789 -> 76.533 | N103: 61.31 | O103: 66.76 | P103: 63.62 | Q103: 52.92 | R103: 54.51 | S103: 71.49 | T103: 55.62 | U103: 57.21 | V103: 57.38 | W103: 57.65 | X103: 58.75 | Y103: 76.65 | Z103: 59.46 | AA103: 61.29 | AB103: 62.93 | AC103: 63.1 | AD103: 64.19 | AE103: 83.08 | AF103: 65.56 | AG103: 64.34 | AH103: 65.47 | AI103: 64.69 | AJ103: 65.39 | AK103: 66.97 | AL103: 68.78 | AM103: 69 | AN103: 69.21 | AO103: 48.61 | AP103: 69.98 | AQ103: 71.84 | AR103: 73.68 | AS103: 73.89 | AT103: 72.49 | AU103: 73.83 | AV103: 74.07 | AW103: 75.37 | AX103: 75.67 | AY103: 50.78 | AZ103: 51.25 | BA103: 51.58 | BB103: 51.81 | BC103: 52.96 | BD103: 53.96 | BE103: 51.66 | BF103: 55.46 | BG103: 55.8 | BH103: 56 | BI103: 56.6 | BJ103: 56.8 | BK103: 59.2 | BL103: 59.4 | BN103: =I103 -> 59.4319 | BO103: =J103 -> 59.752 | BP103: =K103 -> 60.14 | BQ103: =L103 -> 61.11 | BR103: =M103 -> 76.533 | BS103: =N103 -> 61.31 | BT103: =O103 -> 66.76 | BU103: =P103 -> 63.62 | ... CI103: =AD103 -> 64.19 | CJ103: 88.6 | CK103: 55.6 | CL103: 56.6 | CM103: 56.6 | CN103: 56.8 | CO103: =AJ103 -> 65.39 | CP103: =AK103 -> 66.97 | CQ103: =AL103 -> 68.78 | CR103: =AM103 -> 69 | CS103: =AN103 -> 69.21 | CX103: 64.8
E104: ORACLE ERP PROD ausc01-dbprd01/02 (Max = 43TB), 135.2TB after repartition | G104: =59*0.7 -> 41.3 | I104: =32*0.6558 -> 20.9856 | J104: =32*0.6668 -> 21.3376 | K104: =32*0.6733 -> 21.5456 | L104: =32*0.69 -> 22.08 | M104: =32*0.695 -> 22.24 | N104: 22.41 | O104: 22.66 | P104: 22.78 | Q104: 23.09 | R104: 23.36 | S104: 23.89 | T104: 24.29 | U104: 24.45 | V104: 24.68 | W104: 24.98 | X104: 25.35 | Y104: 25.52 | Z104: 25.75 | AA104: 26.01 | AB104: 26.47 | AC104: 26.68 | AD104: 26.93 | AE104: 27.12 | AF104: 27.37 | AG104: 27.6 | AH104: 27.93 | AI104: 28.2 | AJ104: 29 | AK104: 29.23 | AL104: 29.45 | AM104: 29.7 | AN104: 29.97 | AO104: 30.07 | AP104: 31.25 | AQ104: 31.53 | AR104: 31.76 | AS104: 32.65 | AT104: 32.95 | AU104: 33.19 | AV104: 33.84 | AW104: 34.05 | AX104: 34.31 | AY104: 34.52 | AZ104: 35.08 | BA104: 35.32 | BB104: 35.55 | BC104: 35.92 | BD104: 36.36 | BE104: 33.28 | BF104: 36.97 | BG104: 37.28 | BH104: 37.66 | BI104: 38.01 | BJ104: 38.26 | BK104: 38.62 | BL104: 38.9 | BN104: =I104 -> 20.9856 | BO104: =J104 -> 21.3376 | BP104: =K104 -> 21.5456 | BQ104: =L104 -> 22.08 | BR104: =M104 -> 22.24 | BS104: =N104 -> 22.41 | BT104: =O104 -> 22.66 | BU104: =P104 -> 22.78 | ... CI104: =AD104 -> 26.93 | CJ104: 27.8 | CK104: 18.8 | CL104: 19.3 | CM104: 19.3 | CN104: 19.8 | CO104: =AJ104 -> 29 | CP104: =AK104 -> 29.23 | CQ104: =AL104 -> 29.45 | CR104: =AM104 -> 29.7 | CS104: =AN104 -> 29.97 | CX104: 21.8
E106: SHARED
E107: SNAPSHOTS
E108: TOTAL IN-USE | I108: =SUM(I103:I107) -> 80.4175 | J108: =SUM(J103:J107) -> 81.0896 | K108: =SUM(K103:K107) -> 81.6856 | L108: =SUM(L103:L107) -> 83.19 | M108: =SUM(M103:M107) -> 98.773 | N108: =SUM(N103:N107) -> 83.72 | O108: =SUM(O103:O107) -> 89.42 | P108: =SUM(P103:P107) -> 86.4 | ... BL108: =SUM(BL103:BL107) -> 98.3
E109: TOTAL AVAILABLE | G109: =(73+59)*0.8 -> 105.6 | I109: =G109-I108 -> 25.1825 | J109: =G109-J108 -> 24.5104 | K109: =$G$109-K108 -> 23.9144 | L109: =$G$109-L108 -> 22.41 | M109: =$G$109-M108 -> 6.827 | N109: =$G$109-N108 -> 21.88 | O109: =$G$109-O108 -> 16.18 | P109: =$G$109-P108 -> 19.2 | Q109: =$G$109-Q108 -> 29.59 | R109: =$G$109-R108 -> 27.73 | ... BL109: =$G$109-BL108 -> 7.3
E110: % IN-USE Capacity | I110: =I108/G109 -> 0.76152936 | J110: =J108/G109 -> 0.76789394 | K110: =K108/$G$109 -> 0.77353788 | L110: =L108/$G$109 -> 0.78778409 | M110: =M108/$G$109 -> 0.93535038 | N110: =N108/$G$109 -> 0.79280303 | O110: =O108/$G$109 -> 0.8467803 | P110: =P108/$G$109 -> 0.81818182 | Q110: =Q108/$G$109 -> 0.71979167 | R110: =R108/$G$109 -> 0.7374053 | ... BL110: =BL108/$G$109 -> 0.93087121
B112: Denver | C112: Unity NAS | D112: Type | E112: VMFS (Lenovo box) | I112: =1.1+7.3 -> 8.4 | J112: =1.2+7.3 -> 8.5 | K112: =1.3+7.3 -> 8.6 | L112: =0.7+6.8 -> 7.5 | M112: 7.6 | N112: 7.6 | O112: 7.6 | P112: 7.6 | Q112: 7.6 | R112: 7.6 | S112: 7.6 | T112: 7.6 | U112: 7.68 | V112: 7.73 | W112: 7.79 | X112: 7.95 | Y112: 8.09 | Z112: 8.15 | AA112: 8.2 | AB112: 8.32 | AC112: 8.26 | AD112: 8.45 | AE112: 8.45 | AF112: 8.48 | AG112: 8.51 | AH112: 8.81 | AI112: 8.82 | AJ112: 8.88 | AK112: 8.88 | AL112: 9.3 | AM112: 9.77 | AN112: 9.93 | AO112: 9.93 | AP112: 9.93 | AQ112: 10.04 | AR112: 10.04 | AS112: 10.04 | AT112: 10.13 | AU112: 10.2 | AV112: 10.34 | AW112: 10.47 | AX112: 10.89 | AY112: 10.89 | AZ112: 10.98 | BA112: 11.09 | BB112: 11.09 | BC112: 11.22 | BD112: 11.21 | BE112: 11.24 | BF112: 11.22 | BG112: 11.21 | BH112: 11.21 | BI112: 11.21 | BJ112: 11.21 | BK112: 11.2 | BL112: 11.18
E113: FileShare | I113: 6.3 | J113: 6.3 | K113: 6.3 | L113: 6.74 | M113: 6.9 | N113: 6.9 | O113: 6.8 | P113: 7.1 | Q113: 7.3 | R113: 7.3 | S113: 7.6 | T113: 7.7 | U113: 7.78 | V113: 7.81 | W113: 7.84 | X113: 7.91 | Y113: 7.99 | Z113: 8.08 | AA113: 8.14 | AB113: 8.22 | AC113: 8.27 | AD113: 8.34 | AE113: 8.4 | AF113: 8.73 | AG113: 8.75 | AH113: 8.56 | AI113: 8.56 | AJ113: 8.63 | AK113: 8.67 | AL113: 8.74 | AM113: 8.79 | AN113: 8.88 | AO113: 8.94 | AP113: 8.99 | AQ113: 9.03 | AR113: 9.1 | AS113: 9.15 | AT113: 9.2 | AU113: 9.2 | AV113: 9.3 | AW113: 9.34 | AX113: 9.38 | AY113: 9.43 | AZ113: 9.47 | BA113: 9.54 | BB113: 9.57 | BC113: 9.63 | BD113: 9.61 | BE113: 9.63 | BF113: 9.73 | BG113: 9.72 | BH113: 9.72 | BI113: 9.76 | BJ113: 9.79 | BK113: 9.88 | BL113: 9.98
E115: SHARED
E116: SNAPSHOTS
E117: TOTAL IN-USE | I117: =SUM(I112:I116) -> 14.7 | J117: =SUM(J112:J116) -> 14.8 | K117: =SUM(K112:K116) -> 14.9 | L117: =SUM(L112:L116) -> 14.24 | M117: =SUM(M112:M116) -> 14.5 | N117: =SUM(N112:N116) -> 14.5 | O117: =SUM(O112:O116) -> 14.4 | P117: =SUM(P112:P116) -> 14.7 | ... BL117: =SUM(BL112:BL116) -> 21.16
...

Sheet EQUINIX DC
A1: Equinix (12% YoY) | B1: Total Storage | C1: Month | D1: In Use | E1: Change (TB) | F1: Growth (%) | G1: Forecast | H1: In use (%) | I1: Forecast (%) | J1: Max % | AZ1: Aug'25
A2: X20+M20 | B2: =('Data Collection Sheet'!$G$92+'Data Collection Sheet'!$G$100)-35.5+17.2 -> 45.86 | C2: 44562 | D2: ='Data Collection Sheet'!I91+'Data Collection Sheet'!I99 -> 8.90968 | H2: =(D2/B2)*100 -> 19.427998 | J2: 90
B3: =('Data Collection Sheet'!$G$92+'Data Collection Sheet'!$G$100)-35.5+17.2 -> 45.86 | C3: 44593 | D3: ='Data Collection Sheet'!J91+'Data Collection Sheet'!J99 -> 9.867 | H3: =(D3/B3)*100 -> 21.515482 | J3: 90
A4: NR Complete Migration (8.8TB migrated) | B4: =('Data Collection Sheet'!$G$92+'Data Collection Sheet'!$G$100)-35.5+17.2 -> 45.86 | C4: 44621 | D4: =SUM('Data Collection Sheet'!K91+'Data Collection Sheet'!K99) -> 18.677 | H4: =(D4/B4)*100 -> 40.726123 | J4: 90
A5: Stabilized Data | B5: =('Data Collection Sheet'!$G$92+'Data Collection Sheet'!$G$100)-35.5+17.2 -> 45.86 | C5: 44652 | D5: =SUM('Data Collection Sheet'!L91+'Data Collection Sheet'!L99) -> 18.04 | H5: =(D5/B5)*100 -> 39.337113 | J5: 90
A6: Order uplift to 35TB | B6: =('Data Collection Sheet'!$G$92+'Data Collection Sheet'!$G$100)-35.5+17.2 -> 45.86 | C6: 44682 | D6: =SUM('Data Collection Sheet'!M91+'Data Collection Sheet'!M99) -> 18.23 | H6: =(D6/B6)*100 -> 39.751417 | J6: 90
B7: =('Data Collection Sheet'!$G$92+'Data Collection Sheet'!$G$100)-35.5+17.2 -> 45.86 | C7: 44713 | D7: =SUM('Data Collection Sheet'!N91+'Data Collection Sheet'!N99) -> 18.55 | H7: =(D7/B7)*100 -> 40.449193 | J7: 90
B8: =('Data Collection Sheet'!$G$92+'Data Collection Sheet'!$G$100)-35.5+17.2 -> 45.86 | C8: 44743 | D8: =SUM('Data Collection Sheet'!O91+'Data Collection Sheet'!O99) -> 19.035 | H8: =(D8/B8)*100 -> 41.50676 | J8: 90
B9: =('Data Collection Sheet'!$G$92+'Data Collection Sheet'!$G$100)-35.5+17.2 -> 45.86 | C9: 44774 | D9: =SUM('Data Collection Sheet'!P91+'Data Collection Sheet'!P99) -> 19.16 | H9: =(D9/B9)*100 -> 41.779328 | J9: 90 | AZ9: Aug'25
A10: Implement X20 uplift to 35TB | B10: =('Data Collection Sheet'!G92+'Data Collection Sheet'!G100) -> 64.16 | C10: 44805 | D10: =SUM('Data Collection Sheet'!Q91+'Data Collection Sheet'!Q99) -> 20.215 | H10: =(D10/B10)*100 -> 31.50717 | J10: 90 | AZ10: 8.77
A11: Renew maintenace M20 till Nov 24 | B11: =35.5+'Data Collection Sheet'!$G$100 -> 48.21 | C11: 44835 | D11: =SUM('Data Collection Sheet'!R91+'Data Collection Sheet'!R99) -> 20.81 | H11: =(D11/B11)*100 -> 43.165318 | J11: 90 | AZ11: 1.49
B12: =35.5+'Data Collection Sheet'!$G$100 -> 48.21 | C12: 44866 | D12: =SUM('Data Collection Sheet'!S91+'Data Collection Sheet'!S99) -> 20.92 | H12: =(D12/B12)*100 -> 43.393487 | J12: 90 | AZ12: 0.06
B13: =35.5+'Data Collection Sheet'!$G$100 -> 48.21 | C13: 44896 | D13: =SUM('Data Collection Sheet'!T91+'Data Collection Sheet'!T99) -> 21.35 | H13: =(D13/B13)*100 -> 44.285418 | J13: 90 | AZ13: 25.94
B14: =35.5+'Data Collection Sheet'!$G$100 -> 48.21 | C14: 44927 | D14: =SUM('Data Collection Sheet'!U91+'Data Collection Sheet'!U99) -> 21.48 | H14: =(D14/B14)*100 -> 44.555072 | J14: 90 | AZ14: 0.23
B15: =35.5+'Data Collection Sheet'!$G$100 -> 48.21 | C15: 44958 | D15: =SUM('Data Collection Sheet'!V91+'Data Collection Sheet'!V99) -> 21.49 | H15: =(D15/B15)*100 -> 44.575814 | J15: 90 | AZ15: 0.49
B16: =35.5+'Data Collection Sheet'!$G$100 -> 48.21 | C16: 44986 | D16: =SUM('Data Collection Sheet'!W91+'Data Collection Sheet'!W99) -> 21.84 | H16: =(D16/B16)*100 -> 45.301805 | J16: 90 | AZ16: 0.3
B17: =35.5+'Data Collection Sheet'!$G$100 -> 48.21 | C17: 45017 | D17: =SUM('Data Collection Sheet'!X91+'Data Collection Sheet'!X99) -> 22.05 | H17: =(D17/B17)*100 -> 45.737399 | J17: 90 | AZ17: 0
B18: =35.5+'Data Collection Sheet'!$G$100 -> 48.21 | C18: 45047 | D18: =SUM('Data Collection Sheet'!Y91+'Data Collection Sheet'!Y99) -> 22.48 | H18: =(D18/B18)*100 -> 46.62933 | J18: 90 | AZ18: 0
B19: =35.5+'Data Collection Sheet'!$G$100 -> 48.21 | C19: 45078 | D19: =SUM('Data Collection Sheet'!Z91+'Data Collection Sheet'!Z99) -> 22.36 | H19: =(D19/B19)*100 -> 46.380419 | J19: 90 | AZ19: 0
B20: =35.5+'Data Collection Sheet'!$G$100 -> 48.21 | C20: 45108 | D20: =SUM('Data Collection Sheet'!AA91+'Data Collection Sheet'!AA99) -> 22.59 | H20: =(D20/B20)*100 -> 46.857498 | J20: 90 | AZ20: 0
B21: =35.5+'Data Collection Sheet'!$G$100 -> 48.21 | C21: 45139 | D21: =SUM('Data Collection Sheet'!AB91+'Data Collection Sheet'!AB99) -> 22.84 | E21: 0 | H21: =(D21/B21)*100 -> 47.376063 | J21: 90
B22: =35.5+'Data Collection Sheet'!$G$100 -> 48.21 | C22: 45170 | D22: =SUM('Data Collection Sheet'!AC91+'Data Collection Sheet'!AC99) -> 21.06 | H22: =(D22/B22)*100 -> 43.683883 | J22: 90 | AZ22: 3.39
A23: Remove M20- supported till Nov-23 (13TB) | B23: =35.5+'Data Collection Sheet'!$G$100 -> 48.21 | C23: 45200 | D23: =SUM('Data Collection Sheet'!AD91+'Data Collection Sheet'!AD99) -> 21.29 | H23: =(D23/B23)*100 -> 44.160962 | J23: 90 | AZ23: 0.01
B24: 35 | C24: 45231 | D24: =SUM('Data Collection Sheet'!AE91+'Data Collection Sheet'!AE99) -> 21.91 | H24: =(D24/B24)*100 -> 62.6 | J24: 90
B25: 35 | C25: 45261 | D25: =SUM('Data Collection Sheet'!AF91+'Data Collection Sheet'!AF99) -> 21.92 | H25: =(D25/B25)*100 -> 62.628571 | J25: 90
B26: 35 | C26: 45292 | D26: =SUM('Data Collection Sheet'!AG91+'Data Collection Sheet'!AG99) -> 22 | H26: =(D26/B26)*100 -> 62.857143 | J26: 90
B27: 35 | C27: 45323 | D27: =SUM('Data Collection Sheet'!AH91+'Data Collection Sheet'!AH99) -> 22.37 | H27: =(D27/B27)*100 -> 63.914286 | J27: 90
B28: 35 | C28: 45352 | D28: =SUM('Data Collection Sheet'!AI91+'Data Collection Sheet'!AI99) -> 23.24 | H28: =(D28/B28)*100 -> 66.4 | J28: 90 | AY28: 1.14 | AZ28: 1.17
A29: Added more capacity with CR38226 (16TB) | B29: ='Data Collection Sheet'!$G$92 -> 51.45 | C29: 45383 | D29: =SUM('Data Collection Sheet'!AJ91+'Data Collection Sheet'!AJ99) -> 24.16 | H29: =(D29/B29)*100 -> 46.958212 | J29: 90 | AZ29: 0.37
A30: WChill DB 2 SQL - 1 Env. 15TB > 5TB on disk | B30: ='Data Collection Sheet'!$G$92 -> 51.45 | C30: 45413 | D30: =SUM('Data Collection Sheet'!AK91+'Data Collection Sheet'!AK99) -> 24.58 | E30: 9 | H30: =(D30/B30)*100 -> 47.774538 | J30: 90 | AZ30: 0.43
B31: ='Data Collection Sheet'!$G$92 -> 51.45 | C31: 45444 | D31: =SUM('Data Collection Sheet'!AL91+'Data Collection Sheet'!AL99) -> 33.12 | H31: =(D31/B31)*100 -> 64.373178 | J31: 90
B32: ='Data Collection Sheet'!$G$92 -> 51.45 | C32: 45474 | D32: =SUM('Data Collection Sheet'!AM91+'Data Collection Sheet'!AM99) -> 34.02 | H32: =(D32/B32)*100 -> 66.122449 | J32: 90
B33: ='Data Collection Sheet'!$G$92 -> 51.45 | C33: 45505 | D33: =SUM('Data Collection Sheet'!AN91+'Data Collection Sheet'!AN99) -> 33.86 | H33: =(D33/B33)*100 -> 65.811467 | J33: 90 | AZ33: 1.19
B34: ='Data Collection Sheet'!$G$92 -> 51.45 | C34: 45536 | D34: =SUM('Data Collection Sheet'!AO91+'Data Collection Sheet'!AO99) -> 34.3 | H34: =(D34/B34)*100 -> 66.666667 | J34: 90 | AZ34: 2.61
B35: ='Data Collection Sheet'!$G$92 -> 51.45 | C35: 45566 | D35: =SUM('Data Collection Sheet'!AP91+'Data Collection Sheet'!AP99) -> 34.79 | H35: =(D35/B35)*100 -> 67.619048 | J35: 90 | AZ35: 0
B36: ='Data Collection Sheet'!$G$92 -> 51.45 | C36: 45597 | D36: =SUM('Data Collection Sheet'!AQ91+'Data Collection Sheet'!AQ99) -> 35.23 | H36: =(D36/B36)*100 -> 68.474247 | J36: 90 | AZ36: 0.54
A37: Remove the Oracle Windchill RAC | B37: ='Data Collection Sheet'!$G$92 -> 51.45 | C37: 45627 | D37: =SUM('Data Collection Sheet'!AR91+'Data Collection Sheet'!AR99) -> 24.05 | H37: =(D37/B37)*100 -> 46.744412 | J37: 90 | AZ37: 0
B38: ='Data Collection Sheet'!$G$92 -> 51.45 | C38: 45658 | D38: =SUM('Data Collection Sheet'!AS91+'Data Collection Sheet'!AS99) -> 27.91 | H38: =(D38/B38)*100 -> 54.246842 | J38: 90 | AZ38: 0.55
B39: ='Data Collection Sheet'!$G$92 -> 51.45 | C39: 45689 | D39: =SUM('Data Collection Sheet'!AT91+'Data Collection Sheet'!AT99) -> 26.56 | H39: =(D39/B39)*100 -> 51.622935 | J39: 90 | AZ39: 0.93
B40: ='Data Collection Sheet'!$G$92 -> 51.45 | C40: 45717 | D40: =SUM('Data Collection Sheet'!AU91+'Data Collection Sheet'!AU99) -> 26.56 | H40: =(D40/B40)*100 -> 51.622935 | J40: 90 | AZ40: 0.66
B41: ='Data Collection Sheet'!$G$92 -> 51.45 | C41: 45748 | D41: =SUM('Data Collection Sheet'!AV91+'Data Collection Sheet'!AV99) -> 28.38 | H41: =(D41/B41)*100 -> 55.16035 | J41: 90 | AZ41: 2.16
B42: ='Data Collection Sheet'!$G$92 -> 51.45 | C42: 45778 | D42: =SUM('Data Collection Sheet'!AW91+'Data Collection Sheet'!AW99) -> 29.03 | H42: =(D42/B42)*100 -> 56.423712 | J42: 90 | AZ42: 0.31
B43: ='Data Collection Sheet'!$G$92 -> 51.45 | C43: 45809 | D43: =SUM('Data Collection Sheet'!AX91+'Data Collection Sheet'!AX99) -> 29.5 | H43: =(D43/B43)*100 -> 57.337221 | J43: 90 | AZ43: 1.91
B44: ='Data Collection Sheet'!$G$92 -> 51.45 | C44: 45839 | D44: =SUM('Data Collection Sheet'!AY91+'Data Collection Sheet'!AY99) -> 30.07 | H44: =(D44/B44)*100 -> 58.445092 | J44: 90 | AZ44: 0.86
B45: ='Data Collection Sheet'!$G$92 -> 51.45 | C45: 45870 | D45: =SUM('Data Collection Sheet'!AZ91+'Data Collection Sheet'!AZ99) -> 30.64 | H45: =(D45/B45)*100 -> 59.552964 | J45: 90 | AZ45: 1.51
B46: ='Data Collection Sheet'!$G$92 -> 51.45 | C46: 45901 | D46: =SUM('Data Collection Sheet'!BA91+'Data Collection Sheet'!BA99) -> 30.6 | H46: =(D46/B46)*100 -> 59.475219 | J46: 90 | AZ46: 20.16
B47: ='Data Collection Sheet'!$G$92 -> 51.45 | C47: 45931 | D47: =SUM('Data Collection Sheet'!BB91+'Data Collection Sheet'!BB99) -> 31.26 | H47: =(D47/B47)*100 -> 60.758017 | J47: 90 | AZ47: 0
B48: ='Data Collection Sheet'!$G$92 -> 51.45 | C48: 45962 | D48: =SUM('Data Collection Sheet'!BC91+'Data Collection Sheet'!BC99) -> 31.67 | H48: =(D48/B48)*100 -> 61.554908 | J48: 90 | AZ48: 0.49
B49: ='Data Collection Sheet'!$G$92 -> 51.45 | C49: 45992 | D49: =SUM('Data Collection Sheet'!BD91+'Data Collection Sheet'!BD99) -> 31.72 | H49: =(D49/B49)*100 -> 61.652089 | J49: 90 | AZ49: 0.03
B50: ='Data Collection Sheet'!$G$92 -> 51.45 | C50: 46023 | D50: =SUM('Data Collection Sheet'!BE91+'Data Collection Sheet'!BE99) -> 31.43 | H50: =(D50/B50)*100 -> 61.088435 | J50: 90 | AY50: 0 | AZ50: 0
B51: ='Data Collection Sheet'!$G$92 -> 51.45 | C51: 46054 | D51: =SUM('Data Collection Sheet'!BF91+'Data Collection Sheet'!BF99) -> 30.29 | H51: =(D51/B51)*100 -> 58.872692 | J51: 90
A52: Renew Support for M6 | B52: ='Data Collection Sheet'!$G$92 -> 51.45 | C52: 46082 | D52: =SUM('Data Collection Sheet'!BG91+'Data Collection Sheet'!BG99) -> 30.94 | H52: =(D52/B52)*100 -> 60.136054 | J52: 90 | AZ52: 23.17
A53: From 12% to 8% increase (AWS) | B53: ='Data Collection Sheet'!$G$92 -> 51.45 | C53: 46113 | D53: =SUM('Data Collection Sheet'!BH91+'Data Collection Sheet'!BH99) -> 31.66 | H53: =(D53/B53)*100 -> 61.535471 | J53: 90 | AZ53: 4.33
B54: ='Data Collection Sheet'!$G$92 -> 51.45 | C54: 46143 | D54: =SUM('Data Collection Sheet'!BI91+'Data Collection Sheet'!BI99) -> 32.4 | H54: =(D54/B54)*100 -> 62.973761 | J54: 90
B55: ='Data Collection Sheet'!$G$92 -> 51.45 | C55: 46174 | D55: =SUM('Data Collection Sheet'!BJ91+'Data Collection Sheet'!BJ99) -> 32.91 | H55: =(D55/B55)*100 -> 63.965015 | J55: 90
B56: ='Data Collection Sheet'!$G$92 -> 51.45 | C56: 46204 | D56: =SUM('Data Collection Sheet'!BK91+'Data Collection Sheet'!BK99) -> 32.92 | H56: =(D56/B56)*100 -> 63.984451 | J56: 90
B57: ='Data Collection Sheet'!$G$92 -> 51.45 | C57: 46235 | D57: =SUM('Data Collection Sheet'!BL91+'Data Collection Sheet'!BL99) -> 32.59 | F57: 7.12 | G57: =D57 -> 32.59 | H57: =(D57/B57)*100 -> 63.343052 | I57: =(G57/B57)*100 -> 63.343052 | J57: 90
B58: ='Data Collection Sheet'!$G$92 -> 51.45 | C58: 46266 | F58: 1.08 | G58: =G57*(1+(F58^(1/12)-1))+E58 -> 32.799685 | I58: =(G58/B58)*100 -> 63.750603 | J58: 90 | AZ58: 16.01
B59: ='Data Collection Sheet'!$G$92 -> 51.45 | C59: 46296 | F59: 1.08 | G59: =G58*(1+(F59^(1/12)-1))+E59 -> 33.010719 | I59: =(G59/B59)*100 -> 64.160776 | J59: 90 | AZ59: 0.21
B60: ='Data Collection Sheet'!$G$92 -> 51.45 | C60: 46327 | F60: 1.08 | G60: =G59*(1+(F60^(1/12)-1))+E60 -> 33.223111 | I60: =(G60/B60)*100 -> 64.573588 | J60: 90 | AZ60: 0
B61: ='Data Collection Sheet'!$G$92 -> 51.45 | C61: 46357 | F61: 1.08 | G61: =G60*(1+(F61^(1/12)-1))+E61 -> 33.43687 | I61: =(G61/B61)*100 -> 64.989057 | J61: 90 | AZ61: 4.06
B62: ='Data Collection Sheet'!$G$92 -> 51.45 | C62: 46388 | F62: 1.08 | G62: =G61*(1+(F62^(1/12)-1))+E62 -> 33.652003 | I62: =(G62/B62)*100 -> 65.407198 | J62: 90 | AZ62: 0
B63: ='Data Collection Sheet'!$G$92 -> 51.45 | C63: 46419 | F63: 1.08 | G63: =G62*(1+(F63^(1/12)-1))+E63 -> 33.868521 | I63: =(G63/B63)*100 -> 65.82803 | J63: 90 | AZ63: 0
B64: ='Data Collection Sheet'!$G$92 -> 51.45 | C64: 46447 | F64: 1.08 | G64: =G63*(1+(F64^(1/12)-1))+E64 -> 34.086433 | I64: =(G64/B64)*100 -> 66.25157 | J64: 90 | AZ64: 0
B65: ='Data Collection Sheet'!$G$92 -> 51.45 | C65: 46478 | F65: 1.08 | G65: =G64*(1+(F65^(1/12)-1))+E65 -> 34.305746 | I65: =(G65/B65)*100 -> 66.677834 | J65: 90
B66: ='Data Collection Sheet'!$G$92 -> 51.45 | C66: 46508 | F66: 1.08 | G66: =G65*(1+(F66^(1/12)-1))+E66 -> 34.52647 | I66: =(G66/B66)*100 -> 67.106841 | J66: 90 | AZ66: 9.76
B67: ='Data Collection Sheet'!$G$92 -> 51.45 | C67: 46539 | F67: 1.08 | G67: =G66*(1+(F67^(1/12)-1))+E67 -> 34.748614 | I67: =(G67/B67)*100 -> 67.538609 | J67: 90 | AZ67: 0
B68: ='Data Collection Sheet'!$G$92 -> 51.45 | C68: 46569 | F68: 1.08 | G68: =G67*(1+(F68^(1/12)-1))+E68 -> 34.972188 | I68: =(G68/B68)*100 -> 67.973154 | J68: 90
B69: ='Data Collection Sheet'!$G$92 -> 51.45 | C69: 46600 | F69: 1.08 | G69: =G68*(1+(F69^(1/12)-1))+E69 -> 35.1972 | I69: =(G69/B69)*100 -> 68.410496 | J69: 90
B70: ='Data Collection Sheet'!$G$92 -> 51.45 | C70: 46631 | F70: 1.08 | G70: =G69*(1+(F70^(1/12)-1))+E70 -> 35.42366 | I70: =(G70/B70)*100 -> 68.850651 | J70: 90
B71: ='Data Collection Sheet'!$G$92 -> 51.45 | C71: 46661 | F71: 1.08 | G71: =G70*(1+(F71^(1/12)-1))+E71 -> 35.651577 | I71: =(G71/B71)*100 -> 69.293638 | J71: 90
B72: ='Data Collection Sheet'!$G$92 -> 51.45 | C72: 46692 | F72: 1.08 | G72: =G71*(1+(F72^(1/12)-1))+E72 -> 35.88096 | I72: =(G72/B72)*100 -> 69.739475 | J72: 90 | AZ72: 0.22
B73: ='Data Collection Sheet'!$G$92 -> 51.45 | C73: 46722 | F73: 1.08 | G73: =G72*(1+(F73^(1/12)-1))+E73 -> 36.111819 | I73: =(G73/B73)*100 -> 70.188181 | J73: 90 | AZ73: 1.17
B74: ='Data Collection Sheet'!$G$92 -> 51.45 | C74: 46753 | F74: 1.08 | G74: =G73*(1+(F74^(1/12)-1))+E74 -> 36.344164 | I74: =(G74/B74)*100 -> 70.639774 | J74: 90 | AZ74: 2.89
B75: ='Data Collection Sheet'!$G$92 -> 51.45 | C75: 46784 | F75: 1.08 | G75: =G74*(1+(F75^(1/12)-1))+E75 -> 36.578003 | I75: =(G75/B75)*100 -> 71.094273 | J75: 90 | AZ75: 10.16
B76: ='Data Collection Sheet'!$G$92 -> 51.45 | C76: 46813 | F76: 1.08 | G76: =G75*(1+(F76^(1/12)-1))+E76 -> 36.813347 | I76: =(G76/B76)*100 -> 71.551695 | J76: 90 | AZ76: 0.39
B77: ='Data Collection Sheet'!$G$92 -> 51.45 | C77: 46844 | F77: 1.08 | G77: =G76*(1+(F77^(1/12)-1))+E77 -> 37.050205 | I77: =(G77/B77)*100 -> 72.012061 | J77: 90 | AZ77: 0.28
B78: ='Data Collection Sheet'!$G$92 -> 51.45 | C78: 46874 | F78: 1.08 | G78: =G77*(1+(F78^(1/12)-1))+E78 -> 37.288588 | I78: =(G78/B78)*100 -> 72.475389 | J78: 90 | AZ78: 0
B79: ='Data Collection Sheet'!$G$92 -> 51.45 | C79: 46905 | F79: 1.08 | G79: =G78*(1+(F79^(1/12)-1))+E79 -> 37.528503 | I79: =(G79/B79)*100 -> 72.941698 | J79: 90
B80: ='Data Collection Sheet'!$G$92 -> 51.45 | C80: 46935 | F80: 1.08 | G80: =G79*(1+(F80^(1/12)-1))+E80 -> 37.769963 | I80: =(G80/B80)*100 -> 73.411007 | J80: 90 | AZ80: 14.85
B81: ='Data Collection Sheet'!$G$92 -> 51.45 | C81: 46966 | F81: 1.08 | G81: =G80*(1+(F81^(1/12)-1))+E81 -> 38.012976 | I81: =(G81/B81)*100 -> 73.883335 | J81: 90 | AZ81: 0.68
B82: ='Data Collection Sheet'!$G$92 -> 51.45 | C82: 46997 | F82: 1.08 | G82: =G81*(1+(F82^(1/12)-1))+E82 -> 38.257553 | I82: =(G82/B82)*100 -> 74.358703 | J82: 90
B83: ='Data Collection Sheet'!$G$92 -> 51.45 | C83: 47027 | F83: 1.08 | G83: =G82*(1+(F83^(1/12)-1))+E83 -> 38.503703 | I83: =(G83/B83)*100 -> 74.837129 | J83: 90
B84: ='Data Collection Sheet'!$G$92 -> 51.45 | C84: 47058 | F84: 1.08 | G84: =G83*(1+(F84^(1/12)-1))+E84 -> 38.751437 | I84: =(G84/B84)*100 -> 75.318633 | J84: 90
B85: ='Data Collection Sheet'!$G$92 -> 51.45 | C85: 47088 | F85: 1.08 | G85: =G84*(1+(F85^(1/12)-1))+E85 -> 39.000765 | I85: =(G85/B85)*100 -> 75.803236 | J85: 90
B86: ='Data Collection Sheet'!$G$92 -> 51.45 | C86: 47119 | F86: 1.08 | G86: =G85*(1+(F86^(1/12)-1))+E86 -> 39.251697 | I86: =(G86/B86)*100 -> 76.290956 | J86: 90
B87: ='Data Collection Sheet'!$G$92 -> 51.45 | C87: 47150 | F87: 1.08 | G87: =G86*(1+(F87^(1/12)-1))+E87 -> 39.504243 | I87: =(G87/B87)*100 -> 76.781814 | J87: 90
B88: ='Data Collection Sheet'!$G$92 -> 51.45 | C88: 47178 | F88: 1.08 | G88: =G87*(1+(F88^(1/12)-1))+E88 -> 39.758415 | I88: =(G88/B88)*100 -> 77.275831 | J88: 90
B89: ='Data Collection Sheet'!$G$92 -> 51.45 | C89: 47209 | F89: 1.08 | G89: =G88*(1+(F89^(1/12)-1))+E89 -> 40.014222 | I89: =(G89/B89)*100 -> 77.773026 | J89: 90
B90: ='Data Collection Sheet'!$G$92 -> 51.45 | C90: 47239 | F90: 1.08 | G90: =G89*(1+(F90^(1/12)-1))+E90 -> 40.271675 | I90: =(G90/B90)*100 -> 78.27342 | J90: 90
B91: ='Data Collection Sheet'!$G$92 -> 51.45 | C91: 47270 | F91: 1.08 | G91: =G90*(1+(F91^(1/12)-1))+E91 -> 40.530784 | I91: =(G91/B91)*100 -> 78.777033 | J91: 90
B92: ='Data Collection Sheet'!$G$92 -> 51.45 | C92: 47300 | F92: 1.08 | G92: =G91*(1+(F92^(1/12)-1))+E92 -> 40.79156 | I92: =(G92/B92)*100 -> 79.283887 | J92: 90
B93: ='Data Collection Sheet'!$G$92 -> 51.45 | C93: 47331 | F93: 1.08 | G93: =G92*(1+(F93^(1/12)-1))+E93 -> 41.054014 | I93: =(G93/B93)*100 -> 79.794002 | J93: 90
B94: ='Data Collection Sheet'!$G$92 -> 51.45 | C94: 47362 | F94: 1.08 | G94: =G93*(1+(F94^(1/12)-1))+E94 -> 41.318157 | I94: =(G94/B94)*100 -> 80.307399 | J94: 90 | AZ94: 51.25
B95: ='Data Collection Sheet'!$G$92 -> 51.45 | C95: 47392 | F95: 1.08 | G95: =G94*(1+(F95^(1/12)-1))+E95 -> 41.583999 | I95: =(G95/B95)*100 -> 80.824099 | J95: 90 | AZ95: 35.08
B96: ='Data Collection Sheet'!$G$92 -> 51.45 | C96: 47423 | F96: 1.08 | G96: =G95*(1+(F96^(1/12)-1))+E96 -> 41.851552 | I96: =(G96/B96)*100 -> 81.344124 | J96: 90
B97: ='Data Collection Sheet'!$G$92 -> 51.45 | C97: 47453 | F97: 1.08 | G97: =G96*(1+(F97^(1/12)-1))+E97 -> 42.120826 | I97: =(G97/B97)*100 -> 81.867495 | J97: 90
B98: ='Data Collection Sheet'!$G$92 -> 51.45 | C98: 47484 | F98: 1.08 | G98: =G97*(1+(F98^(1/12)-1))+E98 -> 42.391833 | I98: =(G98/B98)*100 -> 82.394232 | J98: 90
B99: ='Data Collection Sheet'!$G$92 -> 51.45 | C99: 47515 | F99: 1.08 | G99: =G98*(1+(F99^(1/12)-1))+E99 -> 42.664583 | I99: =(G99/B99)*100 -> 82.924359 | J99: 90
B100: ='Data Collection Sheet'!$G$92 -> 51.45 | C100: 47543 | F100: 1.08 | G100: =G99*(1+(F100^(1/12)-1))+E100 -> 42.939088 | I100: =(G100/B100)*100 -> 83.457897 | J100: 90
...

Sheet MacPark-DC
A1: MacPark (12% YoY) | B1: Total Storage | C1: Month | D1: In Use | E1: Change (TB) | F1: Growth (%) | G1: Forecast | H1: In use (%) | I1: Forecast (%) | J1: Max %
A2: X50+M20+M20 | B2: =('Data Collection Sheet'!G25+'Data Collection Sheet'!G55) -> 130.5 | C2: 44562 | D2: =('Data Collection Sheet'!I24+'Data Collection Sheet'!I54) -> 103.7358 | H2: =(D2/B2)*100 -> 79.491034 | J2: 90
B3: 128.24 | C3: 44593 | D3: =('Data Collection Sheet'!J24+'Data Collection Sheet'!J54) -> 100.557 | H3: =(D3/B3)*100 -> 78.413132 | J3: 90
B4: 128.24 | C4: 44621 | D4: =('Data Collection Sheet'!K24+'Data Collection Sheet'!K54) -> 112.279 | H4: =(D4/B4)*100 -> 87.553805 | J4: 90
A5: Added NR M20 | B5: =('Data Collection Sheet'!G25+'Data Collection Sheet'!G55+'Data Collection Sheet'!G69) -> 168.05 | C5: 44652 | D5: ='Data Collection Sheet'!L24+'Data Collection Sheet'!L54+'Data Collection Sheet'!L68 -> 112.96 | H5: =(D5/B5)*100 -> 67.21809 | J5: 90
A6: Add Rimini ENV | B6: 165.09 | C6: 44682 | D6: ='Data Collection Sheet'!M24+'Data Collection Sheet'!M54+'Data Collection Sheet'!M68 -> 111.12 | E6: 1 | H6: =(D6/B6)*100 -> 67.308741 | J6: 90
B7: 165.09 | C7: 44713 | D7: ='Data Collection Sheet'!N24+'Data Collection Sheet'!N54+'Data Collection Sheet'!N68 -> 110.54 | H7: =(D7/B7)*100 -> 66.957417 | J7: 90
B8: 165.09 | C8: 44743 | D8: ='Data Collection Sheet'!O24+'Data Collection Sheet'!O54+'Data Collection Sheet'!O68 -> 111.552 | H8: =(D8/B8)*100 -> 67.570416 | J8: 90
A9: Removed staging Marketing Folder | B9: 165.09 | C9: 44774 | D9: ='Data Collection Sheet'!P24+'Data Collection Sheet'!P54+'Data Collection Sheet'!P68 -> 92.25 | H9: =(D9/B9)*100 -> 55.878612 | J9: 90
B10: 165.09 | C10: 44805 | D10: ='Data Collection Sheet'!Q24+'Data Collection Sheet'!Q54+'Data Collection Sheet'!Q68 -> 93.39 | H10: =(D10/B10)*100 -> 56.569144 | J10: 90
B11: 165.09 | C11: 44835 | D11: ='Data Collection Sheet'!R24+'Data Collection Sheet'!R54+'Data Collection Sheet'!R68 -> 95.46 | H11: =(D11/B11)*100 -> 57.823006 | J11: 90
A12: Migrate VNX - data1/MFG 10TB - Done | B12: 165.09 | C12: 44866 | D12: ='Data Collection Sheet'!S24+'Data Collection Sheet'!S54+'Data Collection Sheet'!S68 -> 98.65 | H12: =(D12/B12)*100 -> 59.755285 | J12: 90
A13: Migrate VNX - data2/Marketing 15TB - sync 99% | B13: 165.09 | C13: 44896 | D13: ='Data Collection Sheet'!T24+'Data Collection Sheet'!T54+'Data Collection Sheet'!T68 -> 115.8906 | H13: =(D13/B13)*100 -> 70.198437 | J13: 90
B14: 165.09 | C14: 44927 | D14: ='Data Collection Sheet'!U24+'Data Collection Sheet'!U54+'Data Collection Sheet'!U68 -> 119.8 | H14: =(D14/B14)*100 -> 72.566479 | J14: 90
A15: Migrate VNX - data2/Marketing 15TB - Done | B15: 165.09 | C15: 44958 | D15: ='Data Collection Sheet'!V24+'Data Collection Sheet'!V54+'Data Collection Sheet'!V68 -> 128.9 | H15: =(D15/B15)*100 -> 78.078624 | J15: 90
B16: 165.09 | C16: 44986 | D16: ='Data Collection Sheet'!W24+'Data Collection Sheet'!W54+'Data Collection Sheet'!W68 -> 126.29 | H16: =(D16/B16)*100 -> 76.497668 | J16: 90
B17: 165.09 | C17: 45017 | D17: ='Data Collection Sheet'!X24+'Data Collection Sheet'!X54+'Data Collection Sheet'!X68 -> 126.98 | H17: =(D17/B17)*100 -> 76.915622 | J17: 90
A18: Remove EV Servers since re-hydration completed, -10TB - Done | B18: 165.09 | C18: 45047 | D18: ='Data Collection Sheet'!Y24+'Data Collection Sheet'!Y54+'Data Collection Sheet'!Y68 -> 109.42 | H18: =(D18/B18)*100 -> 66.278999 | J18: 90
B19: 165.09 | C19: 45078 | D19: ='Data Collection Sheet'!Z24+'Data Collection Sheet'!Z54+'Data Collection Sheet'!Z68 -> 109.268 | H19: =(D19/B19)*100 -> 66.186928 | J19: 90
B20: 165.09 | C20: 45108 | D20: ='Data Collection Sheet'!AA24+'Data Collection Sheet'!AA54+'Data Collection Sheet'!AA68 -> 111.39 | H20: =(D20/B20)*100 -> 67.472288 | J20: 90
B21: 165.09 | C21: 45139 | D21: ='Data Collection Sheet'!AB24+'Data Collection Sheet'!AB54+'Data Collection Sheet'!AB68 -> 113.54 | H21: =(D21/B21)*100 -> 68.774608 | J21: 90
B22: 165.09 | C22: 45170 | D22: ='Data Collection Sheet'!AC24+'Data Collection Sheet'!AC54+'Data Collection Sheet'!AC68 -> 114.47 | H22: =(D22/B22)*100 -> 69.337937 | J22: 90
B23: 165.1 | C23: 45200 | D23: ='Data Collection Sheet'!AD24+'Data Collection Sheet'!AD54+'Data Collection Sheet'!AD68 -> 114.53 | H23: =(D23/B23)*100 -> 69.370079 | J23: 90
B24: 165.1 | C24: 45231 | D24: ='Data Collection Sheet'!AE24+'Data Collection Sheet'!AE54+'Data Collection Sheet'!AE68 -> 117.82 | H24: =(D24/B24)*100 -> 71.36281 | J24: 90
B25: 165.1 | C25: 45261 | D25: ='Data Collection Sheet'!AF24+'Data Collection Sheet'!AF54+'Data Collection Sheet'!AF68 -> 123.89 | H25: =(D25/B25)*100 -> 75.03937 | J25: 90
B26: 165.1 | C26: 45292 | D26: ='Data Collection Sheet'!AG24+'Data Collection Sheet'!AG54+'Data Collection Sheet'!AG68 -> 125.96 | H26: =(D26/B26)*100 -> 76.293156 | J26: 90
A27: Move aun-nbm-prd01 & coh-srv-nbm01 to MacPark | B27: 165.1 | C27: 45323 | D27: ='Data Collection Sheet'!AH24+'Data Collection Sheet'!AH54+'Data Collection Sheet'!AH68 -> 126.26 | E27: 1 | H27: =(D27/B27)*100 -> 76.474864 | J27: 90
A28: Windchill 45TB front-end (3-DEV Env. each 9,3 TB on disk) (assum 1,6 compressed) | B28: 165.1 | C28: 45352 | D28: ='Data Collection Sheet'!AI24+'Data Collection Sheet'!AI54+'Data Collection Sheet'!AI68 -> 123.43 | E28: 9 | H28: =(D28/B28)*100 -> 74.760751 | J28: 90
B29: 165.1 | C29: 45383 | D29: ='Data Collection Sheet'!AJ24+'Data Collection Sheet'!AJ54+'Data Collection Sheet'!AJ68 -> 125.36 | H29: =(D29/B29)*100 -> 75.92974 | J29: 90
A30: Refreshed BIEUAT01 env and additional 2TB required | B30: 165.1 | C30: 45413 | D30: ='Data Collection Sheet'!AK24+'Data Collection Sheet'!AK54+'Data Collection Sheet'!AK68 -> 123.05 | H30: =(D30/B30)*100 -> 74.530588 | J30: 90
A31: Move AUM-FPS-PRD03 from aum-pc-prd02 to aum-pc-prd03. New ERPTST01 env with snapclone. Windchill DR env after re-vaulting. | B31: 165.1 | C31: 45444 | D31: ='Data Collection Sheet'!AL24+'Data Collection Sheet'!AL54+'Data Collection Sheet'!AL68 -> 131.27 | H31: =(D31/B31)*100 -> 79.509388 | J31: 90
B32: 165.1 | C32: 45474 | D32: ='Data Collection Sheet'!AM24+'Data Collection Sheet'!AM54+'Data Collection Sheet'!AM68 -> 131.82 | H32: =(D32/B32)*100 -> 79.84252 | J32: 90
B33: 165.1 | C33: 45505 | D33: ='Data Collection Sheet'!AN24+'Data Collection Sheet'!AN54+'Data Collection Sheet'!AN68 -> 132.93 | H33: =(D33/B33)*100 -> 80.514839 | J33: 90
B34: 165.1 | C34: 45536 | D34: ='Data Collection Sheet'!AO24+'Data Collection Sheet'!AO54+'Data Collection Sheet'!AO68 -> 136.16 | H34: =(D34/B34)*100 -> 82.47123 | J34: 90
B35: 165.1 | C35: 45566 | D35: ='Data Collection Sheet'!AP24+'Data Collection Sheet'!AP54+'Data Collection Sheet'!AP68 -> 123.09 | H35: =(D35/B35)*100 -> 74.554815 | J35: 90
B36: 165.1 | C36: 45597 | D36: ='Data Collection Sheet'!AQ24+'Data Collection Sheet'!AQ54+'Data Collection Sheet'!AQ68 -> 123.34 | H36: =(D36/B36)*100 -> 74.706239 | J36: 90
B37: 165.1 | C37: 45627 | D37: ='Data Collection Sheet'!AR24+'Data Collection Sheet'!AR54+'Data Collection Sheet'!AR68 -> 126.76 | H37: =(D37/B37)*100 -> 76.77771 | J37: 90
B38: 165.1 | C38: 45658 | D38: ='Data Collection Sheet'!AS24+'Data Collection Sheet'!AS54+'Data Collection Sheet'!AS68 -> 130.37 | H38: =(D38/B38)*100 -> 78.964264 | J38: 90
B39: 165.1 | C39: 45689 | D39: ='Data Collection Sheet'!AT24+'Data Collection Sheet'!AT54+'Data Collection Sheet'!AT68 -> 128.59 | H39: =(D39/B39)*100 -> 77.88613 | J39: 90
B40: 165.1 | C40: 45717 | D40: ='Data Collection Sheet'!AU24+'Data Collection Sheet'!AU54+'Data Collection Sheet'!AU68 -> 128.59 | H40: =(D40/B40)*100 -> 77.88613 | J40: 90
A41: from 15% to 8% increase | B41: 165.1 | C41: 45748 | D41: ='Data Collection Sheet'!AV24+'Data Collection Sheet'!AV54+'Data Collection Sheet'!AU68 -> 127.99 | H41: =(D41/B41)*100 -> 77.522714 | J41: 90
A42: End-support-contract AUM-PC-PRD03 | B42: 165.1 | C42: 45778 | D42: ='Data Collection Sheet'!AW24+'Data Collection Sheet'!AW54+'Data Collection Sheet'!AW68 -> 132.56 | H42: =(D42/B42)*100 -> 80.290733 | J42: 90
B43: 165.1 | C43: 45809 | D43: ='Data Collection Sheet'!AX24+'Data Collection Sheet'!AX54+'Data Collection Sheet'!AX68 -> 133.54 | H43: =(D43/B43)*100 -> 80.884313 | J43: 90
B44: 165.1 | C44: 45839 | D44: ='Data Collection Sheet'!AY24+'Data Collection Sheet'!AY54+'Data Collection Sheet'!AY68 -> 133.42 | H44: =(D44/B44)*100 -> 80.811629 | J44: 90
B45: 165.1 | C45: 45870 | D45: ='Data Collection Sheet'!AZ24+'Data Collection Sheet'!AZ54+'Data Collection Sheet'!AZ68 -> 134.1 | H45: =(D45/B45)*100 -> 81.223501 | J45: 90
B46: 165.1 | C46: 45901 | D46: ='Data Collection Sheet'!BA24+'Data Collection Sheet'!BA54+'Data Collection Sheet'!BA68 -> 134.95 | H46: =(D46/B46)*100 -> 81.73834 | J46: 90
B47: 165.1 | C47: 45931 | D47: ='Data Collection Sheet'!BB24+'Data Collection Sheet'!BB54+'Data Collection Sheet'!BB68 -> 133.83 | H47: =(D47/B47)*100 -> 81.059964 | J47: 90
B48: 165.1 | C48: 45962 | D48: ='Data Collection Sheet'!BC24+'Data Collection Sheet'!BC54+'Data Collection Sheet'!BC68 -> 135.77 | H48: =(D48/B48)*100 -> 82.235009 | J48: 90
B49: 165.1 | C49: 45992 | D49: ='Data Collection Sheet'!BD24+'Data Collection Sheet'!BD54+'Data Collection Sheet'!BD68 -> 132.61 | H49: =(D49/B49)*100 -> 80.321018 | J49: 90
B50: 165.1 | C50: 46023 | D50: ='Data Collection Sheet'!BE24+'Data Collection Sheet'!BE54+'Data Collection Sheet'!BE68 -> 134.37 | H50: =(D50/B50)*100 -> 81.387038 | J50: 90
B51: 165.1 | C51: 46054 | D51: ='Data Collection Sheet'!BF24+'Data Collection Sheet'!BF54+'Data Collection Sheet'!BF68 -> 135.87 | H51: =(D51/B51)*100 -> 82.295578 | J51: 90
B52: 165.1 | C52: 46082 | D52: ='Data Collection Sheet'!BG24+'Data Collection Sheet'!BG54+'Data Collection Sheet'!BG68 -> 138.11 | H52: =(D52/B52)*100 -> 83.652332 | J52: 90
B53: 165.1 | C53: 46113 | D53: ='Data Collection Sheet'!BH24+'Data Collection Sheet'!BH54+'Data Collection Sheet'!BH68 -> 137.2 | H53: =(D53/B53)*100 -> 83.101151 | J53: 90
B54: 165.1 | C54: 46143 | D54: ='Data Collection Sheet'!BI24+'Data Collection Sheet'!BI54+'Data Collection Sheet'!BH68 -> 130.99 | H54: =(D54/B54)*100 -> 79.339794 | J54: 90
A55: Add aum-pc-prd05 - 459.94 | B55: =165.1 -> 165.1 | C55: 46174 | D55: ='Data Collection Sheet'!BJ24+'Data Collection Sheet'!BJ54+'Data Collection Sheet'!BJ68+'Data Collection Sheet'!BJ77 -> 210.37 | H55: =(D55/B55)*100 -> 127.41975 | J55: 90
B56: =165.1+459.94 -> 625.04 | C56: 46204 | D56: ='Data Collection Sheet'!BK24+'Data Collection Sheet'!BK54+'Data Collection Sheet'!BK68+'Data Collection Sheet'!BK77 -> 211.23 | H56: =(D56/B56)*100 -> 33.794637 | J56: 90
B57: =165.1+459.94 -> 625.04 | C57: 46235 | D57: ='Data Collection Sheet'!BL$24+'Data Collection Sheet'!BL$54+'Data Collection Sheet'!BL$68+'Data Collection Sheet'!BL$77 -> 211.36 | F57: 6.08 | G57: =D57 -> 211.36 | H57: =(D57/B57)*100 -> 33.815436 | I57: =(G57/B57)*100 -> 33.815436 | J57: 90
B58: =165.1+459.94 -> 625.04 | C58: 46266 | F58: 7.08 | G58: =D58 -> 0 | H58: =(D58/B58)*100 -> 0 | I58: =(G58/B58)*100 -> 0 | J58: 90
B59: =165.1+459.94 -> 625.04 | C59: 46296 | F59: 1.08 | G59: =G58*(1+(F59^(1/12)-1))+E59 -> 0 | I59: =(G59/B59)*100 -> 0 | J59: 90
B60: =165.1+459.94 -> 625.04 | C60: 46327 | F60: 1.08 | G60: =G59*(1+(F60^(1/12)-1))+E60 -> 0 | I60: =(G60/B60)*100 -> 0 | J60: 90
B61: =165.1+459.94 -> 625.04 | C61: 46357 | F61: 1.08 | G61: =G60*(1+(F61^(1/12)-1))+E61 -> 0 | I61: =(G61/B61)*100 -> 0 | J61: 90
B62: =165.1+459.94 -> 625.04 | C62: 46388 | F62: 1.08 | G62: =G61*(1+(F62^(1/12)-1))+E62 -> 0 | I62: =(G62/B62)*100 -> 0 | J62: 90
B63: =165.1+459.94 -> 625.04 | C63: 46419 | F63: 1.08 | G63: =G62*(1+(F63^(1/12)-1))+E63 -> 0 | I63: =(G63/B63)*100 -> 0 | J63: 90
B64: =165.1+459.94 -> 625.04 | C64: 46447 | F64: 1.08 | G64: =G63*(1+(F64^(1/12)-1))+E64 -> 0 | I64: =(G64/B64)*100 -> 0 | J64: 90
B65: =165.1+459.94 -> 625.04 | C65: 46478 | F65: 1.08 | G65: =G64*(1+(F65^(1/12)-1))+E65 -> 0 | I65: =(G65/B65)*100 -> 0 | J65: 90
B66: =165.1+459.94 -> 625.04 | C66: 46508 | F66: 1.08 | G66: =G65*(1+(F66^(1/12)-1))+E66 -> 0 | I66: =(G66/B66)*100 -> 0 | J66: 90
B67: =165.1+459.94 -> 625.04 | C67: 46539 | F67: 1.08 | G67: =G66*(1+(F67^(1/12)-1))+E67 -> 0 | I67: =(G67/B67)*100 -> 0 | J67: 90
A68: End-support-contract AUM-PC-PRD01 | B68: =165.1+459.94 -> 625.04 | C68: 46569 | F68: 1.08 | G68: =G67*(1+(F68^(1/12)-1))+E68 -> 0 | I68: =(G68/B68)*100 -> 0 | J68: 90
A69: End-support-contract AUM-PC-PRD02 | B69: =165.1+459.94 -> 625.04 | C69: 46600 | F69: 1.08 | G69: =G68*(1+(F69^(1/12)-1))+E69 -> 0 | I69: =(G69/B69)*100 -> 0 | J69: 90
A70: REPLACE FLASHSTACK | B70: =165.1+459.94 -> 625.04 | C70: 46631 | F70: 1.08 | G70: =G69*(1+(F70^(1/12)-1))+E70 -> 0 | I70: =(G70/B70)*100 -> 0 | J70: 90
A71: Order new FlashStack | B71: =165.1+459.94 -> 625.04 | C71: 46661 | F71: 1.08 | G71: =G70*(1+(F71^(1/12)-1))+E71 -> 0 | I71: =(G71/B71)*100 -> 0 | J71: 90
B72: =165.1+459.94 -> 625.04 | C72: 46692 | F72: 1.08 | G72: =G71*(1+(F72^(1/12)-1))+E72 -> 0 | I72: =(G72/B72)*100 -> 0 | J72: 90
B73: =165.1+459.94 -> 625.04 | C73: 46722 | F73: 1.08 | G73: =G72*(1+(F73^(1/12)-1))+E73 -> 0 | I73: =(G73/B73)*100 -> 0 | J73: 90
B74: =165.1+459.94 -> 625.04 | C74: 46753 | F74: 1.08 | G74: =G73*(1+(F74^(1/12)-1))+E74 -> 0 | I74: =(G74/B74)*100 -> 0 | J74: 90
B75: =165.1+459.94 -> 625.04 | C75: 46784 | F75: 1.08 | G75: =G74*(1+(F75^(1/12)-1))+E75 -> 0 | I75: =(G75/B75)*100 -> 0 | J75: 90
B76: =165.1+459.94 -> 625.04 | C76: 46813 | F76: 1.08 | G76: =G75*(1+(F76^(1/12)-1))+E76 -> 0 | I76: =(G76/B76)*100 -> 0 | J76: 90
B77: =165.1+459.94 -> 625.04 | C77: 46844 | F77: 1.08 | G77: =G76*(1+(F77^(1/12)-1))+E77 -> 0 | I77: =(G77/B77)*100 -> 0 | J77: 90
B78: =165.1+459.94 -> 625.04 | C78: 46874 | F78: 1.08 | G78: =G77*(1+(F78^(1/12)-1))+E78 -> 0 | I78: =(G78/B78)*100 -> 0 | J78: 90
B79: =165.1+459.94 -> 625.04 | C79: 46905 | F79: 1.08 | G79: =G78*(1+(F79^(1/12)-1))+E79 -> 0 | I79: =(G79/B79)*100 -> 0 | J79: 90
B80: =165.1+459.94 -> 625.04 | C80: 46935 | F80: 1.08 | G80: =G79*(1+(F80^(1/12)-1))+E80 -> 0 | I80: =(G80/B80)*100 -> 0 | J80: 90

Sheet Denver (Unity)
A1: Denver (12% YoY) | B1: Total Storage | C1: Month | D1: In Use | E1: Change (TB) | F1: Growth (%) | G1: Forecast | H1: In use (%) | I1: Forecast (%) | J1: Max %
A2: USD-UNITY-PRD01 POOL1 | B2: 25.7 | C2: 45292 | D2: 14.15 | H2: =(D2/B2)*100 -> 55.058366 | J2: 90
B3: 25.7 | C3: 45323 | D3: 14.2 | H3: =(D3/B3)*100 -> 55.252918 | J3: 90
B4: 25.7 | C4: 45352 | D4: 14.2 | H4: =(D4/B4)*100 -> 55.252918 | J4: 90
B5: 25.7 | C5: 45383 | D5: 14.6 | H5: =(D5/B5)*100 -> 56.809339 | J5: 90
B6: 25.7 | C6: 45413 | D6: 14.4 | H6: =(D6/B6)*100 -> 56.031128 | J6: 90
B7: 25.7 | C7: 45444 | D7: 14.6 | H7: =(D7/B7)*100 -> 56.809339 | J7: 90
B8: 25.7 | C8: 45474 | D8: 15 | H8: =(D8/B8)*100 -> 58.365759 | J8: 90
B9: 25.7 | C9: 45505 | D9: 15.1 | H9: =(D9/B9)*100 -> 58.754864 | J9: 90
B10: 25.7 | C10: 45536 | D10: 15.2 | H10: =(D10/B10)*100 -> 59.143969 | J10: 90
B11: 25.7 | C11: 45566 | D11: 15.2 | H11: =(D11/B11)*100 -> 59.143969 | J11: 90
B12: 25.7 | C12: 45597 | D12: 15.3 | H12: =(D12/B12)*100 -> 59.533074 | J12: 90
B13: 25.7 | C13: 45627 | D13: 15.3 | H13: =(D13/B13)*100 -> 59.533074 | J13: 90
B14: 25.7 | C14: 45658 | D14: 15.4 | H14: =(D14/B14)*100 -> 59.922179 | J14: 90
... B25: 25.7 | C25: 45992 | D25: 16.2 | H25: =(D25/B25)*100 -> 63.035019 | J25: 90
A26: Move 7TB FileServices to AWS or HQ | B26: 25.7 | C26: 46023 | D26: 16.2 | H26: =(D26/B26)*100 -> 63.035019 | J26: 90
B27: 25.7 | C27: 46054 | D27: 16.2 | H27: =(D27/B27)*100 -> 63.035019 | J27: 90
B28: 25.7 | C28: 46082 | D28: 16.2 | H28: =(D28/B28)*100 -> 63.035019 | J28: 90
B29: 25.7 | C29: 46113 | D29: 16.2 | H29: =(D29/B29)*100 -> 63.035019 | J29: 90
B30: 25.7 | C30: 46143 | D30: 16.2 | H30: =(D30/B30)*100 -> 63.035019 | J30: 90
B31: 25.7 | C31: 46174 | D31: 16.2 | H31: =(D31/B31)*100 -> 63.035019 | J31: 90
B32: 25.7 | C32: 46204 | D32: 16.3 | H32: =(D32/B32)*100 -> 63.424125 | J32: 90
B33: 25.7 | C33: 46235 | D33: 16.3 | F33: 1.08 | G33: =D33 -> 16.3 | H33: =(D33/B33)*100 -> 63.424125 | I33: =(G33/B33)*100 -> 63.424125 | J33: 90
B34: 25.7 | C34: 46266 | F34: 1.08 | G34: =G33*(1+(F34^(1/12)-1))+E34 -> 16.404875 | I34: =(G34/B34)*100 -> 63.832197 | J34: 90
B35: 25.7 | C35: 46296 | F35: 1.08 | G35: =G34*(1+(F35^(1/12)-1))+E35 -> 16.510424 | I35: =(G35/B35)*100 -> 64.242896 | J35: 90
B36: 25.7 | C36: 46327 | F36: 1.08 | G36: =G35*(1+(F36^(1/12)-1))+E36 -> 16.616653 | I36: =(G36/B36)*100 -> 64.656236 | J36: 90
B37: 25.7 | C37: 46357 | F37: 1.08 | G37: =G36*(1+(F37^(1/12)-1))+E37 -> 16.723565 | I37: =(G37/B37)*100 -> 65.072236 | J37: 90
B38: 25.7 | C38: 46388 | F38: 1.08 | G38: =G37*(1+(F38^(1/12)-1))+E38 -> 16.831165 | I38: =(G38/B38)*100 -> 65.490913 | J38: 90
B39: 25.7 | C39: 46419 | F39: 1.08 | G39: =G38*(1+(F39^(1/12)-1))+E39 -> 16.939457 | I39: =(G39/B39)*100 -> 65.912284 | J39: 90
B40: 25.7 | C40: 46447 | F40: 1.08 | G40: =G39*(1+(F40^(1/12)-1))+E40 -> 17.048446 | I40: =(G40/B40)*100 -> 66.336365 | J40: 90
B41: 25.7 | C41: 46478 | F41: 1.08 | G41: =G40*(1+(F41^(1/12)-1))+E41 -> 17.158136 | I41: =(G41/B41)*100 -> 66.763175 | J41: 90
B42: 25.7 | C42: 46508 | F42: 1.08 | G42: =G41*(1+(F42^(1/12)-1))+E42 -> 17.268532 | I42: =(G42/B42)*100 -> 67.192732 | J42: 90
B43: 25.7 | C43: 46539 | F43: 1.08 | G43: =G42*(1+(F43^(1/12)-1))+E43 -> 17.379638 | I43: =(G43/B43)*100 -> 67.625052 | J43: 90
B44: 25.7 | C44: 46569 | F44: 1.08 | G44: =G43*(1+(F44^(1/12)-1))+E44 -> 17.491459 | I44: =(G44/B44)*100 -> 68.060153 | J44: 90
B45: 25.7 | C45: 46600 | F45: 1.08 | G45: =G44*(1+(F45^(1/12)-1))+E45 -> 17.604 | I45: =(G45/B45)*100 -> 68.498054 | J45: 90
... B85: 25.7 | C85: 47818 | F85: 1.08 | G85: =G84*(1+(F85^(1/12)-1))+E85 -> 22.752225 | I85: =(G85/B85)*100 -> 88.530059 | J85: 90

Sheet Denver (HX)
A1: Denver (12% YoY) | B1: Total Storage | C1: Month | D1: In Use | E1: Change (TB) | F1: Growth (%) | G1: Forecast | H1: In use (%) | I1: Forecast (%) | J1: Max %
A2: HyperFlex | B2: =25.7 -> 25.7 | C2: 44562 | D2: ='Data Collection Sheet'!I$124 -> 12.65 | H2: =(D2/B2)*100 -> 49.22179 | J2: 75
B3: =25.7 -> 25.7 | C3: 44593 | D3: ='Data Collection Sheet'!J$124 -> 12.75 | H3: =(D3/B3)*100 -> 49.610895 | J3: 75
B4: =25.7 -> 25.7 | C4: 44621 | D4: ='Data Collection Sheet'!K$124 -> 12.85 | H4: =(D4/B4)*100 -> 50 | J4: 75
B5: =25.7 -> 25.7 | C5: 44652 | D5: ='Data Collection Sheet'!L$124 -> 12.3874 | H5: =(D5/B5)*100 -> 48.2 | J5: 75
B6: =25.7 -> 25.7 | C6: 44682 | D6: ='Data Collection Sheet'!M$124 -> 12.4 | H6: =(D6/B6)*100 -> 48.249027 | J6: 75
A7: Add 10TB Marketing (option-Consumer NAS) | B7: =25.7 -> 25.7 | C7: 44713 | D7: ='Data Collection Sheet'!N$124 -> 12.6 | H7: =(D7/B7)*100 -> 49.027237 | J7: 75
B8: =25.7 -> 25.7 | C8: 44743 | D8: ='Data Collection Sheet'!O$124 -> 12.8 | H8: =(D8/B8)*100 -> 49.805447 | J8: 75
B9: =25.7 -> 25.7 | C9: 44774 | D9: ='Data Collection Sheet'!P$124 -> 11.4 | H9: =(D9/B9)*100 -> 44.357977 | J9: 75
B10: =25.7 -> 25.7 | C10: 44805 | D10: ='Data Collection Sheet'!Q$124 -> 11.8 | H10: =(D10/B10)*100 -> 45.914397 | J10: 75
B11: =25.7 -> 25.7 | C11: 44835 | D11: ='Data Collection Sheet'!R$124 -> 12 | H11: =(D11/B11)*100 -> 46.692607 | J11: 75
B12: =25.7 -> 25.7 | C12: 44866 | D12: ='Data Collection Sheet'!S$124 -> 12.1 | H12: =(D12/B12)*100 -> 47.081712 | J12: 75
B13: =25.7 -> 25.7 | C13: 44896 | D13: ='Data Collection Sheet'!T$124 -> 12.5 | H13: =(D13/B13)*100 -> 48.638132 | J13: 75
B14: =25.7 -> 25.7 | C14: 44927 | D14: ='Data Collection Sheet'!U$124 -> 12.2 | H14: =(D14/B14)*100 -> 47.470817 | J14: 75
B15: =25.7 -> 25.7 | C15: 44958 | D15: ='Data Collection Sheet'!V$124 -> 12.3 | H15: =(D15/B15)*100 -> 47.859922 | J15: 75
B16: =25.7 -> 25.7 | C16: 44986 | D16: ='Data Collection Sheet'!W$124 -> 12 | H16: =(D16/B16)*100 -> 46.692607 | J16: 75
B17: =25.7 -> 25.7 | C17: 45017 | D17: ='Data Collection Sheet'!X$124 -> 11.9 | H17: =(D17/B17)*100 -> 46.303502 | J17: 75
B18: =25.7 -> 25.7 | C18: 45047 | D18: ='Data Collection Sheet'!Y$124 -> 12.1 | H18: =(D18/B18)*100 -> 47.081712 | J18: 75
B19: =25.7 -> 25.7 | C19: 45078 | D19: ='Data Collection Sheet'!Z$124 -> 11.2 | H19: =(D19/B19)*100 -> 43.579767 | J19: 75
B20: =25.7 -> 25.7 | C20: 45108 | D20: ='Data Collection Sheet'!AA$124 -> 11.5 | H20: =(D20/B20)*100 -> 44.747082 | J20: 75
B21: =25.7 -> 25.7 | C21: 45139 | D21: ='Data Collection Sheet'!AB$124 -> 11.7 | H21: =(D21/B21)*100 -> 45.525292 | J21: 75
B22: =25.7 -> 25.7 | C22: 45170 | D22: ='Data Collection Sheet'!AC$124 -> 12 | H22: =(D22/B22)*100 -> 46.692607 | J22: 75
B23: =25.7 -> 25.7 | C23: 45200 | D23: ='Data Collection Sheet'!AD$124 -> 12.2 | H23: =(D23/B23)*100 -> 47.470817 | J23: 75
B24: =25.7 -> 25.7 | C24: 45231 | D24: ='Data Collection Sheet'!AE$124 -> 12.5 | H24: =(D24/B24)*100 -> 48.638132 | J24: 75
B25: =25.7 -> 25.7 | C25: 45261 | D25: ='Data Collection Sheet'!AF$124 -> 12.6 | H25: =(D25/B25)*100 -> 49.027237 | J25: 75
B26: =25.7 -> 25.7 | C26: 45292 | D26: ='Data Collection Sheet'!AG$124 -> 12.2 | H26: =(D26/B26)*100 -> 47.470817 | J26: 75
B27: =25.7 -> 25.7 | C27: 45323 | D27: ='Data Collection Sheet'!AH$124 -> 12.5 | H27: =(D27/B27)*100 -> 48.638132 | J27: 75
B28: =25.7 -> 25.7 | C28: 45352 | D28: ='Data Collection Sheet'!AI$124 -> 12.4 | H28: =(D28/B28)*100 -> 48.249027 | J28: 75
B29: =25.7 -> 25.7 | C29: 45383 | D29: ='Data Collection Sheet'!AJ$124 -> 12.3 | H29: =(D29/B29)*100 -> 47.859922 | J29: 75
B30: =25.7 -> 25.7 | C30: 45413 | D30: ='Data Collection Sheet'!AK$124 -> 11.9 | H30: =(D30/B30)*100 -> 46.303502 | J30: 75
A31: Rehydrate 8TB from CV-archive | B31: =25.7 -> 25.7 | C31: 45444 | D31: ='Data Collection Sheet'!AL$124 -> 11.6 | H31: =(D31/B31)*100 -> 45.136187 | J31: 75
B32: =25.7 -> 25.7 | C32: 45474 | D32: ='Data Collection Sheet'!AM$124 -> 11.7 | H32: =(D32/B32)*100 -> 45.525292 | J32: 75
B33: =25.7 -> 25.7 | C33: 45505 | D33: ='Data Collection Sheet'!AN$124 -> 11.9 | H33: =(D33/B33)*100 -> 46.303502 | J33: 75
B34: =25.7 -> 25.7 | C34: 45536 | D34: ='Data Collection Sheet'!AO$124 -> 11.9 | H34: =(D34/B34)*100 -> 46.303502 | J34: 75
A35: from 12% to 8% increase | B35: =25.7 -> 25.7 | C35: 45566 | D35: ='Data Collection Sheet'!AP$124 -> 12.3 | H35: =(D35/B35)*100 -> 47.859922 | J35: 75
B36: =25.7 -> 25.7 | C36: 45597 | D36: ='Data Collection Sheet'!AQ$124 -> 12.4 | H36: =(D36/B36)*100 -> 48.249027 | J36: 75
B37: =25.7 -> 25.7 | C37: 45627 | D37: ='Data Collection Sheet'!AR$124 -> 12.6 | H37: =(D37/B37)*100 -> 49.027237 | J37: 75
B38: =25.7 -> 25.7 | C38: 45658 | D38: ='Data Collection Sheet'!AS$124 -> 12.6 | H38: =(D38/B38)*100 -> 49.027237 | J38: 75
B39: =25.7 -> 25.7 | C39: 45689 | D39: ='Data Collection Sheet'!AT$124 -> 12.8 | H39: =(D39/B39)*100 -> 49.805447 | J39: 75
B40: =25.7 -> 25.7 | C40: 45717 | D40: ='Data Collection Sheet'!AU$124 -> 12.8 | H40: =(D40/B40)*100 -> 49.805447 | J40: 75
B41: =25.7 -> 25.7 | C41: 45748 | D41: ='Data Collection Sheet'!AV$124 -> 12.7 | H41: =(D41/B41)*100 -> 49.416342 | J41: 75
B42: =25.7 -> 25.7 | C42: 45778 | D42: ='Data Collection Sheet'!AW$124 -> 12.9 | H42: =(D42/B42)*100 -> 50.194553 | J42: 75
B43: =25.7 -> 25.7 | C43: 45809 | D43: ='Data Collection Sheet'!AX$124 -> 12.8 | H43: =(D43/B43)*100 -> 49.805447 | J43: 75
B44: =25.7 -> 25.7 | C44: 45839 | D44: ='Data Collection Sheet'!AY$124 -> 12.3 | H44: =(D44/B44)*100 -> 47.859922 | J44: 75
B45: =25.7 -> 25.7 | C45: 45870 | D45: ='Data Collection Sheet'!AZ$124 -> 12.2 | H45: =(D45/B45)*100 -> 47.470817 | J45: 75
B46: =25.7 -> 25.7 | C46: 45901 | D46: ='Data Collection Sheet'!BA$124 -> 12.3 | H46: =(D46/B46)*100 -> 47.859922 | J46: 75
B47: =25.7 -> 25.7 | C47: 45931 | D47: ='Data Collection Sheet'!BB$124 -> 12.6 | H47: =(D47/B47)*100 -> 49.027237 | J47: 75
B48: =25.7 -> 25.7 | C48: 45962 | D48: ='Data Collection Sheet'!BC$124 -> 12.6 | H48: =(D48/B48)*100 -> 49.027237 | J48: 75
B49: =25.7 -> 25.7 | C49: 45992 | D49: ='Data Collection Sheet'!BD$124 -> 12.8 | H49: =(D49/B49)*100 -> 49.805447 | J49: 75
B50: =25.7 -> 25.7 | C50: 46023 | D50: ='Data Collection Sheet'!BE$124 -> 12.8 | H50: =(D50/B50)*100 -> 49.805447 | J50: 75
B51: =25.7 -> 25.7 | C51: 46054 | D51: ='Data Collection Sheet'!BF$124 -> 12.8 | H51: =(D51/B51)*100 -> 49.805447 | J51: 75
B52: =25.7 -> 25.7 | C52: 46082 | D52: ='Data Collection Sheet'!BG$124 -> 12.8 | H52: =(D52/B52)*100 -> 49.805447 | J52: 75
A53: Consolidate Mexico / Panama = 1TB each | B53: =25.7 -> 25.7 | C53: 46113 | D53: ='Data Collection Sheet'!BH$124 -> 12.8 | H53: =(D53/B53)*100 -> 49.805447 | J53: 75
B54: =25.7 -> 25.7 | C54: 46143 | D54: ='Data Collection Sheet'!BI$124 -> 12.8 | H54: =(D54/B54)*100 -> 49.805447 | J54: 75
B55: =25.7 -> 25.7 | C55: 46174 | D55: ='Data Collection Sheet'!BJ$124 -> 12.8 | H55: =(D55/B55)*100 -> 49.805447 | J55: 75
B56: =25.7 -> 25.7 | C56: 46204 | D56: ='Data Collection Sheet'!BK$124 -> 12.9 | F56: 6.08 | G56: =D56 -> 12.9 | H56: =(D56/B56)*100 -> 50.194553 | I56: =(G56/B56)*100 -> 50.194553 | J56: 75
B57: =25.7 -> 25.7 | C57: 46235 | D57: ='Data Collection Sheet'!BL$124 -> 12.8 | F57: 7.08 | G57: =D57 -> 12.8 | H57: =(D57/B57)*100 -> 49.805447 | I57: =(G57/B57)*100 -> 49.805447 | J57: 75
A58: Initial HX is 8 years old | B58: =25.7 -> 25.7 | C58: 46266 | F58: 1.08 | G58: =G57*(1+(F58^(1/12)-1))+E58 -> 12.882356 | I58: =(G58/B58)*100 -> 50.125897 | J58: 75
B59: =25.7 -> 25.7 | C59: 46296 | F59: 1.08 | G59: =G58*(1+(F59^(1/12)-1))+E59 -> 12.965241 | I59: =(G59/B59)*100 -> 50.448409 | J59: 75
B60: =25.7 -> 25.7 | C60: 46327 | F60: 1.08 | G60: =G59*(1+(F60^(1/12)-1))+E60 -> 13.04866 | I60: =(G60/B60)*100 -> 50.772995 | J60: 75
B61: =25.7 -> 25.7 | C61: 46357 | F61: 1.08 | G61: =G60*(1+(F61^(1/12)-1))+E61 -> 13.132615 | I61: =(G61/B61)*100 -> 51.09967 | J61: 75
B62: =25.7 -> 25.7 | C62: 46388 | F62: 1.08 | G62: =G61*(1+(F62^(1/12)-1))+E62 -> 13.217111 | I62: =(G62/B62)*100 -> 51.428447 | J62: 75
B63: =25.7 -> 25.7 | C63: 46419 | F63: 1.08 | G63: =G62*(1+(F63^(1/12)-1))+E63 -> 13.30215 | I63: =(G63/B63)*100 -> 51.759339 | J63: 75
B64: =25.7 -> 25.7 | C64: 46447 | F64: 1.08 | G64: =G63*(1+(F64^(1/12)-1))+E64 -> 13.387737 | I64: =(G64/B64)*100 -> 52.09236 | J64: 75
B65: =25.7 -> 25.7 | C65: 46478 | F65: 1.08 | G65: =G64*(1+(F65^(1/12)-1))+E65 -> 13.473874 | I65: =(G65/B65)*100 -> 52.427524 | J65: 75
B66: =25.7 -> 25.7 | C66: 46508 | F66: 1.08 | G66: =G65*(1+(F66^(1/12)-1))+E66 -> 13.560565 | I66: =(G66/B66)*100 -> 52.764845 | J66: 75
B67: =25.7 -> 25.7 | C67: 46539 | F67: 1.08 | G67: =G66*(1+(F67^(1/12)-1))+E67 -> 13.647814 | I67: =(G67/B67)*100 -> 53.104335 | J67: 75
B68: =25.7 -> 25.7 | C68: 46569 | F68: 1.08 | G68: =G67*(1+(F68^(1/12)-1))+E68 -> 13.735625 | I68: =(G68/B68)*100 -> 53.44601 | J68: 75
B69: =25.7 -> 25.7 | C69: 46600 | F69: 1.08 | G69: =G68*(1+(F69^(1/12)-1))+E69 -> 13.824 | I69: =(G69/B69)*100 -> 53.789883 | J69: 75
B70: =25.7 -> 25.7 | C70: 46631 | F70: 1.08 | G70: =G69*(1+(F70^(1/12)-1))+E70 -> 13.912944 | I70: =(G70/B70)*100 -> 54.135969 | J70: 75
... B109: =25.7 -> 25.7 | C109: 47818 | F109: 1.08 | G109: =G108*(1+(F109^(1/12)-1))+E109 -> 17.866778 | I109: =(G109/B109)*100 -> 69.520537 | J109: 75

Sheet Denver (ESX)
A1: Denver (12% YoY) | B1: Total Storage | C1: Month | D1: In Use | E1: Change (TB) | F1: Growth (%) | G1: Forecast | H1: In use (%) | I1: Forecast (%) | J1: Max %
A2: USD-UNITY-PRD01 UNS | B2: =25.7-10.3 -> 15.4 | C2: 44562 | D2: ='Data Collection Sheet'!I$112 -> 8.4 | H2: =(D2/B2)*100 -> 54.545455 | J2: 90
B3: =25.7-10.3 -> 15.4 | C3: 44593 | D3: ='Data Collection Sheet'!J$112 -> 8.5 | H3: =(D3/B3)*100 -> 55.194805 | J3: 90
B4: =25.7-10.3 -> 15.4 | C4: 44621 | D4: ='Data Collection Sheet'!K$112 -> 8.6 | H4: =(D4/B4)*100 -> 55.844156 | J4: 90
B5: =25.7-10.3 -> 15.4 | C5: 44652 | D5: ='Data Collection Sheet'!L$112 -> 7.5 | H5: =(D5/B5)*100 -> 48.701299 | J5: 90
B6: =25.7-10.3 -> 15.4 | C6: 44682 | D6: ='Data Collection Sheet'!M$112 -> 7.6 | H6: =(D6/B6)*100 -> 49.350649 | J6: 90
B7: =25.7-10.3 -> 15.4 | C7: 44713 | D7: ='Data Collection Sheet'!N$112 -> 7.6 | H7: =(D7/B7)*100 -> 49.350649 | J7: 90
B8: =25.7-10.3 -> 15.4 | C8: 44743 | D8: ='Data Collection Sheet'!O$112 -> 7.6 | H8: =(D8/B8)*100 -> 49.350649 | J8: 90
B9: =25.7-10.3 -> 15.4 | C9: 44774 | D9: ='Data Collection Sheet'!P$112 -> 7.6 | H9: =(D9/B9)*100 -> 49.350649 | J9: 90
B10: =25.7-10.3 -> 15.4 | C10: 44805 | D10: ='Data Collection Sheet'!Q$112 -> 7.6 | H10: =(D10/B10)*100 -> 49.350649 | J10: 90
B11: =25.7-10.3 -> 15.4 | C11: 44835 | D11: ='Data Collection Sheet'!R$112 -> 7.6 | H11: =(D11/B11)*100 -> 49.350649 | J11: 90
B12: =25.7-10.3 -> 15.4 | C12: 44866 | D12: ='Data Collection Sheet'!S$112 -> 7.6 | H12: =(D12/B12)*100 -> 49.350649 | J12: 90
B13: =25.7-10.3 -> 15.4 | C13: 44896 | D13: ='Data Collection Sheet'!T$112 -> 7.6 | H13: =(D13/B13)*100 -> 49.350649 | J13: 90
B14: =25.7-10.3 -> 15.4 | C14: 44927 | D14: ='Data Collection Sheet'!U$112 -> 7.68 | H14: =(D14/B14)*100 -> 49.87013 | J14: 90
B15: =25.7-10.3 -> 15.4 | C15: 44958 | D15: ='Data Collection Sheet'!V$112 -> 7.73 | H15: =(D15/B15)*100 -> 50.194805 | J15: 90
B16: =25.7-10.3 -> 15.4 | C16: 44986 | D16: ='Data Collection Sheet'!W$112 -> 7.79 | H16: =(D16/B16)*100 -> 50.584416 | J16: 90
B17: =25.7-10.3 -> 15.4 | C17: 45017 | D17: ='Data Collection Sheet'!X$112 -> 7.95 | H17: =(D17/B17)*100 -> 51.623377 | J17: 90
B18: =25.7-10.3 -> 15.4 | C18: 45047 | D18: ='Data Collection Sheet'!Y$112 -> 8.09 | H18: =(D18/B18)*100 -> 52.532468 | J18: 90
B19: =25.7-10.3 -> 15.4 | C19: 45078 | D19: ='Data Collection Sheet'!Z$112 -> 8.15 | H19: =(D19/B19)*100 -> 52.922078 | J19: 90
B20: =25.7-10.3 -> 15.4 | C20: 45108 | D20: ='Data Collection Sheet'!AA$112 -> 8.2 | H20: =(D20/B20)*100 -> 53.246753 | J20: 90
B21: =25.7-10.3 -> 15.4 | C21: 45139 | D21: ='Data Collection Sheet'!AB$112 -> 8.32 | H21: =(D21/B21)*100 -> 54.025974 | J21: 90
B22: =25.7-10.3 -> 15.4 | C22: 45170 | D22: ='Data Collection Sheet'!AC$112 -> 8.26 | H22: =(D22/B22)*100 -> 53.636364 | J22: 90
B23: =25.7-10.3 -> 15.4 | C23: 45200 | D23: ='Data Collection Sheet'!AD$112 -> 8.45 | H23: =(D23/B23)*100 -> 54.87013 | J23: 90
B24: =25.7-10.3 -> 15.4 | C24: 45231 | D24: ='Data Collection Sheet'!AE$112 -> 8.45 | H24: =(D24/B24)*100 -> 54.87013 | J24: 90
B25: =25.7-10.3 -> 15.4 | C25: 45261 | D25: ='Data Collection Sheet'!AF$112 -> 8.48 | H25: =(D25/B25)*100 -> 55.064935 | J25: 90
B26: =25.7-10.3 -> 15.4 | C26: 45292 | D26: ='Data Collection Sheet'!AG$112 -> 8.51 | H26: =(D26/B26)*100 -> 55.25974 | J26: 90
B27: =25.7-10.3 -> 15.4 | C27: 45323 | D27: ='Data Collection Sheet'!AH$112 -> 8.81 | H27: =(D27/B27)*100 -> 57.207792 | J27: 90
B28: =25.7-10.3 -> 15.4 | C28: 45352 | D28: ='Data Collection Sheet'!AI$112 -> 8.82 | H28: =(D28/B28)*100 -> 57.272727 | J28: 90
B29: =25.7-10.3 -> 15.4 | C29: 45383 | D29: ='Data Collection Sheet'!AJ$112 -> 8.88 | H29: =(D29/B29)*100 -> 57.662338 | J29: 90
B30: =25.7-10.3 -> 15.4 | C30: 45413 | D30: ='Data Collection Sheet'!AK$112 -> 8.88 | H30: =(D30/B30)*100 -> 57.662338 | J30: 90
B31: =25.7-10.3 -> 15.4 | C31: 45444 | D31: ='Data Collection Sheet'!AL$112 -> 9.3 | H31: =(D31/B31)*100 -> 60.38961 | J31: 90
B32: =25.7-10.3 -> 15.4 | C32: 45474 | D32: ='Data Collection Sheet'!AM$112 -> 9.77 | H32: =(D32/B32)*100 -> 63.441558 | J32: 90
B33: =25.7-10.3 -> 15.4 | C33: 45505 | D33: ='Data Collection Sheet'!AN$112 -> 9.93 | H33: =(D33/B33)*100 -> 64.480519 | J33: 90
B34: =25.7-10.3 -> 15.4 | C34: 45536 | D34: ='Data Collection Sheet'!AO$112 -> 9.93 | H34: =(D34/B34)*100 -> 64.480519 | J34: 90
B35: =25.7-10.3 -> 15.4 | C35: 45566 | D35: ='Data Collection Sheet'!AP$112 -> 9.93 | H35: =(D35/B35)*100 -> 64.480519 | J35: 90
B36: =25.7-10.3 -> 15.4 | C36: 45597 | D36: ='Data Collection Sheet'!AQ$112 -> 10.04 | H36: =(D36/B36)*100 -> 65.194805 | J36: 90
B37: =25.7-10.3 -> 15.4 | C37: 45627 | D37: ='Data Collection Sheet'!AR$112 -> 10.04 | H37: =(D37/B37)*100 -> 65.194805 | J37: 90
B38: =25.7-10.3 -> 15.4 | C38: 45658 | D38: ='Data Collection Sheet'!AS$112 -> 10.04 | H38: =(D38/B38)*100 -> 65.194805 | J38: 90
B39: =25.7-10.3 -> 15.4 | C39: 45689 | D39: ='Data Collection Sheet'!AT$112 -> 10.13 | H39: =(D39/B39)*100 -> 65.779221 | J39: 90
B40: =25.7-10.3 -> 15.4 | C40: 45717 | D40: ='Data Collection Sheet'!AU$112 -> 10.2 | H40: =(D40/B40)*100 -> 66.233766 | J40: 90
B41: =25.7-10.3 -> 15.4 | C41: 45748 | D41: ='Data Collection Sheet'!AV$112 -> 10.34 | H41: =(D41/B41)*100 -> 67.142857 | J41: 90
B42: =25.7-10.3 -> 15.4 | C42: 45778 | D42: ='Data Collection Sheet'!AW$112 -> 10.47 | H42: =(D42/B42)*100 -> 67.987013 | J42: 90
B43: =25.7-10.3 -> 15.4 | C43: 45809 | D43: ='Data Collection Sheet'!AX$112 -> 10.89 | H43: =(D43/B43)*100 -> 70.714286 | J43: 90
B44: =25.7-10.3 -> 15.4 | C44: 45839 | D44: ='Data Collection Sheet'!AY$112 -> 10.89 | H44: =(D44/B44)*100 -> 70.714286 | J44: 90
B45: =25.7-10.3 -> 15.4 | C45: 45870 | D45: ='Data Collection Sheet'!AZ$112 -> 10.98 | H45: =(D45/B45)*100 -> 71.298701 | J45: 90
B46: =25.7-10.3 -> 15.4 | C46: 45901 | D46: ='Data Collection Sheet'!BA$112 -> 11.09 | H46: =(D46/B46)*100 -> 72.012987 | J46: 90
B47: =25.7-10.3 -> 15.4 | C47: 45931 | D47: ='Data Collection Sheet'!BB$112 -> 11.09 | H47: =(D47/B47)*100 -> 72.012987 | J47: 90
B48: =25.7-10.3 -> 15.4 | C48: 45962 | D48: ='Data Collection Sheet'!BC$112 -> 11.22 | H48: =(D48/B48)*100 -> 72.857143 | J48: 90
B49: =25.7-10.3 -> 15.4 | C49: 45992 | D49: ='Data Collection Sheet'!BD$112 -> 11.21 | H49: =(D49/B49)*100 -> 72.792208 | J49: 90
B50: =25.7-10.3 -> 15.4 | C50: 46023 | D50: ='Data Collection Sheet'!BE$112 -> 11.24 | H50: =(D50/B50)*100 -> 72.987013 | J50: 90
B51: =25.7-10.3 -> 15.4 | C51: 46054 | D51: ='Data Collection Sheet'!BF$112 -> 11.22 | H51: =(D51/B51)*100 -> 72.857143 | J51: 90
B52: =25.7-10.3 -> 15.4 | C52: 46082 | D52: ='Data Collection Sheet'!BG$112 -> 11.21 | H52: =(D52/B52)*100 -> 72.792208 | J52: 90
B53: =25.7-10.3 -> 15.4 | C53: 46113 | D53: ='Data Collection Sheet'!BH$112 -> 11.21 | H53: =(D53/B53)*100 -> 72.792208 | J53: 90
B54: =25.7-10.3 -> 15.4 | C54: 46143 | D54: ='Data Collection Sheet'!BI$112 -> 11.21 | H54: =(D54/B54)*100 -> 72.792208 | J54: 90
B55: =25.7-10.3 -> 15.4 | C55: 46174 | D55: ='Data Collection Sheet'!BJ$112 -> 11.21 | H55: =(D55/B55)*100 -> 72.792208 | J55: 90
B56: =25.7-10.3 -> 15.4 | C56: 46204 | D56: ='Data Collection Sheet'!BK$112 -> 11.2 | H56: =(D56/B56)*100 -> 72.727273 | J56: 90
B57: =25.7-10.3 -> 15.4 | C57: 46235 | D57: ='Data Collection Sheet'!BL$112 -> 11.18 | F57: 8.08 | G57: =D57 -> 11.18 | H57: =(D57/B57)*100 -> 72.597403 | I57: =(G57/B57)*100 -> 72.597403 | J57: 90
B58: =25.7-10.3 -> 15.4 | C58: 46266 | F58: 1.08 | G58: =G57*(1+(F58^(1/12)-1))+E58 -> 11.251932 | I58: =(G58/B58)*100 -> 73.064496 | J58: 90
B59: =25.7-10.3 -> 15.4 | C59: 46296 | F59: 1.08 | G59: =G58*(1+(F59^(1/12)-1))+E59 -> 11.324328 | I59: =(G59/B59)*100 -> 73.534596 | J59: 90
B60: =25.7-10.3 -> 15.4 | C60: 46327 | F60: 1.08 | G60: =G59*(1+(F60^(1/12)-1))+E60 -> 11.397189 | I60: =(G60/B60)*100 -> 74.007719 | J60: 90
B61: =25.7-10.3 -> 15.4 | C61: 46357 | F61: 1.08 | G61: =G60*(1+(F61^(1/12)-1))+E61 -> 11.470519 | I61: =(G61/B61)*100 -> 74.483887 | J61: 90
B62: =25.7-10.3 -> 15.4 | C62: 46388 | F62: 1.08 | G62: =G61*(1+(F62^(1/12)-1))+E62 -> 11.54432 | I62: =(G62/B62)*100 -> 74.963119 | J62: 90
B63: =25.7-10.3 -> 15.4 | C63: 46419 | F63: 1.08 | G63: =G62*(1+(F63^(1/12)-1))+E63 -> 11.618597 | I63: =(G63/B63)*100 -> 75.445434 | J63: 90
B64: =25.7-10.3 -> 15.4 | C64: 46447 | F64: 1.08 | G64: =G63*(1+(F64^(1/12)-1))+E64 -> 11.693351 | I64: =(G64/B64)*100 -> 75.930852 | J64: 90
B65: =25.7-10.3 -> 15.4 | C65: 46478 | F65: 1.08 | G65: =G64*(1+(F65^(1/12)-1))+E65 -> 11.768587 | I65: =(G65/B65)*100 -> 76.419393 | J65: 90
B66: =25.7-10.3 -> 15.4 | C66: 46508 | F66: 1.08 | G66: =G65*(1+(F66^(1/12)-1))+E66 -> 11.844306 | I66: =(G66/B66)*100 -> 76.911078 | J66: 90
B67: =25.7-10.3 -> 15.4 | C67: 46539 | F67: 1.08 | G67: =G66*(1+(F67^(1/12)-1))+E67 -> 11.920513 | I67: =(G67/B67)*100 -> 77.405926 | J67: 90
B68: =25.7-10.3 -> 15.4 | C68: 46569 | F68: 1.08 | G68: =G67*(1+(F68^(1/12)-1))+E68 -> 11.99721 | I68: =(G68/B68)*100 -> 77.903958 | J68: 90
B69: =25.7-10.3 -> 15.4 | C69: 46600 | F69: 1.08 | G69: =G68*(1+(F69^(1/12)-1))+E69 -> 12.0744 | I69: =(G69/B69)*100 -> 78.405195 | J69: 90
... B109: =25.7-10.3 -> 15.4 | C109: 47818 | F109: 1.08 | G109: =G108*(1+(F109^(1/12)-1))+E109 -> 15.605514 | I109: =(G109/B109)*100 -> 101.33451 | J109: 90

Sheet Denver (FPS)
A1: Denver (12% YoY) | B1: Total Storage | C1: Month | D1: In Use | E1: Change (TB) | F1: Growth (%) | G1: Forecast | H1: In use (%) | I1: Forecast (%) | J1: Max %
A2: USD-UNITY-PRD01 File service | B2: 10.7 | C2: 44562 | D2: ='Data Collection Sheet'!I$113 -> 6.3 | H2: =(D2/B2)*100 -> 58.878505 | J2: 90
B3: 10.7 | C3: 44593 | D3: ='Data Collection Sheet'!J$113 -> 6.3 | H3: =(D3/B3)*100 -> 58.878505 | J3: 90
B4: 10.7 | C4: 44621 | D4: ='Data Collection Sheet'!K$113 -> 6.3 | H4: =(D4/B4)*100 -> 58.878505 | J4: 90
B5: 10.7 | C5: 44652 | D5: ='Data Collection Sheet'!L$113 -> 6.74 | H5: =(D5/B5)*100 -> 62.990654 | J5: 90
B6: 10.7 | C6: 44682 | D6: ='Data Collection Sheet'!M$113 -> 6.9 | H6: =(D6/B6)*100 -> 64.485981 | J6: 90
B7: 10.7 | C7: 44713 | D7: ='Data Collection Sheet'!N$113 -> 6.9 | H7: =(D7/B7)*100 -> 64.485981 | J7: 90
B8: 10.7 | C8: 44743 | D8: ='Data Collection Sheet'!O$113 -> 6.8 | H8: =(D8/B8)*100 -> 63.551402 | J8: 90
B9: 10.7 | C9: 44774 | D9: ='Data Collection Sheet'!P$113 -> 7.1 | H9: =(D9/B9)*100 -> 66.35514 | J9: 90
B10: 10.7 | C10: 44805 | D10: ='Data Collection Sheet'!Q$113 -> 7.3 | H10: =(D10/B10)*100 -> 68.224299 | J10: 90
B11: 10.7 | C11: 44835 | D11: ='Data Collection Sheet'!R$113 -> 7.3 | H11: =(D11/B11)*100 -> 68.224299 | J11: 90
B12: 10.7 | C12: 44866 | D12: ='Data Collection Sheet'!S$113 -> 7.6 | H12: =(D12/B12)*100 -> 71.028037 | J12: 90
B13: 10.7 | C13: 44896 | D13: ='Data Collection Sheet'!T$113 -> 7.7 | H13: =(D13/B13)*100 -> 71.962617 | J13: 90
B14: 10.7 | C14: 44927 | D14: ='Data Collection Sheet'!U$113 -> 7.78 | H14: =(D14/B14)*100 -> 72.71028 | J14: 90
B15: 10.7 | C15: 44958 | D15: ='Data Collection Sheet'!V$113 -> 7.81 | H15: =(D15/B15)*100 -> 72.990654 | J15: 90
B16: 10.7 | C16: 44986 | D16: ='Data Collection Sheet'!W$113 -> 7.84 | H16: =(D16/B16)*100 -> 73.271028 | J16: 90
B17: 10.7 | C17: 45017 | D17: ='Data Collection Sheet'!X$113 -> 7.91 | H17: =(D17/B17)*100 -> 73.925234 | J17: 90
B18: 10.7 | C18: 45047 | D18: ='Data Collection Sheet'!Y$113 -> 7.99 | H18: =(D18/B18)*100 -> 74.672897 | J18: 90
B19: 10.7 | C19: 45078 | D19: ='Data Collection Sheet'!Z$113 -> 8.08 | H19: =(D19/B19)*100 -> 75.514019 | J19: 90
B20: 10.7 | C20: 45108 | D20: ='Data Collection Sheet'!AA$113 -> 8.14 | H20: =(D20/B20)*100 -> 76.074766 | J20: 90
B21: 10.7 | C21: 45139 | D21: ='Data Collection Sheet'!AB$113 -> 8.22 | H21: =(D21/B21)*100 -> 76.82243 | J21: 90
B22: 10.7 | C22: 45170 | D22: ='Data Collection Sheet'!AC$113 -> 8.27 | H22: =(D22/B22)*100 -> 77.28972 | J22: 90
B23: 10.7 | C23: 45200 | D23: ='Data Collection Sheet'!AD$113 -> 8.34 | H23: =(D23/B23)*100 -> 77.943925 | J23: 90
B24: 10.7 | C24: 45231 | D24: ='Data Collection Sheet'!AE$113 -> 8.4 | H24: =(D24/B24)*100 -> 78.504673 | J24: 90
B25: 10.7 | C25: 45261 | D25: ='Data Collection Sheet'!AF$113 -> 8.73 | H25: =(D25/B25)*100 -> 81.588785 | J25: 90
B26: 10.7 | C26: 45292 | D26: ='Data Collection Sheet'!AG$113 -> 8.75 | H26: =(D26/B26)*100 -> 81.775701 | J26: 90
B27: 10.7 | C27: 45323 | D27: ='Data Collection Sheet'!AH$113 -> 8.56 | H27: =(D27/B27)*100 -> 80 | J27: 90
B28: 10.7 | C28: 45352 | D28: ='Data Collection Sheet'!AI$113 -> 8.56 | H28: =(D28/B28)*100 -> 80 | J28: 90
B29: 10.7 | C29: 45383 | D29: ='Data Collection Sheet'!AJ$113 -> 8.63 | H29: =(D29/B29)*100 -> 80.654206 | J29: 90
B30: 10.7 | C30: 45413 | D30: ='Data Collection Sheet'!AK$113 -> 8.67 | H30: =(D30/B30)*100 -> 81.028037 | J30: 90
B31: 10.7 | C31: 45444 | D31: ='Data Collection Sheet'!AL$113 -> 8.74 | H31: =(D31/B31)*100 -> 81.682243 | J31: 90
B32: 10.7 | C32: 45474 | D32: ='Data Collection Sheet'!AM$113 -> 8.79 | H32: =(D32/B32)*100 -> 82.149533 | J32: 90
B33: 10.7 | C33: 45505 | D33: ='Data Collection Sheet'!AN$113 -> 8.88 | H33: =(D33/B33)*100 -> 82.990654 | J33: 90
B34: 10.7 | C34: 45536 | D34: ='Data Collection Sheet'!AO$113 -> 8.94 | H34: =(D34/B34)*100 -> 83.551402 | J34: 90
B35: 10.7 | C35: 45566 | D35: ='Data Collection Sheet'!AP$113 -> 8.99 | H35: =(D35/B35)*100 -> 84.018692 | J35: 90
B36: 10.7 | C36: 45597 | D36: ='Data Collection Sheet'!AQ$113 -> 9.03 | H36: =(D36/B36)*100 -> 84.392523 | J36: 90
B37: 10.7 | C37: 45627 | D37: ='Data Collection Sheet'!AR$113 -> 9.1 | H37: =(D37/B37)*100 -> 85.046729 | J37: 90
B38: 10.7 | C38: 45658 | D38: ='Data Collection Sheet'!AS$113 -> 9.15 | H38: =(D38/B38)*100 -> 85.514019 | J38: 90
B39: 10.7 | C39: 45689 | D39: ='Data Collection Sheet'!AT$113 -> 9.2 | H39: =(D39/B39)*100 -> 85.981308 | J39: 90
B40: 10.7 | C40: 45717 | D40: ='Data Collection Sheet'!AU$113 -> 9.2 | H40: =(D40/B40)*100 -> 85.981308 | J40: 90
B41: 11.1 | C41: 45748 | D41: ='Data Collection Sheet'!AV$113 -> 9.3 | H41: =(D41/B41)*100 -> 83.783784 | J41: 90
B42: 11.1 | C42: 45778 | D42: ='Data Collection Sheet'!AW$113 -> 9.34 | H42: =(D42/B42)*100 -> 84.144144 | J42: 90
B43: 11.1 | C43: 45809 | D43: ='Data Collection Sheet'!AX$113 -> 9.38 | H43: =(D43/B43)*100 -> 84.504505 | J43: 90
B44: 11.1 | C44: 45839 | D44: ='Data Collection Sheet'!AY$113 -> 9.43 | H44: =(D44/B44)*100 -> 84.954955 | J44: 90
B45: 11.1 | C45: 45870 | D45: ='Data Collection Sheet'!AZ$113 -> 9.47 | H45: =(D45/B45)*100 -> 85.315315 | J45: 90
B46: 11.1 | C46: 45901 | D46: ='Data Collection Sheet'!BA$113 -> 9.54 | H46: =(D46/B46)*100 -> 85.945946 | J46: 90
B47: 11.6 | C47: 45931 | D47: ='Data Collection Sheet'!BB$113 -> 9.57 | H47: =(D47/B47)*100 -> 82.5 | J47: 90
B48: 11.6 | C48: 45962 | D48: ='Data Collection Sheet'!BC$113 -> 9.63 | H48: =(D48/B48)*100 -> 83.017241 | J48: 90
B49: 11.6 | C49: 45992 | D49: ='Data Collection Sheet'!BD$113 -> 9.61 | H49: =(D49/B49)*100 -> 82.844828 | J49: 90
B50: 11.6 | C50: 46023 | D50: ='Data Collection Sheet'!BE$113 -> 9.63 | H50: =(D50/B50)*100 -> 83.017241 | J50: 90
B51: 11.6 | C51: 46054 | D51: ='Data Collection Sheet'!BF$113 -> 9.73 | H51: =(D51/B51)*100 -> 83.87931 | J51: 90
B52: 11.6 | C52: 46082 | D52: ='Data Collection Sheet'!BG$113 -> 9.72 | H52: =(D52/B52)*100 -> 83.793103 | J52: 90
B53: 11.6 | C53: 46113 | D53: ='Data Collection Sheet'!BH$113 -> 9.72 | H53: =(D53/B53)*100 -> 83.793103 | J53: 90
B54: 11.6 | C54: 46143 | D54: ='Data Collection Sheet'!BI$113 -> 9.76 | H54: =(D54/B54)*100 -> 84.137931 | J54: 90
B55: 11.6 | C55: 46174 | D55: ='Data Collection Sheet'!BJ$113 -> 9.79 | H55: =(D55/B55)*100 -> 84.396552 | J55: 90
B56: 11.6 | C56: 46204 | D56: ='Data Collection Sheet'!BK$113 -> 9.88 | H56: =(D56/B56)*100 -> 85.172414 | J56: 90
B57: 11.6 | C57: 46235 | D57: ='Data Collection Sheet'!BL$113 -> 9.98 | F57: 8.08 | G57: =D57 -> 9.98 | H57: =(D57/B57)*100 -> 86.034483 | I57: =(G57/B57)*100 -> 86.034483 | J57: 90
B58: 11.6 | C58: 46266 | F58: 1.08 | G58: =G57*(1+(F58^(1/12)-1))+E58 -> 10.044212 | I58: =(G58/B58)*100 -> 86.588031 | J58: 90
B59: 11.6 | C59: 46296 | F59: 1.08 | G59: =G58*(1+(F59^(1/12)-1))+E59 -> 10.108836 | I59: =(G59/B59)*100 -> 87.145141 | J59: 90
B60: 11.6 | C60: 46327 | F60: 1.08 | G60: =G59*(1+(F60^(1/12)-1))+E60 -> 10.173877 | I60: =(G60/B60)*100 -> 87.705836 | J60: 90
B61: 11.6 | C61: 46357 | F61: 1.08 | G61: =G60*(1+(F61^(1/12)-1))+E61 -> 10.239336 | I61: =(G61/B61)*100 -> 88.270138 | J61: 90
B62: 11.6 | C62: 46388 | F62: 1.08 | G62: =G61*(1+(F62^(1/12)-1))+E62 -> 10.305216 | I62: =(G62/B62)*100 -> 88.83807 | J62: 90
B63: 11.6 | C63: 46419 | F63: 1.08 | G63: =G62*(1+(F63^(1/12)-1))+E63 -> 10.37152 | I63: =(G63/B63)*100 -> 89.409657 | J63: 90
B64: 11.6 | C64: 46447 | F64: 1.08 | G64: =G63*(1+(F64^(1/12)-1))+E64 -> 10.438251 | I64: =(G64/B64)*100 -> 89.984922 | J64: 90
B65: 11.6 | C65: 46478 | F65: 1.08 | G65: =G64*(1+(F65^(1/12)-1))+E65 -> 10.505411 | I65: =(G65/B65)*100 -> 90.563887 | J65: 90
B66: 11.6 | C66: 46508 | F66: 1.08 | G66: =G65*(1+(F66^(1/12)-1))+E66 -> 10.573003 | I66: =(G66/B66)*100 -> 91.146578 | J66: 90
B67: 11.6 | C67: 46539 | F67: 1.08 | G67: =G66*(1+(F67^(1/12)-1))+E67 -> 10.64103 | I67: =(G67/B67)*100 -> 91.733018 | J67: 90
B68: 11.6 | C68: 46569 | F68: 1.08 | G68: =G67*(1+(F68^(1/12)-1))+E68 -> 10.709495 | I68: =(G68/B68)*100 -> 92.323231 | J68: 90
B69: 11.6 | C69: 46600 | F69: 1.08 | G69: =G68*(1+(F69^(1/12)-1))+E69 -> 10.7784 | I69: =(G69/B69)*100 -> 92.917241 | J69: 90
... B109: 11.6 | C109: 47818 | F109: 1.08 | G109: =G108*(1+(F109^(1/12)-1))+E109 -> 13.930504 | I109: =(G109/B109)*100 -> 120.09055 | J109: 90

Sheet Mechelen (HX)
A1: Mechelen (12% YoY) | B1: Total Storage | C1: Month | D1: In Use | E1: Change (TB) | F1: Growth (%) | G1: Forecast | H1: In use (%) | I1: Forecast (%) | J1: Max %
A2: HyperFlex | B2: ='Data Collection Sheet'!$G$128 -> 35.4 | C2: 44562 | D2: 26.8 | H2: =(D2/B2)*100 -> 75.706215 | J2: 75
B3: ='Data Collection Sheet'!$G$128 -> 35.4 | C3: 44593 | D3: 26.9 | H3: =(D3/B3)*100 -> 75.988701 | J3: 75
B4: ='Data Collection Sheet'!$G$128 -> 35.4 | C4: 44621 | D4: 27.2 | H4: =(D4/B4)*100 -> 76.836158 | J4: 75
B5: ='Data Collection Sheet'!$G$128 -> 35.4 | C5: 44652 | D5: 27.4 | H5: =(D5/B5)*100 -> 77.40113 | J5: 75
A6: Order extra capacity | B6: ='Data Collection Sheet'!$G$128 -> 35.4 | C6: 44682 | D6: 27.1 | H6: =(D6/B6)*100 -> 76.553672 | J6: 75
B7: ='Data Collection Sheet'!$G$128 -> 35.4 | C7: 44713 | D7: 27 | H7: =(D7/B7)*100 -> 76.271186 | J7: 75
B8: ='Data Collection Sheet'!$G$128 -> 35.4 | C8: 44743 | D8: 26.9 | H8: =(D8/B8)*100 -> 75.988701 | J8: 75
B9: ='Data Collection Sheet'!$G$128 -> 35.4 | C9: 44774 | D9: 26.8 | H9: =(D9/B9)*100 -> 75.706215 | J9: 75
B10: ='Data Collection Sheet'!$G$128 -> 35.4 | C10: 44805 | D10: 26.7 | H10: =(D10/B10)*100 -> 75.423729 | J10: 75
B11: ='Data Collection Sheet'!$G$128 -> 35.4 | C11: 44835 | D11: 26.6 | H11: =(D11/B11)*100 -> 75.141243 | J11: 75
B12: ='Data Collection Sheet'!$G$128 -> 35.4 | C12: 44866 | D12: 26.7 | H12: =(D12/B12)*100 -> 75.423729 | J12: 75
B13: ='Data Collection Sheet'!$G$128 -> 35.4 | C13: 44896 | D13: 26.4 | H13: =(D13/B13)*100 -> 74.576271 | J13: 75
B14: ='Data Collection Sheet'!$G$128 -> 35.4 | C14: 44927 | D14: 26.2 | H14: =(D14/B14)*100 -> 74.011299 | J14: 75
B15: ='Data Collection Sheet'!$G$128 -> 35.4 | C15: 44958 | D15: 25.8 | H15: =(D15/B15)*100 -> 72.881356 | J15: 75
B16: ='Data Collection Sheet'!$G$128 -> 35.4 | C16: 44986 | D16: 25.4 | H16: =(D16/B16)*100 -> 71.751412 | J16: 75
B17: ='Data Collection Sheet'!$G$128 -> 35.4 | C17: 45017 | D17: 25.4 | H17: =(D17/B17)*100 -> 71.751412 | J17: 75
B18: ='Data Collection Sheet'!$G$128 -> 35.4 | C18: 45047 | D18: 25.8 | H18: =(D18/B18)*100 -> 72.881356 | J18: 75
B19: ='Data Collection Sheet'!$G$132 -> 70.8 | C19: 45078 | D19: 27.5 | H19: =(D19/B19)*100 -> 38.841808 | J19: 75
A20: Add 40 TB to HX | B20: ='Data Collection Sheet'!$G$132 -> 70.8 | C20: 45108 | D20: ='Data Collection Sheet'!AA131 -> 30.4 | H20: =(D20/B20)*100 -> 42.937853 | J20: 75
B21: ='Data Collection Sheet'!$G$132 -> 70.8 | C21: 45139 | D21: ='Data Collection Sheet'!AB131 -> 31.8 | H21: =(D21/B21)*100 -> 44.915254 | J21: 75
B22: ='Data Collection Sheet'!$G$132 -> 70.8 | C22: 45170 | D22: ='Data Collection Sheet'!AC131 -> 33 | H22: =(D22/B22)*100 -> 46.610169 | J22: 75
B23: ='Data Collection Sheet'!$G$132 -> 70.8 | C23: 45200 | D23: ='Data Collection Sheet'!AD131 -> 32.8 | H23: =(D23/B23)*100 -> 46.327684 | J23: 75
B24: ='Data Collection Sheet'!$G$132 -> 70.8 | C24: 45231 | D24: ='Data Collection Sheet'!AE131 -> 34.2 | H24: =(D24/B24)*100 -> 48.305085 | J24: 75
B25: ='Data Collection Sheet'!$G$132 -> 70.8 | C25: 45261 | D25: ='Data Collection Sheet'!AF131 -> 35.3 | H25: =(D25/B25)*100 -> 49.858757 | J25: 75
B26: ='Data Collection Sheet'!$G$132 -> 70.8 | C26: 45292 | D26: ='Data Collection Sheet'!AG131 -> 34.2 | H26: =(D26/B26)*100 -> 48.305085 | J26: 75
B27: ='Data Collection Sheet'!$G$132 -> 70.8 | C27: 45323 | D27: ='Data Collection Sheet'!AH131 -> 34.2 | H27: =(D27/B27)*100 -> 48.305085 | J27: 75
B28: ='Data Collection Sheet'!$G$132 -> 70.8 | C28: 45352 | D28: ='Data Collection Sheet'!AI131 -> 34.8 | H28: =(D28/B28)*100 -> 49.152542 | J28: 75
B29: ='Data Collection Sheet'!$G$132 -> 70.8 | C29: 45383 | D29: ='Data Collection Sheet'!AJ131 -> 35.3 | H29: =(D29/B29)*100 -> 49.858757 | J29: 75
B30: ='Data Collection Sheet'!$G$132 -> 70.8 | C30: 45413 | D30: ='Data Collection Sheet'!AK131 -> 34 | H30: =(D30/B30)*100 -> 48.022599 | J30: 75
B31: ='Data Collection Sheet'!$G$132 -> 70.8 | C31: 45444 | D31: ='Data Collection Sheet'!AL131 -> 32.9 | H31: =(D31/B31)*100 -> 46.468927 | J31: 75
B32: ='Data Collection Sheet'!$G$132 -> 70.8 | C32: 45474 | D32: ='Data Collection Sheet'!AM131 -> 33.1 | H32: =(D32/B32)*100 -> 46.751412 | J32: 75
B33: ='Data Collection Sheet'!$G$132 -> 70.8 | C33: 45505 | D33: ='Data Collection Sheet'!AN131 -> 35.2 | H33: =(D33/B33)*100 -> 49.717514 | J33: 75
B34: ='Data Collection Sheet'!$G$132 -> 70.8 | C34: 45536 | D34: ='Data Collection Sheet'!AO131 -> 40.9 | H34: =(D34/B34)*100 -> 57.768362 | J34: 75
B35: ='Data Collection Sheet'!$G$132 -> 70.8 | C35: 45566 | D35: ='Data Collection Sheet'!AP131 -> 44 | H35: =(D35/B35)*100 -> 62.146893 | J35: 75
B36: ='Data Collection Sheet'!$G$132 -> 70.8 | C36: 45597 | D36: ='Data Collection Sheet'!AQ131 -> 48.2 | H36: =(D36/B36)*100 -> 68.079096 | J36: 75
B37: ='Data Collection Sheet'!$G$132 -> 70.8 | C37: 45627 | D37: ='Data Collection Sheet'!AR131 -> 44.6 | H37: =(D37/B37)*100 -> 62.99435 | J37: 75
B38: ='Data Collection Sheet'!$G$132 -> 70.8 | C38: 45658 | D38: ='Data Collection Sheet'!AS131 -> 45.7 | H38: =(D38/B38)*100 -> 64.548023 | J38: 75
B39: ='Data Collection Sheet'!$G$132 -> 70.8 | C39: 45689 | D39: ='Data Collection Sheet'!AT$131 -> 47.1 | H39: =(D39/B39)*100 -> 66.525424 | J39: 75
B40: ='Data Collection Sheet'!$G$132 -> 70.8 | C40: 45717 | D40: ='Data Collection Sheet'!AU$131 -> 47.5 | H40: =(D40/B40)*100 -> 67.090395 | J40: 75
B41: ='Data Collection Sheet'!$G$132 -> 70.8 | C41: 45748 | D41: ='Data Collection Sheet'!AV$131 -> 48.1 | H41: =(D41/B41)*100 -> 67.937853 | J41: 75
B42: ='Data Collection Sheet'!$G$132 -> 70.8 | C42: 45778 | D42: ='Data Collection Sheet'!AW$131 -> 48.4 | H42: =(D42/B42)*100 -> 68.361582 | J42: 75
B43: ='Data Collection Sheet'!$G$132 -> 70.8 | C43: 45809 | D43: ='Data Collection Sheet'!AX$131 -> 48.6 | H43: =(D43/B43)*100 -> 68.644068 | J43: 75
A44: from 12% to 8% increase | B44: ='Data Collection Sheet'!$G$132 -> 70.8 | C44: 45839 | D44: ='Data Collection Sheet'!AY$131 -> 49.5 | H44: =(D44/B44)*100 -> 69.915254 | J44: 75
B45: 90 | C45: 45870 | D45: ='Data Collection Sheet'!AZ$131 -> 50.5 | H45: =(D45/B45)*100 -> 56.111111 | J45: 75
A46: Add 10 TB to HX | B46: 90 | C46: 45901 | D46: ='Data Collection Sheet'!BA$131 -> 51 | H46: =(D46/B46)*100 -> 56.666667 | J46: 75
B47: 90 | C47: 45931 | D47: ='Data Collection Sheet'!BB$131 -> 51.5 | H47: =(D47/B47)*100 -> 57.222222 | J47: 75
A48: Consolidate Toulouse 1TB | B48: 90 | C48: 45962 | D48: ='Data Collection Sheet'!BC$131 -> 52.8 | H48: =(D48/B48)*100 -> 58.666667 | J48: 75
A49: Consolidate Vienna 1TB | B49: 90 | C49: 45992 | D49: ='Data Collection Sheet'!BD$131 -> 54.1 | H49: =(D49/B49)*100 -> 60.111111 | J49: 75
A50: Consolidate Bologna 1TB | B50: 90 | C50: 46023 | D50: ='Data Collection Sheet'!BE$131 -> 54.7 | H50: =(D50/B50)*100 -> 60.777778 | J50: 75
A51: Consolidate Istanbul 1TB | B51: 90 | C51: 46054 | D51: ='Data Collection Sheet'!BF$131 -> 55.4 | H51: =(D51/B51)*100 -> 61.555556 | J51: 75
A52: Consolidate Dubai 1TB | B52: 90 | C52: 46082 | D52: ='Data Collection Sheet'!BG$131 -> 56.5 | H52: =(D52/B52)*100 -> 62.777778 | J52: 75
B53: 90 | C53: 46113 | D53: ='Data Collection Sheet'!BH$131 -> 57 | H53: =(D53/B53)*100 -> 63.333333 | J53: 75
B54: 90 | C54: 46143 | D54: ='Data Collection Sheet'!BI$131 -> 57.5 | H54: =(D54/B54)*100 -> 63.888889 | J54: 75
B55: 90 | C55: 46174 | D55: ='Data Collection Sheet'!BJ$131 -> 57.4 | H55: =(D55/B55)*100 -> 63.777778 | J55: 75
B56: 90 | C56: 46204 | D56: ='Data Collection Sheet'!BK$131 -> 58.5 | H56: =(D56/B56)*100 -> 65 | J56: 75
B57: 90 | C57: 46235 | D57: ='Data Collection Sheet'!BL$131 -> 57 | F57: 4.08 | G57: =D57 -> 57 | H57: =(D57/B57)*100 -> 63.333333 | I57: =(G57/B57)*100 -> 63.333333 | J57: 75
A58: Consolidate Basel 9TB | B58: 90 | C58: 46266 | F58: 1.08 | G58: =G57*(1+(F58^(1/12)-1))+E58 -> 57.36674 | I58: =(G58/B58)*100 -> 63.740822 | J58: 75
A59: Consolidate Hanover 3TB | B59: 90 | C59: 46296 | F59: 1.08 | G59: =G58*(1+(F59^(1/12)-1))+E59 -> 57.735839 | I59: =(G59/B59)*100 -> 64.150932 | J59: 75
B60: 90 | C60: 46327 | F60: 1.08 | G60: =G59*(1+(F60^(1/12)-1))+E60 -> 58.107313 | I60: =(G60/B60)*100 -> 64.563681 | J60: 75
B61: 90 | C61: 46357 | F61: 1.08 | G61: =G60*(1+(F61^(1/12)-1))+E61 -> 58.481177 | I61: =(G61/B61)*100 -> 64.979086 | J61: 75
B62: 90 | C62: 46388 | F62: 1.08 | G62: =G61*(1+(F62^(1/12)-1))+E62 -> 58.857447 | I62: =(G62/B62)*100 -> 65.397163 | J62: 75
B63: 90 | C63: 46419 | F63: 1.08 | G63: =G62*(1+(F63^(1/12)-1))+E63 -> 59.236138 | I63: =(G63/B63)*100 -> 65.817931 | J63: 75
B64: 90 | C64: 46447 | F64: 1.08 | G64: =G63*(1+(F64^(1/12)-1))+E64 -> 59.617265 | I64: =(G64/B64)*100 -> 66.241405 | J64: 75
B65: 90 | C65: 46478 | F65: 1.08 | G65: =G64*(1+(F65^(1/12)-1))+E65 -> 60.000844 | I65: =(G65/B65)*100 -> 66.667604 | J65: 75
B66: 90 | C66: 46508 | F66: 1.08 | G66: =G65*(1+(F66^(1/12)-1))+E66 -> 60.386891 | I66: =(G66/B66)*100 -> 67.096546 | J66: 75
B67: 90 | C67: 46539 | F67: 1.08 | G67: =G66*(1+(F67^(1/12)-1))+E67 -> 60.775422 | I67: =(G67/B67)*100 -> 67.528247 | J67: 75
B68: 90 | C68: 46569 | F68: 1.08 | G68: =G67*(1+(F68^(1/12)-1))+E68 -> 61.166453 | I68: =(G68/B68)*100 -> 67.962726 | J68: 75
B69: 90 | C69: 46600 | F69: 1.08 | G69: =G68*(1+(F69^(1/12)-1))+E69 -> 61.56 | I69: =(G69/B69)*100 -> 68.4 | J69: 75
A70: Renew Cisco HW to a Managed Service Vendor | B70: 90 | C70: 46631 | F70: 1.08 | G70: =G69*(1+(F70^(1/12)-1))+E70 -> 61.956079 | I70: =(G70/B70)*100 -> 68.840088 | J70: 75
B71: 90 | C71: 46661 | F71: 1.08 | G71: =G70*(1+(F71^(1/12)-1))+E71 -> 62.354706 | I71: =(G71/B71)*100 -> 69.283007 | J71: 75
B72: 90 | C72: 46692 | F72: 1.08 | G72: =G71*(1+(F72^(1/12)-1))+E72 -> 62.755898 | I72: =(G72/B72)*100 -> 69.728776 | J72: 75
B73: 90 | C73: 46722 | F73: 1.08 | G73: =G72*(1+(F73^(1/12)-1))+E73 -> 63.159672 | I73: =(G73/B73)*100 -> 70.177413 | J73: 75
B74: 90 | C74: 46753 | F74: 1.08 | G74: =G73*(1+(F74^(1/12)-1))+E74 -> 63.566043 | I74: =(G74/B74)*100 -> 70.628936 | J74: 75
B75: 90 | C75: 46784 | F75: 1.08 | G75: =G74*(1+(F75^(1/12)-1))+E75 -> 63.975029 | I75: =(G75/B75)*100 -> 71.083365 | J75: 75
B76: 90 | C76: 46813 | F76: 1.08 | G76: =G75*(1+(F76^(1/12)-1))+E76 -> 64.386646 | I76: =(G76/B76)*100 -> 71.540718 | J76: 75
B77: 90 | C77: 46844 | F77: 1.08 | G77: =G76*(1+(F77^(1/12)-1))+E77 -> 64.800912 | I77: =(G77/B77)*100 -> 72.001013 | J77: 75
B78: 90 | C78: 46874 | F78: 1.08 | G78: =G77*(1+(F78^(1/12)-1))+E78 -> 65.217843 | I78: =(G78/B78)*100 -> 72.464269 | J78: 75
B79: 90 | C79: 46905 | F79: 1.08 | G79: =G78*(1+(F79^(1/12)-1))+E79 -> 65.637456 | I79: =(G79/B79)*100 -> 72.930507 | J79: 75
B80: 90 | C80: 46935 | F80: 1.08 | G80: =G79*(1+(F80^(1/12)-1))+E80 -> 66.059769 | I80: =(G80/B80)*100 -> 73.399744 | J80: 75
B81: 90 | C81: 46966 | F81: 1.08 | G81: =G80*(1+(F81^(1/12)-1))+E81 -> 66.4848 | I81: =(G81/B81)*100 -> 73.872 | J81: 75
B82: 90 | C82: 46997 | F82: 1.08 | G82: =G81*(1+(F82^(1/12)-1))+E82 -> 66.912565 | I82: =(G82/B82)*100 -> 74.347295 | J82: 75
... B105: 90 | C105: 47696 | F105: 1.08 | G105: =G104*(1+(F105^(1/12)-1))+E105 -> 77.547871 | I105: =(G105/B105)*100 -> 86.164301 | J105: 75

Sheet AUB (HX)
A1: Brisbane (12% YoY) | B1: Total Storage | C1: Month | D1: In Use | E1: Change (TB) | F1: Growth (%) | G1: Forecast | H1: In use (%) | I1: Forecast (%) | J1: Max %
A2: HyperFlex | B2: 45 | C2: 44927 | D2: ='Data Collection Sheet'!U141 -> 15.6 | H2: =(D2/B2)*100 -> 34.666667 | J2: 75
B3: 45 | C3: 44958 | D3: ='Data Collection Sheet'!V141 -> 16.2 | H3: =(D3/B3)*100 -> 36 | J3: 75
B4: 45 | C4: 44986 | D4: ='Data Collection Sheet'!W141 -> 17.7 | H4: =(D4/B4)*100 -> 39.333333 | J4: 75
B5: 45 | C5: 45017 | D5: ='Data Collection Sheet'!X141 -> 17.7 | H5: =(D5/B5)*100 -> 39.333333 | J5: 75
B6: 45 | C6: 45047 | D6: ='Data Collection Sheet'!Y141 -> 19.6 | H6: =(D6/B6)*100 -> 43.555556 | J6: 75
B7: 45 | C7: 45078 | D7: ='Data Collection Sheet'!Z141 -> 19.3 | H7: =(D7/B7)*100 -> 42.888889 | J7: 75
B8: 45 | C8: 45108 | D8: ='Data Collection Sheet'!AA143 -> 19.9 | H8: =(D8/B8)*100 -> 44.222222 | J8: 75
B9: 45 | C9: 45139 | D9: ='Data Collection Sheet'!AB143 -> 20.2 | H9: =(D9/B9)*100 -> 44.888889 | J9: 75
B10: 45 | C10: 45170 | D10: ='Data Collection Sheet'!AC143 -> 20.2 | H10: =(D10/B10)*100 -> 44.888889 | J10: 75
B11: 45 | C11: 45200 | D11: ='Data Collection Sheet'!AD143 -> 20.3 | H11: =(D11/B11)*100 -> 45.111111 | J11: 75
B12: 45 | C12: 45231 | D12: ='Data Collection Sheet'!AE143 -> 20.3 | H12: =(D12/B12)*100 -> 45.111111 | J12: 75
B13: 45 | C13: 45261 | D13: ='Data Collection Sheet'!AF143 -> 20.6 | H13: =(D13/B13)*100 -> 45.777778 | J13: 75
A14: Delete old SAP environment | B14: 45 | C14: 45292 | D14: ='Data Collection Sheet'!AG143 -> 14.8 | H14: =(D14/B14)*100 -> 32.888889 | J14: 75
B15: 45 | C15: 45323 | D15: ='Data Collection Sheet'!AH143 -> 15.3 | H15: =(D15/B15)*100 -> 34 | J15: 75
B16: 45 | C16: 45352 | D16: ='Data Collection Sheet'!AI143 -> 15.3 | H16: =(D16/B16)*100 -> 34 | J16: 75
B17: 45 | C17: 45383 | D17: ='Data Collection Sheet'!AJ143 -> 16.1 | H17: =(D17/B17)*100 -> 35.777778 | J17: 75
B18: 45 | C18: 45413 | D18: ='Data Collection Sheet'!AK143 -> 15.7 | H18: =(D18/B18)*100 -> 34.888889 | J18: 75
B19: 45 | C19: 45444 | D19: ='Data Collection Sheet'!AL143 -> 15.9 | H19: =(D19/B19)*100 -> 35.333333 | J19: 75
B20: 45 | C20: 45474 | D20: ='Data Collection Sheet'!AM143 -> 16 | H20: =(D20/B20)*100 -> 35.555556 | J20: 75
B21: 45 | C21: 45505 | D21: ='Data Collection Sheet'!AN143 -> 17.3 | H21: =(D21/B21)*100 -> 38.444444 | J21: 75
B22: 45 | C22: 45536 | D22: ='Data Collection Sheet'!AO143 -> 15.4 | H22: =(D22/B22)*100 -> 34.222222 | J22: 75
B23: 45 | C23: 45566 | D23: ='Data Collection Sheet'!AP143 -> 15.4 | H23: =(D23/B23)*100 -> 34.222222 | J23: 75
B24: 45 | C24: 45597 | D24: ='Data Collection Sheet'!AQ143 -> 16.6 | H24: =(D24/B24)*100 -> 36.888889 | J24: 75
B25: 45 | C25: 45627 | D25: ='Data Collection Sheet'!AR143 -> 15.4 | H25: =(D25/B25)*100 -> 34.222222 | J25: 75
B26: 45 | C26: 45658 | D26: ='Data Collection Sheet'!AS143 -> 15.6 | H26: =(D26/B26)*100 -> 34.666667 | J26: 75
B27: 45 | C27: 45689 | D27: ='Data Collection Sheet'!AT$143 -> 16.1 | H27: =(D27/B27)*100 -> 35.777778 | J27: 75
B28: 45 | C28: 45717 | D28: ='Data Collection Sheet'!AU$143 -> 16.5 | H28: =(D28/B28)*100 -> 36.666667 | J28: 75
A29: Does Cisco support till this date ? | B29: 45 | C29: 45748 | D29: ='Data Collection Sheet'!AV$143 -> 16.7 | H29: =(D29/B29)*100 -> 37.111111 | J29: 75
B30: 45 | C30: 45778 | D30: ='Data Collection Sheet'!AW$143 -> 16.7 | H30: =(D30/B30)*100 -> 37.111111 | J30: 75
B31: 45 | C31: 45809 | D31: ='Data Collection Sheet'!AX$143 -> 16.8 | H31: =(D31/B31)*100 -> 37.333333 | J31: 75
B32: 45 | C32: 45839 | D32: ='Data Collection Sheet'!AY$143 -> 16.9 | H32: =(D32/B32)*100 -> 37.555556 | J32: 75
B33: 45 | C33: 45870 | D33: ='Data Collection Sheet'!AZ$143 -> 17 | H33: =(D33/B33)*100 -> 37.777778 | J33: 75
A34: from 12% to 8% increase | B34: 45 | C34: 45901 | D34: ='Data Collection Sheet'!BA$143 -> 17 | H34: =(D34/B34)*100 -> 37.777778 | J34: 75
B35: 45 | C35: 45931 | D35: ='Data Collection Sheet'!BB$143 -> 17.3 | H35: =(D35/B35)*100 -> 38.444444 | J35: 75
B36: 45 | C36: 45962 | D36: ='Data Collection Sheet'!BC$143 -> 17.5 | H36: =(D36/B36)*100 -> 38.888889 | J36: 75
B37: 45 | C37: 45992 | D37: ='Data Collection Sheet'!BD$143 -> 17.5 | H37: =(D37/B37)*100 -> 38.888889 | J37: 75
B38: 45 | C38: 46023 | D38: ='Data Collection Sheet'!BE$143 -> 18.1 | H38: =(D38/B38)*100 -> 40.222222 | J38: 75
B39: 45 | C39: 46054 | D39: ='Data Collection Sheet'!BF$143 -> 19.5 | H39: =(D39/B39)*100 -> 43.333333 | J39: 75
B40: 45 | C40: 46082 | D40: ='Data Collection Sheet'!BG$143 -> 20.1 | H40: =(D40/B40)*100 -> 44.666667 | J40: 75
B41: 45 | C41: 46113 | D41: ='Data Collection Sheet'!BH$143 -> 20 | H41: =(D41/B41)*100 -> 44.444444 | J41: 75
B42: 45 | C42: 46143 | D42: ='Data Collection Sheet'!BI$143 -> 20.4 | H42: =(D42/B42)*100 -> 45.333333 | J42: 75
B43: 45 | C43: 46174 | D43: ='Data Collection Sheet'!BJ$143 -> 20.7 | H43: =(D43/B43)*100 -> 46 | J43: 75
B44: 45 | C44: 46204 | D44: ='Data Collection Sheet'!BK$143 -> 19.1 | H44: =(D44/B44)*100 -> 42.444444 | J44: 75
B45: 45 | C45: 46235 | D45: ='Data Collection Sheet'!BL$143 -> 20 | F45: 8.08 | G45: =D45 -> 20 | H45: =(D45/B45)*100 -> 44.444444 | I45: =(G45/B45)*100 -> 44.444444 | J45: 75
B46: 45 | C46: 46266 | F46: 1.08 | G46: =G45*(1+(F46^(1/12)-1))+E46 -> 20.128681 | I46: =(G46/B46)*100 -> 44.730401 | J46: 75
B47: 45 | C47: 46296 | F47: 1.08 | G47: =G46*(1+(F47^(1/12)-1))+E47 -> 20.258189 | I47: =(G47/B47)*100 -> 45.018198 | J47: 75
B48: 45 | C48: 46327 | F48: 1.08 | G48: =G47*(1+(F48^(1/12)-1))+E48 -> 20.388531 | I48: =(G48/B48)*100 -> 45.307847 | J48: 75
B49: 45 | C49: 46357 | F49: 1.08 | G49: =G48*(1+(F49^(1/12)-1))+E49 -> 20.519711 | I49: =(G49/B49)*100 -> 45.599359 | J49: 75
B50: 45 | C50: 46388 | F50: 1.08 | G50: =G49*(1+(F50^(1/12)-1))+E50 -> 20.651736 | I50: =(G50/B50)*100 -> 45.892746 | J50: 75
B51: 45 | C51: 46419 | F51: 1.08 | G51: =G50*(1+(F51^(1/12)-1))+E51 -> 20.78461 | I51: =(G51/B51)*100 -> 46.188022 | J51: 75
B52: 45 | C52: 46447 | F52: 1.08 | G52: =G51*(1+(F52^(1/12)-1))+E52 -> 20.918338 | I52: =(G52/B52)*100 -> 46.485197 | J52: 75
B53: 45 | C53: 46478 | F53: 1.08 | G53: =G52*(1+(F53^(1/12)-1))+E53 -> 21.052928 | I53: =(G53/B53)*100 -> 46.784284 | J53: 75
B54: 45 | C54: 46508 | F54: 1.08 | G54: =G53*(1+(F54^(1/12)-1))+E54 -> 21.188383 | I54: =(G54/B54)*100 -> 47.085295 | J54: 75
B55: 45 | C55: 46539 | F55: 1.08 | G55: =G54*(1+(F55^(1/12)-1))+E55 -> 21.32471 | I55: =(G55/B55)*100 -> 47.388244 | J55: 75
B56: 45 | C56: 46569 | F56: 1.08 | G56: =G55*(1+(F56^(1/12)-1))+E56 -> 21.461913 | I56: =(G56/B56)*100 -> 47.693141 | J56: 75
B57: 45 | C57: 46600 | F57: 1.08 | G57: =G56*(1+(F57^(1/12)-1))+E57 -> 21.6 | I57: =(G57/B57)*100 -> 48 | J57: 75
... B97: 45 | C97: 47818 | F97: 1.08 | G97: =G96*(1+(F97^(1/12)-1))+E97 -> 27.916841 | I97: =(G97/B97)*100 -> 62.037424 | J97: 75

Sheet CMY (HX)
A1: Kuala Lumpur (12% YoY) | B1: Total Storage | C1: Month | D1: In Use | E1: Change (TB) | F1: Growth (%) | G1: Forecast | H1: In use (%) | I1: Forecast (%) | J1: Max %
A2: HyperFlex | B2: 22.5 | C2: 44927 | D2: ='Data Collection Sheet'!U153 -> 6.6 | H2: =(D2/B2)*100 -> 29.333333 | J2: 75
B3: 22.5 | C3: 44958 | D3: ='Data Collection Sheet'!V153 -> 6.6 | H3: =(D3/B3)*100 -> 29.333333 | J3: 75
B4: 22.5 | C4: 44986 | D4: ='Data Collection Sheet'!W153 -> 6.6 | H4: =(D4/B4)*100 -> 29.333333 | J4: 75
B5: 22.5 | C5: 45017 | D5: ='Data Collection Sheet'!X153 -> 7.3 | H5: =(D5/B5)*100 -> 32.444444 | J5: 75
B6: 22.5 | C6: 45047 | D6: ='Data Collection Sheet'!Y153 -> 6.7 | H6: =(D6/B6)*100 -> 29.777778 | J6: 75
B7: 22.5 | C7: 45078 | D7: ='Data Collection Sheet'!Z153 -> 6.6 | H7: =(D7/B7)*100 -> 29.333333 | J7: 75
B8: 22.5 | C8: 45108 | D8: ='Data Collection Sheet'!AA155 -> 6.9 | H8: =(D8/B8)*100 -> 30.666667 | J8: 75
B9: 22.5 | C9: 45139 | D9: ='Data Collection Sheet'!AB155 -> 7.7 | H9: =(D9/B9)*100 -> 34.222222 | J9: 75
B10: 22.5 | C10: 45170 | D10: ='Data Collection Sheet'!AC155 -> 7.5 | H10: =(D10/B10)*100 -> 33.333333 | J10: 75
B11: 22.5 | C11: 45200 | D11: ='Data Collection Sheet'!AD155 -> 7.6 | H11: =(D11/B11)*100 -> 33.777778 | J11: 75
B12: 22.5 | C12: 45231 | D12: ='Data Collection Sheet'!AE155 -> 7.6 | H12: =(D12/B12)*100 -> 33.777778 | J12: 75
B13: 22.5 | C13: 45261 | D13: ='Data Collection Sheet'!AF155 -> 8.1 | H13: =(D13/B13)*100 -> 36 | J13: 75
B14: 22.5 | C14: 45292 | D14: ='Data Collection Sheet'!AG155 -> 7.6 | H14: =(D14/B14)*100 -> 33.777778 | J14: 75
B15: 22.5 | C15: 45323 | D15: ='Data Collection Sheet'!AH155 -> 7.8 | H15: =(D15/B15)*100 -> 34.666667 | J15: 75
B16: 22.5 | C16: 45352 | D16: ='Data Collection Sheet'!AI155 -> 7.9 | H16: =(D16/B16)*100 -> 35.111111 | J16: 75
B17: 22.5 | C17: 45383 | D17: ='Data Collection Sheet'!AJ155 -> 8 | H17: =(D17/B17)*100 -> 35.555556 | J17: 75
B18: 22.5 | C18: 45413 | D18: ='Data Collection Sheet'!AK155 -> 8 | H18: =(D18/B18)*100 -> 35.555556 | J18: 75
B19: 22.5 | C19: 45444 | D19: ='Data Collection Sheet'!AL155 -> 7.9 | H19: =(D19/B19)*100 -> 35.111111 | J19: 75
B20: 22.5 | C20: 45474 | D20: ='Data Collection Sheet'!AM155 -> 8.2 | H20: =(D20/B20)*100 -> 36.444444 | J20: 75
B21: 22.5 | C21: 45505 | D21: ='Data Collection Sheet'!AN155 -> 8.3 | H21: =(D21/B21)*100 -> 36.888889 | J21: 75
B22: 22.5 | C22: 45536 | D22: ='Data Collection Sheet'!AO155 -> 8.4 | H22: =(D22/B22)*100 -> 37.333333 | J22: 75
B23: 22.5 | C23: 45566 | D23: ='Data Collection Sheet'!AP155 -> 8.4 | H23: =(D23/B23)*100 -> 37.333333 | J23: 75
B24: 22.5 | C24: 45597 | D24: ='Data Collection Sheet'!AQ155 -> 8.5 | H24: =(D24/B24)*100 -> 37.777778 | J24: 75
B25: 22.5 | C25: 45627 | D25: ='Data Collection Sheet'!AR155 -> 8.5 | H25: =(D25/B25)*100 -> 37.777778 | J25: 75
B26: 22.5 | C26: 45658 | D26: ='Data Collection Sheet'!AS155 -> 8.6 | H26: =(D26/B26)*100 -> 38.222222 | J26: 75
B27: 22.5 | C27: 45689 | D27: ='Data Collection Sheet'!AT$155 -> 8.6 | H27: =(D27/B27)*100 -> 38.222222 | J27: 75
B28: 22.5 | C28: 45717 | D28: ='Data Collection Sheet'!AU$155 -> 8.8 | H28: =(D28/B28)*100 -> 39.111111 | J28: 75
A29: Does Cisco support till this date ? | B29: 22.5 | C29: 45748 | D29: ='Data Collection Sheet'!AV$155 -> 9.8 | H29: =(D29/B29)*100 -> 43.555556 | J29: 75
B30: 22.5 | C30: 45778 | D30: ='Data Collection Sheet'!AW$155 -> 9.9 | H30: =(D30/B30)*100 -> 44 | J30: 75
B31: 22.5 | C31: 45809 | D31: ='Data Collection Sheet'!AX$155 -> 9.8 | H31: =(D31/B31)*100 -> 43.555556 | J31: 75
B32: 22.5 | C32: 45839 | D32: ='Data Collection Sheet'!AY$155 -> 9 | H32: =(D32/B32)*100 -> 40 | J32: 75
B33: 22.5 | C33: 45870 | D33: ='Data Collection Sheet'!AZ$155 -> 8.9 | H33: =(D33/B33)*100 -> 39.555556 | J33: 75
A34: from 12% to 8% increase | B34: 22.5 | C34: 45901 | D34: ='Data Collection Sheet'!BA$155 -> 8.8 | H34: =(D34/B34)*100 -> 39.111111 | J34: 75
B35: 22.5 | C35: 45931 | D35: ='Data Collection Sheet'!BB$155 -> 9.1 | H35: =(D35/B35)*100 -> 40.444444 | J35: 75
B36: 22.5 | C36: 45962 | D36: ='Data Collection Sheet'!BC$155 -> 9.1 | H36: =(D36/B36)*100 -> 40.444444 | J36: 75
B37: 22.5 | C37: 45992 | D37: ='Data Collection Sheet'!BD$155 -> 9.2 | H37: =(D37/B37)*100 -> 40.888889 | J37: 75
B38: 22.5 | C38: 46023 | D38: ='Data Collection Sheet'!BE$155 -> 9.3 | H38: =(D38/B38)*100 -> 41.333333 | J38: 75
B39: 22.5 | C39: 46054 | D39: ='Data Collection Sheet'!BF$155 -> 9.5 | H39: =(D39/B39)*100 -> 42.222222 | J39: 75
B40: 22.5 | C40: 46082 | D40: ='Data Collection Sheet'!BG$155 -> 9.9 | H40: =(D40/B40)*100 -> 44 | J40: 75
B41: 22.5 | C41: 46113 | D41: ='Data Collection Sheet'!BH$155 -> 10.1 | H41: =(D41/B41)*100 -> 44.888889 | J41: 75
B42: 22.5 | C42: 46143 | D42: ='Data Collection Sheet'!BI$155 -> 10.4 | H42: =(D42/B42)*100 -> 46.222222 | J42: 75
B43: 22.5 | C43: 46174 | D43: ='Data Collection Sheet'!BJ$155 -> 10.5 | H43: =(D43/B43)*100 -> 46.666667 | J43: 75
B44: 22.5 | C44: 46204 | D44: ='Data Collection Sheet'!BK$155 -> 10 | H44: =(D44/B44)*100 -> 44.444444 | J44: 75
B45: 22.5 | C45: 46235 | D45: ='Data Collection Sheet'!BL$155 -> 10.2 | F45: 8.08 | G45: =D45 -> 10.2 | H45: =(D45/B45)*100 -> 45.333333 | I45: =(G45/B45)*100 -> 45.333333 | J45: 75
B46: 22.5 | C46: 46266 | F46: 1.08 | G46: =G45*(1+(F46^(1/12)-1))+E46 -> 10.265627 | I46: =(G46/B46)*100 -> 45.625009 | J46: 75
B47: 22.5 | C47: 46296 | F47: 1.08 | G47: =G46*(1+(F47^(1/12)-1))+E47 -> 10.331676 | I47: =(G47/B47)*100 -> 45.918562 | J47: 75
B48: 22.5 | C48: 46327 | F48: 1.08 | G48: =G47*(1+(F48^(1/12)-1))+E48 -> 10.398151 | I48: =(G48/B48)*100 -> 46.214003 | J48: 75
B49: 22.5 | C49: 46357 | F49: 1.08 | G49: =G48*(1+(F49^(1/12)-1))+E49 -> 10.465053 | I49: =(G49/B49)*100 -> 46.511346 | J49: 75 | M49: =27*0.7 -> 18.9
B50: 22.5 | C50: 46388 | F50: 1.08 | G50: =G49*(1+(F50^(1/12)-1))+E50 -> 10.532385 | I50: =(G50/B50)*100 -> 46.810601 | J50: 75
B51: 22.5 | C51: 46419 | F51: 1.08 | G51: =G50*(1+(F51^(1/12)-1))+E51 -> 10.600151 | I51: =(G51/B51)*100 -> 47.111782 | J51: 75
B52: 22.5 | C52: 46447 | F52: 1.08 | G52: =G51*(1+(F52^(1/12)-1))+E52 -> 10.668353 | I52: =(G52/B52)*100 -> 47.414901 | J52: 75
B53: 22.5 | C53: 46478 | F53: 1.08 | G53: =G52*(1+(F53^(1/12)-1))+E53 -> 10.736993 | I53: =(G53/B53)*100 -> 47.719969 | J53: 75
B54: 22.5 | C54: 46508 | F54: 1.08 | G54: =G53*(1+(F54^(1/12)-1))+E54 -> 10.806075 | I54: =(G54/B54)*100 -> 48.027001 | J54: 75
B55: 22.5 | C55: 46539 | F55: 1.08 | G55: =G54*(1+(F55^(1/12)-1))+E55 -> 10.875602 | I55: =(G55/B55)*100 -> 48.336008 | J55: 75
B56: 22.5 | C56: 46569 | F56: 1.08 | G56: =G55*(1+(F56^(1/12)-1))+E56 -> 10.945576 | I56: =(G56/B56)*100 -> 48.647004 | J56: 75
B57: 22.5 | C57: 46600 | F57: 1.08 | G57: =G56*(1+(F57^(1/12)-1))+E57 -> 11.016 | I57: =(G57/B57)*100 -> 48.96 | J57: 75
B58: 22.5 | C58: 46631 | F58: 1.08 | G58: =G57*(1+(F58^(1/12)-1))+E58 -> 11.086877 | I58: =(G58/B58)*100 -> 49.27501 | J58: 75
B59: 22.5 | C59: 46661 | F59: 1.08 | G59: =G58*(1+(F59^(1/12)-1))+E59 -> 11.158211 | I59: =(G59/B59)*100 -> 49.592047 | J59: 75
B60: 22.5 | C60: 46692 | F60: 1.08 | G60: =G59*(1+(F60^(1/12)-1))+E60 -> 11.230003 | I60: =(G60/B60)*100 -> 49.911124 | J60: 75
B61: 22.5 | C61: 46722 | F61: 1.08 | G61: =G60*(1+(F61^(1/12)-1))+E61 -> 11.302257 | I61: =(G61/B61)*100 -> 50.232253 | J61: 75
... B97: 22.5 | C97: 47818 | F97: 1.08 | G97: =G96*(1+(F97^(1/12)-1))+E97 -> 14.237589 | I97: =(G97/B97)*100 -> 63.278172 | J97: 75

Sheet CNC (HX)
A1: Chengdu (12% YoY) | B1: Total Storage | C1: Month | D1: In Use | E1: Change (TB) | F1: Growth (%) | G1: Forecast | H1: In use (%) | I1: Forecast (%) | J1: Max %
A2: HyperFlex | B2: 28.9 | C2: 44927 | D2: ='Data Collection Sheet'!U159 -> 5.2 | H2: =(D2/B2)*100 -> 17.99308 | J2: 75
B3: 28.9 | C3: 44958 | D3: ='Data Collection Sheet'!V159 -> 5.2 | H3: =(D3/B3)*100 -> 17.99308 | J3: 75
B4: 28.9 | C4: 44986 | D4: ='Data Collection Sheet'!W159 -> 5.2 | H4: =(D4/B4)*100 -> 17.99308 | J4: 75
B5: 28.9 | C5: 45017 | D5: ='Data Collection Sheet'!X159 -> 5.6 | H5: =(D5/B5)*100 -> 19.377163 | J5: 75
B6: 28.9 | C6: 45047 | D6: ='Data Collection Sheet'!Y159 -> 5.4 | H6: =(D6/B6)*100 -> 18.685121 | J6: 75
B7: 28.9 | C7: 45078 | D7: ='Data Collection Sheet'!Z159 -> 5.3 | H7: =(D7/B7)*100 -> 18.3391 | J7: 75
B8: 28.9 | C8: 45108 | D8: ='Data Collection Sheet'!AA161 -> 5.6 | H8: =(D8/B8)*100 -> 19.377163 | J8: 75
B9: 28.9 | C9: 45139 | D9: ='Data Collection Sheet'!AB161 -> 5.8 | H9: =(D9/B9)*100 -> 20.069204 | J9: 75
B10: 28.9 | C10: 45170 | D10: ='Data Collection Sheet'!AC161 -> 5.8 | H10: =(D10/B10)*100 -> 20.069204 | J10: 75
B11: 28.9 | C11: 45200 | D11: ='Data Collection Sheet'!AD161 -> 5.9 | H11: =(D11/B11)*100 -> 20.415225 | J11: 75
B12: 28.9 | C12: 45231 | D12: ='Data Collection Sheet'!AE161 -> 5.9 | H12: =(D12/B12)*100 -> 20.415225 | J12: 75
B13: 28.9 | C13: 45261 | D13: ='Data Collection Sheet'!AF161 -> 7.1 | H13: =(D13/B13)*100 -> 24.567474 | J13: 75
B14: 28.9 | C14: 45292 | D14: ='Data Collection Sheet'!AG161 -> 6.5 | H14: =(D14/B14)*100 -> 22.491349 | J14: 75
B15: 28.9 | C15: 45323 | D15: ='Data Collection Sheet'!AH161 -> 6.7 | H15: =(D15/B15)*100 -> 23.183391 | J15: 75
B16: 28.9 | C16: 45352 | D16: ='Data Collection Sheet'!AI161 -> 7.1 | H16: =(D16/B16)*100 -> 24.567474 | J16: 75
B17: 28.9 | C17: 45383 | D17: ='Data Collection Sheet'!AJ161 -> 7 | H17: =(D17/B17)*100 -> 24.221453 | J17: 75
B18: 28.9 | C18: 45413 | D18: ='Data Collection Sheet'!AK161 -> 7.1 | H18: =(D18/B18)*100 -> 24.567474 | J18: 75
B19: 28.9 | C19: 45444 | D19: ='Data Collection Sheet'!AL161 -> 7 | H19: =(D19/B19)*100 -> 24.221453 | J19: 75
B20: 28.9 | C20: 45474 | D20: ='Data Collection Sheet'!AM161 -> 7.1 | H20: =(D20/B20)*100 -> 24.567474 | J20: 75
B21: 28.9 | C21: 45505 | D21: ='Data Collection Sheet'!AN161 -> 7.3 | H21: =(D21/B21)*100 -> 25.259516 | J21: 75
B22: 28.9 | C22: 45536 | D22: ='Data Collection Sheet'!AO161 -> 7.4 | H22: =(D22/B22)*100 -> 25.605536 | J22: 75
B23: 28.9 | C23: 45566 | D23: ='Data Collection Sheet'!AP161 -> 7.2 | H23: =(D23/B23)*100 -> 24.913495 | J23: 75
B24: 28.9 | C24: 45597 | D24: ='Data Collection Sheet'!AQ161 -> 7.3 | H24: =(D24/B24)*100 -> 25.259516 | J24: 75
B25: 28.9 | C25: 45627 | D25: ='Data Collection Sheet'!AR161 -> 7.4 | H25: =(D25/B25)*100 -> 25.605536 | J25: 75
B26: 28.9 | C26: 45658 | D26: ='Data Collection Sheet'!AS161 -> 7.4 | H26: =(D26/B26)*100 -> 25.605536 | J26: 75
B27: 28.9 | C27: 45689 | D27: ='Data Collection Sheet'!AT$161 -> 7.5 | H27: =(D27/B27)*100 -> 25.951557 | J27: 75
B28: 28.9 | C28: 45717 | D28: ='Data Collection Sheet'!AU$161 -> 7.6 | H28: =(D28/B28)*100 -> 26.297578 | J28: 75
A29: Does Cisco support till this date ? | B29: 28.9 | C29: 45748 | D29: ='Data Collection Sheet'!AV$161 -> 7.7 | H29: =(D29/B29)*100 -> 26.643599 | J29: 75
B30: 28.9 | C30: 45778 | D30: ='Data Collection Sheet'!AW$161 -> 7.8 | H30: =(D30/B30)*100 -> 26.989619 | J30: 75
B31: 28.9 | C31: 45809 | D31: ='Data Collection Sheet'!AX$161 -> 7.8 | H31: =(D31/B31)*100 -> 26.989619 | J31: 75
B32: 28.9 | C32: 45839 | D32: ='Data Collection Sheet'!AY$161 -> 7.9 | H32: =(D32/B32)*100 -> 27.33564 | J32: 75
B33: 28.9 | C33: 45870 | D33: ='Data Collection Sheet'!AZ$161 -> 8 | H33: =(D33/B33)*100 -> 27.681661 | J33: 75
A34: from 12% to 8% increase | B34: 28.9 | C34: 45901 | D34: ='Data Collection Sheet'!BA$161 -> 8 | H34: =(D34/B34)*100 -> 27.681661 | J34: 75
B35: 28.9 | C35: 45931 | D35: ='Data Collection Sheet'!BB$161 -> 8.1 | H35: =(D35/B35)*100 -> 28.027682 | J35: 75
B36: 28.9 | C36: 45962 | D36: ='Data Collection Sheet'!BC$161 -> 8.2 | H36: =(D36/B36)*100 -> 28.373702 | J36: 75
B37: 28.9 | C37: 45992 | D37: ='Data Collection Sheet'!BD$161 -> 8.2 | H37: =(D37/B37)*100 -> 28.373702 | J37: 75
B38: 28.9 | C38: 46023 | D38: ='Data Collection Sheet'!BE$161 -> 8.4 | H38: =(D38/B38)*100 -> 29.065744 | J38: 75
B39: 28.9 | C39: 46054 | D39: ='Data Collection Sheet'!BF$161 -> 8.5 | H39: =(D39/B39)*100 -> 29.411765 | J39: 75
B40: 28.9 | C40: 46082 | D40: ='Data Collection Sheet'!BG$161 -> 8.6 | H40: =(D40/B40)*100 -> 29.757785 | J40: 75
B41: 28.9 | C41: 46113 | D41: ='Data Collection Sheet'!BH$161 -> 8.7 | H41: =(D41/B41)*100 -> 30.103806 | J41: 75
B42: 28.9 | C42: 46143 | D42: ='Data Collection Sheet'!BI$161 -> 10.1 | H42: =(D42/B42)*100 -> 34.948097 | J42: 75
B43: 28.9 | C43: 46174 | D43: ='Data Collection Sheet'!BJ$161 -> 9.1 | H43: =(D43/B43)*100 -> 31.487889 | J43: 75
B44: 28.9 | C44: 46204 | D44: ='Data Collection Sheet'!BK$161 -> 8.9 | H44: =(D44/B44)*100 -> 30.795848 | J44: 75
B45: 28.9 | C45: 46235 | D45: ='Data Collection Sheet'!BL$161 -> 9.1 | F45: 8.08 | G45: =D45 -> 9.1 | H45: =(D45/B45)*100 -> 31.487889 | I45: =(G45/B45)*100 -> 31.487889 | J45: 75
B46: 28.9 | C46: 46266 | F46: 1.08 | G46: =G45*(1+(F46^(1/12)-1))+E46 -> 9.1585497 | I46: =(G46/B46)*100 -> 31.690483 | J46: 75
B47: 28.9 | C47: 46296 | F47: 1.08 | G47: =G46*(1+(F47^(1/12)-1))+E47 -> 9.2174761 | I47: =(G47/B47)*100 -> 31.894381 | J47: 75
B48: 28.9 | C48: 46327 | F48: 1.08 | G48: =G47*(1+(F48^(1/12)-1))+E48 -> 9.2767816 | I48: =(G48/B48)*100 -> 32.09959 | J48: 75
B49: 28.9 | C49: 46357 | F49: 1.08 | G49: =G48*(1+(F49^(1/12)-1))+E49 -> 9.3364687 | I49: =(G49/B49)*100 -> 32.30612 | J49: 75
B50: 28.9 | C50: 46388 | F50: 1.08 | G50: =G49*(1+(F50^(1/12)-1))+E50 -> 9.3965398 | I50: =(G50/B50)*100 -> 32.513979 | J50: 75
B51: 28.9 | C51: 46419 | F51: 1.08 | G51: =G50*(1+(F51^(1/12)-1))+E51 -> 9.4569974 | I51: =(G51/B51)*100 -> 32.723174 | J51: 75
B52: 28.9 | C52: 46447 | F52: 1.08 | G52: =G51*(1+(F52^(1/12)-1))+E52 -> 9.517844 | I52: =(G52/B52)*100 -> 32.933716 | J52: 75
B53: 28.9 | C53: 46478 | F53: 1.08 | G53: =G52*(1+(F53^(1/12)-1))+E53 -> 9.5790821 | I53: =(G53/B53)*100 -> 33.145613 | J53: 75
B54: 28.9 | C54: 46508 | F54: 1.08 | G54: =G53*(1+(F54^(1/12)-1))+E54 -> 9.6407142 | I54: =(G54/B54)*100 -> 33.358873 | J54: 75
B55: 28.9 | C55: 46539 | F55: 1.08 | G55: =G54*(1+(F55^(1/12)-1))+E55 -> 9.7027429 | I55: =(G55/B55)*100 -> 33.573505 | J55: 75
B56: 28.9 | C56: 46569 | F56: 1.08 | G56: =G55*(1+(F56^(1/12)-1))+E56 -> 9.7651706 | I56: =(G56/B56)*100 -> 33.789518 | J56: 75
B57: 28.9 | C57: 46600 | F57: 1.08 | G57: =G56*(1+(F57^(1/12)-1))+E57 -> 9.828 | I57: =(G57/B57)*100 -> 34.00692 | J57: 75
... B97: 28.9 | C97: 47818 | F97: 1.08 | G97: =G96*(1+(F97^(1/12)-1))+E97 -> 12.702163 | I97: =(G97/B97)*100 -> 43.95212 | J97: 75

Sheet GBW (HX)
A1: Weybridge (12% YoY) | B1: Total Storage | C1: Month | D1: In Use | E1: Change (TB) | F1: Growth (%) | G1: Forecast | H1: In use (%) | I1: Forecast (%) | J1: Max %
A2: HyperFlex | B2: 16.1 | C2: 44927 | D2: ='Data Collection Sheet'!U147 -> 6.6 | H2: =(D2/B2)*100 -> 40.993789 | J2: 75
B3: 16.1 | C3: 44958 | D3: ='Data Collection Sheet'!V147 -> 6.6 | H3: =(D3/B3)*100 -> 40.993789 | J3: 75
B4: 16.1 | C4: 44986 | D4: ='Data Collection Sheet'!W147 -> 7.1 | H4: =(D4/B4)*100 -> 44.099379 | J4: 75
B5: 16.1 | C5: 45017 | D5: ='Data Collection Sheet'!X147 -> 6.9 | H5: =(D5/B5)*100 -> 42.857143 | J5: 75
B6: 16.1 | C6: 45047 | D6: ='Data Collection Sheet'!Y147 -> 6.9 | H6: =(D6/B6)*100 -> 42.857143 | J6: 75
B7: 16.1 | C7: 45078 | D7: ='Data Collection Sheet'!Z147 -> 6.4 | H7: =(D7/B7)*100 -> 39.751553 | J7: 75
B8: 16.1 | C8: 45108 | D8: ='Data Collection Sheet'!AA147 -> 6.7 | H8: =(D8/B8)*100 -> 41.614907 | J8: 75
B9: 16.1 | C9: 45139 | D9: ='Data Collection Sheet'!AB147 -> 6.7 | H9: =(D9/B9)*100 -> 41.614907 | J9: 75
B10: 16.1 | C10: 45170 | D10: ='Data Collection Sheet'!AC147 -> 6.8 | H10: =(D10/B10)*100 -> 42.236025 | J10: 75
B11: 16.1 | C11: 45200 | D11: ='Data Collection Sheet'!AD147 -> 6.7 | H11: =(D11/B11)*100 -> 41.614907 | J11: 75
B12: 16.1 | C12: 45231 | D12: ='Data Collection Sheet'!AE147 -> 6.8 | H12: =(D12/B12)*100 -> 42.236025 | J12: 75
B13: 16.1 | C13: 45261 | D13: ='Data Collection Sheet'!AF147 -> 6.3 | H13: =(D13/B13)*100 -> 39.130435 | J13: 75
B14: 16.1 | C14: 45292 | D14: ='Data Collection Sheet'!AG147 -> 6.4 | H14: =(D14/B14)*100 -> 39.751553 | J14: 75
B15: 16.1 | C15: 45323 | D15: ='Data Collection Sheet'!AH147 -> 6.6 | H15: =(D15/B15)*100 -> 40.993789 | J15: 75
B16: 16.1 | C16: 45352 | D16: ='Data Collection Sheet'!AI147 -> 6.6 | H16: =(D16/B16)*100 -> 40.993789 | J16: 75
B17: 16.1 | C17: 45383 | D17: ='Data Collection Sheet'!AJ147 -> 6.6 | H17: =(D17/B17)*100 -> 40.993789 | J17: 75
B18: 16.1 | C18: 45413 | D18: ='Data Collection Sheet'!AK147 -> 6.4 | H18: =(D18/B18)*100 -> 39.751553 | J18: 75
B19: 16.1 | C19: 45444 | D19: ='Data Collection Sheet'!AL147 -> 6.6 | H19: =(D19/B19)*100 -> 40.993789 | J19: 75
B20: 16.1 | C20: 45474 | D20: ='Data Collection Sheet'!AM147 -> 6.7 | H20: =(D20/B20)*100 -> 41.614907 | J20: 75
B21: 16.1 | C21: 45505 | D21: ='Data Collection Sheet'!AN147 -> 7.2 | H21: =(D21/B21)*100 -> 44.720497 | J21: 75
B22: 16.1 | C22: 45536 | D22: ='Data Collection Sheet'!AO147 -> 7.4 | H22: =(D22/B22)*100 -> 45.962733 | J22: 75
B23: 16.1 | C23: 45566 | D23: ='Data Collection Sheet'!AP147 -> 7.7 | H23: =(D23/B23)*100 -> 47.826087 | J23: 75
B24: 16.1 | C24: 45597 | D24: ='Data Collection Sheet'!AQ147 -> 7.7 | H24: =(D24/B24)*100 -> 47.826087 | J24: 75
B25: 16.1 | C25: 45627 | D25: ='Data Collection Sheet'!AR147 -> 7.4 | H25: =(D25/B25)*100 -> 45.962733 | J25: 75
B26: 16.1 | C26: 45658 | D26: ='Data Collection Sheet'!AS147 -> 7.6 | H26: =(D26/B26)*100 -> 47.204969 | J26: 75
B27: 16.1 | C27: 45689 | D27: ='Data Collection Sheet'!AT$147 -> 7.4 | H27: =(D27/B27)*100 -> 45.962733 | J27: 75
B28: 16.1 | C28: 45717 | D28: ='Data Collection Sheet'!AU$147 -> 7.5 | H28: =(D28/B28)*100 -> 46.583851 | J28: 75
A29: Does Cisco support till this date ? | B29: 16.1 | C29: 45748 | D29: ='Data Collection Sheet'!AV$147 -> 7.7 | H29: =(D29/B29)*100 -> 47.826087 | J29: 75
B30: 16.1 | C30: 45778 | D30: ='Data Collection Sheet'!AW$147 -> 7.7 | H30: =(D30/B30)*100 -> 47.826087 | J30: 75
B31: 16.1 | C31: 45809 | D31: ='Data Collection Sheet'!AX$147 -> 7.7 | H31: =(D31/B31)*100 -> 47.826087 | J31: 75
B32: 16.1 | C32: 45839 | D32: ='Data Collection Sheet'!AY$147 -> 7.8 | H32: =(D32/B32)*100 -> 48.447205 | J32: 75
B33: 16.1 | C33: 45870 | D33: ='Data Collection Sheet'!AZ$147 -> 8 | H33: =(D33/B33)*100 -> 49.689441 | J33: 75
A34: from 12% to 8% increase | B34: 16.1 | C34: 45901 | D34: ='Data Collection Sheet'!BA$147 -> 8 | H34: =(D34/B34)*100 -> 49.689441 | J34: 75
B35: 16.1 | C35: 45931 | D35: ='Data Collection Sheet'!BB$147 -> 8 | H35: =(D35/B35)*100 -> 49.689441 | J35: 75
B36: 16.1 | C36: 45962 | D36: ='Data Collection Sheet'!BC$147 -> 7.3 | H36: =(D36/B36)*100 -> 45.341615 | J36: 75
B37: 16.1 | C37: 45992 | D37: ='Data Collection Sheet'!BD$147 -> 7.7 | H37: =(D37/B37)*100 -> 47.826087 | J37: 75
B38: 16.1 | C38: 46023 | D38: ='Data Collection Sheet'!BE$147 -> 7.9 | H38: =(D38/B38)*100 -> 49.068323 | J38: 75
B39: 16.1 | C39: 46054 | D39: ='Data Collection Sheet'!BF$147 -> 8 | H39: =(D39/B39)*100 -> 49.689441 | J39: 75
B40: 16.1 | C40: 46082 | D40: ='Data Collection Sheet'!BG$147 -> 8 | H40: =(D40/B40)*100 -> 49.689441 | J40: 75
B41: 16.1 | C41: 46113 | D41: ='Data Collection Sheet'!BH$147 -> 8 | H41: =(D41/B41)*100 -> 49.689441 | J41: 75
B42: 16.1 | C42: 46143 | D42: ='Data Collection Sheet'!BI$147 -> 8 | H42: =(D42/B42)*100 -> 49.689441 | J42: 75
B43: 16.1 | C43: 46174 | D43: ='Data Collection Sheet'!BJ$147 -> 8 | H43: =(D43/B43)*100 -> 49.689441 | J43: 75
B44: 16.1 | C44: 46204 | D44: ='Data Collection Sheet'!BK$147 -> 8 | H44: =(D44/B44)*100 -> 49.689441 | J44: 75
B45: 16.1 | C45: 46235 | D45: ='Data Collection Sheet'!BL$147 -> 7.3 | F45: 8.08 | G45: =D45 -> 7.3 | H45: =(D45/B45)*100 -> 45.341615 | I45: =(G45/B45)*100 -> 45.341615 | J45: 75
B46: 16.1 | C46: 46266 | F46: 1.08 | G46: =G45*(1+(F46^(1/12)-1))+E46 -> 7.3469684 | I46: =(G46/B46)*100 -> 45.633344 | J46: 75
B47: 16.1 | C47: 46296 | F47: 1.08 | G47: =G46*(1+(F47^(1/12)-1))+E47 -> 7.394239 | I47: =(G47/B47)*100 -> 45.926951 | J47: 75
B48: 16.1 | C48: 46327 | F48: 1.08 | G48: =G47*(1+(F48^(1/12)-1))+E48 -> 7.4418138 | I48: =(G48/B48)*100 -> 46.222446 | J48: 75
B49: 16.1 | C49: 46357 | F49: 1.08 | G49: =G48*(1+(F49^(1/12)-1))+E49 -> 7.4896946 | I49: =(G49/B49)*100 -> 46.519843 | J49: 75
B50: 16.1 | C50: 46388 | F50: 1.08 | G50: =G49*(1+(F50^(1/12)-1))+E50 -> 7.5378836 | I50: =(G50/B50)*100 -> 46.819153 | J50: 75
B51: 16.1 | C51: 46419 | F51: 1.08 | G51: =G50*(1+(F51^(1/12)-1))+E51 -> 7.5863825 | I51: =(G51/B51)*100 -> 47.120388 | J51: 75
B52: 16.1 | C52: 46447 | F52: 1.08 | G52: =G51*(1+(F52^(1/12)-1))+E52 -> 7.6351936 | I52: =(G52/B52)*100 -> 47.423562 | J52: 75
B53: 16.1 | C53: 46478 | F53: 1.08 | G53: =G52*(1+(F53^(1/12)-1))+E53 -> 7.6843186 | I53: =(G53/B53)*100 -> 47.728687 | J53: 75
B54: 16.1 | C54: 46508 | F54: 1.08 | G54: =G53*(1+(F54^(1/12)-1))+E54 -> 7.7337598 | I54: =(G54/B54)*100 -> 48.035775 | J54: 75
B55: 16.1 | C55: 46539 | F55: 1.08 | G55: =G54*(1+(F55^(1/12)-1))+E55 -> 7.783519 | I55: =(G55/B55)*100 -> 48.344838 | J55: 75
B56: 16.1 | C56: 46569 | F56: 1.08 | G56: =G55*(1+(F56^(1/12)-1))+E56 -> 7.8335984 | I56: =(G56/B56)*100 -> 48.655891 | J56: 75
B57: 16.1 | C57: 46600 | F57: 1.08 | G57: =G56*(1+(F57^(1/12)-1))+E57 -> 7.884 | I57: =(G57/B57)*100 -> 48.968944 | J57: 75
... B97: 16.1 | C97: 47818 | F97: 1.08 | G97: =G96*(1+(F97^(1/12)-1))+E97 -> 10.189647 | I97: =(G97/B97)*100 -> 63.289732 | J97: 75

Sheet SEG (HX)
A1: Gothenburg (12% YoY) | B1: Total Storage | C1: Month | D1: In Use | E1: Change (TB) | F1: Growth (%) | G1: Forecast | H1: In use (%) | I1: Forecast (%) | J1: Max %
A2: HyperFlex | B2: 51.4 | C2: 44927 | D2: ='Data Collection Sheet'!U137 -> 30 | H2: =(D2/B2)*100 -> 58.365759 | J2: 75
B3: 51.4 | C3: 44958 | D3: ='Data Collection Sheet'!V137 -> 30.2 | H3: =(D3/B3)*100 -> 58.754864 | J3: 75
B4: 51.4 | C4: 44986 | D4: ='Data Collection Sheet'!W137 -> 30.8 | H4: =(D4/B4)*100 -> 59.922179 | J4: 75
B5: 51.4 | C5: 45017 | D5: ='Data Collection Sheet'!X137 -> 31 | H5: =(D5/B5)*100 -> 60.311284 | J5: 75
B6: 51.4 | C6: 45047 | D6: ='Data Collection Sheet'!Y137 -> 31 | H6: =(D6/B6)*100 -> 60.311284 | J6: 75
B7: 51.4 | C7: 45078 | D7: ='Data Collection Sheet'!Z137 -> 30.3 | H7: =(D7/B7)*100 -> 58.949416 | J7: 75
B8: 51.4 | C8: 45108 | D8: ='Data Collection Sheet'!AA137 -> 30.6 | H8: =(D8/B8)*100 -> 59.533074 | J8: 75
B9: 51.4 | C9: 45139 | D9: ='Data Collection Sheet'!AB137 -> 30.8 | H9: =(D9/B9)*100 -> 59.922179 | J9: 75
B10: 51.4 | C10: 45170 | D10: ='Data Collection Sheet'!AC137 -> 30.2 | H10: =(D10/B10)*100 -> 58.754864 | J10: 75
B11: 51.4 | C11: 45200 | D11: ='Data Collection Sheet'!AD137 -> 30.4 | H11: =(D11/B11)*100 -> 59.143969 | J11: 75
B12: 51.4 | C12: 45231 | D12: ='Data Collection Sheet'!AE137 -> 30.6 | H12: =(D12/B12)*100 -> 59.533074 | J12: 75
B13: 51.4 | C13: 45261 | D13: ='Data Collection Sheet'!AF137 -> 30.6 | H13: =(D13/B13)*100 -> 59.533074 | J13: 75
B14: 51.4 | C14: 45292 | D14: ='Data Collection Sheet'!AG137 -> 30.5 | H14: =(D14/B14)*100 -> 59.338521 | J14: 75
B15: 51.4 | C15: 45323 | D15: ='Data Collection Sheet'!AH137 -> 30.6 | H15: =(D15/B15)*100 -> 59.533074 | J15: 75
B16: 51.4 | C16: 45352 | D16: ='Data Collection Sheet'!AI137 -> 30.9 | H16: =(D16/B16)*100 -> 60.116732 | J16: 75
B17: 51.4 | C17: 45383 | D17: ='Data Collection Sheet'!AJ137 -> 31 | H17: =(D17/B17)*100 -> 60.311284 | J17: 75
B18: 51.4 | C18: 45413 | D18: ='Data Collection Sheet'!AK137 -> 30.9 | H18: =(D18/B18)*100 -> 60.116732 | J18: 75
B19: 51.4 | C19: 45444 | D19: ='Data Collection Sheet'!AL137 -> 30.8 | H19: =(D19/B19)*100 -> 59.922179 | J19: 75
B20: 51.4 | C20: 45474 | D20: ='Data Collection Sheet'!AM137 -> 31.1 | H20: =(D20/B20)*100 -> 60.505837 | J20: 75
B21: 51.4 | C21: 45505 | D21: ='Data Collection Sheet'!AN137 -> 30.8 | H21: =(D21/B21)*100 -> 59.922179 | J21: 75
A22: Add OTICON GOT 3TB | B22: 51.4 | C22: 45536 | D22: ='Data Collection Sheet'!AO137 -> 31 | E22: 3 | H22: =(D22/B22)*100 -> 60.311284 | J22: 75
B23: 51.4 | C23: 45566 | D23: ='Data Collection Sheet'!AP137 -> 31.1 | H23: =(D23/B23)*100 -> 60.505837 | J23: 75
B24: 51.4 | C24: 45597 | D24: ='Data Collection Sheet'!AQ137 -> 31.2 | H24: =(D24/B24)*100 -> 60.700389 | J24: 75
A25: Move 10TB FileServices to AWS | B25: 51.4 | C25: 45627 | D25: ='Data Collection Sheet'!AR137 -> 31.4 | E25: -10 | H25: =(D25/B25)*100 -> 61.089494 | J25: 75
B26: 51.4 | C26: 45658 | D26: ='Data Collection Sheet'!AS137 -> 31.5 | H26: =(D26/B26)*100 -> 61.284047 | J26: 75
B27: 51.4 | C27: 45689 | D27: ='Data Collection Sheet'!AT$137 -> 31.4 | H27: =(D27/B27)*100 -> 61.089494 | J27: 75
B28: 51.4 | C28: 45717 | D28: ='Data Collection Sheet'!AU$137 -> 31.5 | H28: =(D28/B28)*100 -> 61.284047 | J28: 75
A29: Does Cisco support till this date ? | B29: 51.4 | C29: 45748 | D29: ='Data Collection Sheet'!AV$137 -> 31.7 | H29: =(D29/B29)*100 -> 61.673152 | J29: 75
B30: 51.4 | C30: 45778 | D30: ='Data Collection Sheet'!AW$137 -> 31.9 | H30: =(D30/B30)*100 -> 62.062257 | J30: 75
B31: 51.4 | C31: 45809 | D31: ='Data Collection Sheet'!AX$137 -> 31.9 | H31: =(D31/B31)*100 -> 62.062257 | J31: 75
B32: 51.4 | C32: 45839 | D32: ='Data Collection Sheet'!AY$137 -> 32.1 | H32: =(D32/B32)*100 -> 62.451362 | J32: 75
B33: 51.4 | C33: 45870 | D33: ='Data Collection Sheet'!AZ$137 -> 31.3 | H33: =(D33/B33)*100 -> 60.894942 | J33: 75
A34: from 12% to 8% increase | B34: 51.4 | C34: 45901 | D34: ='Data Collection Sheet'!BA$137 -> 31.8 | H34: =(D34/B34)*100 -> 61.867704 | J34: 75
B35: 51.4 | C35: 45931 | D35: ='Data Collection Sheet'!BB$137 -> 32.2 | H35: =(D35/B35)*100 -> 62.645914 | J35: 75
B36: 51.4 | C36: 45962 | D36: ='Data Collection Sheet'!BC$137 -> 32.1 | H36: =(D36/B36)*100 -> 62.451362 | J36: 75
B37: 51.4 | C37: 45992 | D37: ='Data Collection Sheet'!BD$137 -> 32.2 | H37: =(D37/B37)*100 -> 62.645914 | J37: 75
B38: 51.4 | C38: 46023 | D38: ='Data Collection Sheet'!BE$137 -> 32.3 | H38: =(D38/B38)*100 -> 62.840467 | J38: 75
B39: 51.4 | C39: 46054 | D39: ='Data Collection Sheet'!BF$137 -> 31.9 | H39: =(D39/B39)*100 -> 62.062257 | J39: 75
B40: 51.4 | C40: 46082 | D40: ='Data Collection Sheet'!BG$137 -> 31.4 | H40: =(D40/B40)*100 -> 61.089494 | J40: 75
B41: 51.4 | C41: 46113 | D41: ='Data Collection Sheet'!BH$137 -> 31.4 | H41: =(D41/B41)*100 -> 61.089494 | J41: 75
B42: 51.4 | C42: 46143 | D42: ='Data Collection Sheet'!BI$137 -> 31.8 | H42: =(D42/B42)*100 -> 61.867704 | J42: 75
B43: 51.4 | C43: 46174 | D43: ='Data Collection Sheet'!BJ$137 -> 31.9 | H43: =(D43/B43)*100 -> 62.062257 | J43: 75
B44: 51.4 | C44: 46204 | D44: ='Data Collection Sheet'!BK$137 -> 31.7 | H44: =(D44/B44)*100 -> 61.673152 | J44: 75
B45: 51.4 | C45: 46235 | D45: ='Data Collection Sheet'!BL$137 -> 31.6 | F45: 2.08 | G45: =D45 -> 31.6 | H45: =(D45/B45)*100 -> 61.478599 | I45: =(G45/B45)*100 -> 61.478599 | J45: 75
B46: 51.4 | C46: 46266 | F46: 1.08 | G46: =G45*(1+(F46^(1/12)-1))+E46 -> 31.803315 | I46: =(G46/B46)*100 -> 61.874154 | J46: 75
B47: 51.4 | C47: 46296 | F47: 1.08 | G47: =G46*(1+(F47^(1/12)-1))+E47 -> 32.007939 | I47: =(G47/B47)*100 -> 62.272255 | J47: 75
B48: 51.4 | C48: 46327 | F48: 1.08 | G48: =G47*(1+(F48^(1/12)-1))+E48 -> 32.213879 | I48: =(G48/B48)*100 -> 62.672916 | J48: 75
B49: 51.4 | C49: 46357 | F49: 1.08 | G49: =G48*(1+(F49^(1/12)-1))+E49 -> 32.421144 | I49: =(G49/B49)*100 -> 63.076156 | J49: 75
B50: 51.4 | C50: 46388 | F50: 1.08 | G50: =G49*(1+(F50^(1/12)-1))+E50 -> 32.629743 | I50: =(G50/B50)*100 -> 63.481989 | J50: 75
B51: 51.4 | C51: 46419 | F51: 1.08 | G51: =G50*(1+(F51^(1/12)-1))+E51 -> 32.839683 | I51: =(G51/B51)*100 -> 63.890434 | J51: 75
B52: 51.4 | C52: 46447 | F52: 1.08 | G52: =G51*(1+(F52^(1/12)-1))+E52 -> 33.050975 | I52: =(G52/B52)*100 -> 64.301507 | J52: 75
B53: 51.4 | C53: 46478 | F53: 1.08 | G53: =G52*(1+(F53^(1/12)-1))+E53 -> 33.263626 | I53: =(G53/B53)*100 -> 64.715225 | J53: 75
B54: 51.4 | C54: 46508 | F54: 1.08 | G54: =G53*(1+(F54^(1/12)-1))+E54 -> 33.477645 | I54: =(G54/B54)*100 -> 65.131605 | J54: 75
B55: 51.4 | C55: 46539 | F55: 1.08 | G55: =G54*(1+(F55^(1/12)-1))+E55 -> 33.693041 | I55: =(G55/B55)*100 -> 65.550664 | J55: 75
B56: 51.4 | C56: 46569 | F56: 1.08 | G56: =G55*(1+(F56^(1/12)-1))+E56 -> 33.909823 | I56: =(G56/B56)*100 -> 65.972419 | J56: 75
B57: 51.4 | C57: 46600 | F57: 1.08 | G57: =G56*(1+(F57^(1/12)-1))+E57 -> 34.128 | I57: =(G57/B57)*100 -> 66.396887 | J57: 75
... B97: 51.4 | C97: 47818 | F97: 1.08 | G97: =G96*(1+(F97^(1/12)-1))+E97 -> 44.108608 | I97: =(G97/B97)*100 -> 85.814413 | J97: 75

Sheet Commvault S3 Data Collection
C1: YoY growth = | D1: 1.15 | E1: % | G1: Month | I1: Jan'22 | J1: Feb'22 | K1: Mar'22 | L1: Apr'22 | M1: May'22 | N1: Jun'22 | O1: Jul'22 | P1: Aug'22 | Q1: Sep'22 | R1: Oct'22 | S1: Nov'22 | T1: Dec'22 | U1: Jan'23 | V1: Feb'23 | W1: Mar'23 | X1: Apr'23 | Y1: May'23 | Z1: Jun'23 | AA1: Jul'23 | AB1: Aug'23 | AC1: Sep'23 | AD1: Oct'23 | AE1: Nov'23 | AF1: Dec'23 | AG1: Jan'24 | AH1: Feb'24 | AI1: Mar'24 | AJ1: Apr'24 | AK1: May'24 | AL1: Jun'24 | AM1: Jul'24 | AN1: Aug'24 | AO1: Sept'24 | AP1: Oct'24 | AQ1: Nov'24 | AR1: Dec'24 | AS1: Jan'25 | AT1: Feb'25 | AU1: Mar'25 | AV1: Apr'25 | AW1: May'25 | AX1: Jun'25 | AY1: Jul'25 | AZ1: Aug'25 | BA1: Sept'25 | BB1: Oct'25 | BC1: Nov'25 | BD1: Dec'25 | BE1: Jan'26 | BF1: Feb'26 | BG1: Mar'26 | BH1: Apr'26 | BI1: May'26 | BJ1: Jun'26 | BK1: Jul'26 | BL1: Aug'26 | BM1: Sept'26 | BN1: Oct'26 | BO1: Nov'26 | BP1: Dec'26
D2: 4
G3: TOTAL Commavault S3 cost | I3: =I22+I28+I33+I38+I43+I54+I66 -> 0 | J3: =J22+J28+J33+J38+J43+J54+J66 -> 0 | K3: =K22+K28+K33+K38+K43+K54+K66 -> 0 | L3: =L22+L28+L33+L38+L43+L54+L66 -> 0 | M3: =M22+M28+M33+M38+M43+M54+M66 -> 0 | N3: =N22+N28+N33+N38+N43+N54+N66 -> 0 | O3: =O22+O28+O33+O38+O43+O54+O66 -> 0 | P3: =P22+P28+P33+P38+P43+P54+P66 -> 0 | ... BP3: =BP22+BP28+BP33+BP38+BP43+BP54+BP66 -> 0
B8: Region | E8: s3 bucket
I9: Jan'22 | J9: Feb'22 | K9: Mar'22 | L9: Apr'22 | M9: May'22 | N9: Jun'22 | O9: Jul'22 | P9: Aug'22 | Q9: Sep'22 | R9: Oct'22 | S9: Nov'22 | T9: Dec'22 | U9: Jan'23 | V9: Feb'23 | W9: Mar'23 | X9: Apr'23 | Y9: May'23 | Z9: Jun'23 | AA9: Jul'23 | AB9: Aug'23 | AC9: Sep'23 | AD9: Oct'23 | AE9: Nov'23 | AF9: Dec'23 | AG9: Jan'24 | AH9: Feb'24 | AI9: Mar'24 | AJ9: Apr'24 | AK9: May'24 | AL9: Jun'24 | AM9: Jul'24 | AN9: Aug'24 | AO9: Sept'24 | AP9: Oct'24 | AQ9: Nov'24 | AR9: Dec'24 | AS9: Jan'25 | AT9: Feb'25 | AU9: Mar'25 | AV9: Apr'25 | AW9: May'25 | AX9: Jun'25 | AY9: Jul'25 | AZ9: Aug'25 | BA9: Sept'25 | BB9: Oct'25 | BC9: Nov'25 | BD9: Dec'25 | BE9: Jan'26 | BF9: Feb'26 | BG9: Mar'26 | BH9: Apr'26 | BI9: May'26 | BJ9: Jun'26 | BK9: Jul'26 | BL9: Aug'26 | BM9: Sept'26 | BN9: Oct'26 | BO9: Nov'26 | BP9: Dec'26
B10: ap-southeast-2 | C10: Sydney | E10: aum-backup-commvault-01 | U10: 4355.97 | V10: 4139.62 | W10: 4260.95 | X10: 4341.95 | Y10: 4357.27 | Z10: 4325.63 | AA10: 4330.15 | AB10: 4754.49 | AC10: 5254.97 | AD10: 5689.65 | AE10: 6001.53 | AF10: 7061.3 | AG10: 7268.11 | AH10: 7581.7 | AI10: 7235.3 | AJ10: 9266.83 | AK10: 7116.95 | AL10: 6863.74 | AM10: 6440.3 | AN10: 6567.6883 | AO10: 6519 | AP10: 6484.63 | AQ10: 6481.16 | AR10: 6346.41 | AS10: 6238.04 | AT10: 6225.7 | AU10: 6163.67 | AV10: 6240.73 | AW10: 6337.56 | AX10: 6376.41 | AY10: 6815.34 | AZ10: 7148.45 | BA10: 7305.92 | BB10: 7606.37 | BC10: 7625.04 | BD10: 7547.03 | BE10: 7693.63 | BF10: 7713.84 | BG10: 7753.14 | BH10: 7813.77 | BI10: 7962.38 | BJ10: 8160.58 | BK10: 8138.12
E11: aum-backup-commvault-02 | U11: 88.25 | V11: 0.21 | W11: 0.16 | X11: 0.16 | Y11: 0.16 | Z11: 0.16 | AA11: 0.16 | AB11: 0.16 | AC11: 0.16 | AD11: 0.16 | AE11: 0.16 | AF11: 0.16 | AG11: 0.16 | AH11: 0.16 | AI11: 0.16 | AJ11: 0.16 | AK11: 0.16 | AL11: 0.16 | AM11: 0.16 | AN11: 0.16 | AO11: 0.16 | AP11: 0.16 | AQ11: 0.16 | AR11: 0.16 | AS11: 0.16 | AT11: 0.16 | AU11: 0.16 | AV11: 0.16 | AW11: 0.16 | AX11: 0.16 | AY11: 0.17 | AZ11: 0.17 | BA11: 0.17 | BB11: 0.17 | BC11: 0.17 | BD11: 0.17 | BE11: 0.17 | BF11: 0.17 | BG11: 0.17 | BH11: 0.17 | BI11: 0.17 | BJ11: 0.17 | BK11: 0.16
E12: aub-backup-commvault-01 | U12: 381.29 | V12: 383 | W12: 403.05 | X12: 468.83 | Y12: 442.49 | Z12: 546.63 | AA12: 577.78 | AB12: 661 | AC12: 608.19 | AD12: 633.35 | AE12: 596.63 | AF12: 672.04 | AG12: 781.07 | AH12: 738.59 | AI12: 681.9 | AJ12: 804.63 | AK12: 682.23 | AL12: 723.62 | AM12: 727.2 | AN12: 752.221 | AO12: 725 | AP12: 726 | AQ12: 728.66 | AR12: 733.75 | AS12: 756.69 | AT12: 762.26 | AU12: 765.43 | AV12: 765.02 | AW12: 766.52 | AX12: 769.13 | AY12: 776.03 | AZ12: 782.68 | BA12: 789.16 | BB12: 793.46 | BC12: 798.75 | BD12: 808.95 | BE12: 817.95 | BF12: 829 | BG12: 836.59 | BH12: 822.4 | BI12: 827.27 | BJ12: 834.64 | BK12: 820.51
E13: aps2-commvault-backup-str-01 | U13: 2.78 | V13: 1.26 | W13: 15.64 | X13: 14.3 | Y13: 12.19 | Z13: 12.18 | AA13: 11.77 | AB13: 11.81 | AC13: 12.01 | AD13: 12.7 | AE13: 13.91 | AF13: 14.03 | AG13: 14.13 | AH13: 30.07 | AI13: 24.59 | AJ13: 27.55 | AK13: 33.95 | AL13: 43.96 | AM13: 44.4 | AN13: 46.0548 | AO13: 48.1 | AP13: 43.35 | AQ13: 44.17 | AR13: 42.98 | AS13: 40.88 | AT13: 45.83 | AU13: 52.2 | AV13: 71.39 | AW13: 93.4 | AX13: 110.01 | AY13: 99.07 | AZ13: 77.26 | BA13: 49.47 | BB13: 20.33 | BC13: 15.66 | BD13: 15.66 | BE13: 15.65 | BF13: 15.57 | BG13: 15.49 | BH13: 14.84 | BI13: 18.09 | BJ13: 80.12 | BK13: 118.92
E14: aps2-commvault-backup-ltr-im-01 | Y14: 0.19 | Z14: 0.13 | AA14: 0.51 | AB14: 181.87 | AC14: 299.32 | AD14: 730.64 | AE14: 985.57 | AF14: 1394.19 | AG14: 1495.44 | AH14: 1713.13 | AI14: 1750.01 | AJ14: 2426.72 | AK14: 2189.67 | AL14: 2104.86 | AM14: 2682.7 | AN14: 3141.9892 | AO14: 3209 | AP14: 3495.81 | AQ14: 3506.38 | AR14: 3879.68 | AS14: 4303.7 | AT14: 4258.1 | AU14: 4310.26 | AV14: 4460.52 | AW14: 4781.2 | AX14: 4856.47 | AY14: 5062.46 | AZ14: 5255.87 | BA14: 5728.88 | BB14: 6096.84 | BC14: 6374.46 | BD14: 6686.05 | BE14: 6905.97 | BF14: 6698.86 | BG14: 6989.63 | BH14: 7338.27 | BI14: 7533.59 | BJ14: 8026.9 | BK14: 8288.75
E15: aps2-commvault-backup-ltr-im-01-ddb512kb | Z15: 0.01 | AA15: 0.01 | AB15: 0.01 | AC15: 0.02 | AD15: 0.02 | AE15: 0.04 | AF15: 0.04 | AG15: 0.04 | AH15: 0.03 | AI15: 0.01 | AJ15: 0.01 | AK15: 0.01 | AL15: 0.01 | AM15: 0.01 | AN15: 0.01 | AO15: 0.01 | AP15: 0.01 | AQ15: 0.01 | AR15: 0.01 | AS15: 0.01 | AT15: 0.01 | AU15: 0.01 | AV15: 0.01 | AW15: 0.01 | AX15: 0.01 | AY15: 0.01 | AZ15: 0.01 | BA15: 0.01 | BB15: 0.01 | BC15: 0.01 | BD15: 0.01 | BE15: 0.01 | BF15: 0.01 | BG15: 0.01 | BH15: 0.01 | BI15: 0.01 | BJ15: 0.01 | BK15: 0.01
E16: aps2-commvault-backup-ltr-quarterly-2y-01 | Y16: 0.13 | Z16: 0.08 | AA16: 0.97 | AB16: 0.28 | AC16: 78.17 | AD16: 164.7 | AE16: 93.98 | AF16: 108.47 | AG16: 228.61 | AH16: 150.71 | AI16: 159.97 | AJ16: 261.04 | AK16: 205.01 | AL16: 219.06 | AM16: 233.02 | AN16: 244.8799 | AO16: 251.4 | AP16: 298.02 | AQ16: 302.2 | AR16: 304.35 | AS16: 314.98 | AT16: 318.17 | AU16: 321.4 | AV16: 330.16 | AW16: 333.35 | AX16: 336.59 | AY16: 389.46 | AZ16: 396.49 | BA16: 399.71 | BB16: 423.57 | BC16: 429.91 | BD16: 434.18 | BE16: 447.03 | BF16: 451.49 | BG16: 455.01 | BH16: 429.81 | BI16: 435.57 | BJ16: 439.04 | BK16: 470.05
E17: aps2-commvault-backup-ltr-quarterly-2y-01-ddb512kb | Z17: 0.06 | AA17: 0.01 | AB17: 0.01 | AC17: 0.02 | AD17: 0.04 | AE17: 0.04 | AF17: 0.04 | AG17: 0.04 | AH17: 0.03 | AI17: 0.01 | AJ17: 0.01 | AK17: 0.01 | AL17: 0.01 | AM17: 0.01 | AN17: 0.01 | AO17: 0.01 | AP17: 0.01 | AQ17: 0.01 | AR17: 0.01 | AS17: 0.01 | AT17: 0.01 | AU17: 0.01 | AV17: 0.01 | AW17: 0.01 | AX17: 0.01 | AY17: 0.01 | AZ17: 0.01 | BA17: 0.01 | BB17: 0.01 | BC17: 0.01 | BD17: 0.01 | BE17: 0.01 | BF17: 0.01 | BG17: 0.01 | BH17: 0.01 | BI17: 0.01 | BJ17: 0.01 | BK17: 0.01
E18: aps2-commvault-backup-ltr-yearly-7y-01 | Y18: 0.06 | Z18: 0.01 | AA18: 0.03 | AB18: 0.31 | AC18: 1.53 | AD18: 4.71 | AE18: 8.26 | AF18: 9.95 | AG18: 24.41 | AH18: 22.76 | AI18: 18.38 | AJ18: 18.39 | AK18: 20 | AL18: 20.15 | AM18: 19.4 | AN18: 20.0547 | AO18: 20.0547 | AP18: 20.0547 | AQ18: 20.18 | AR18: 20.37 | AS18: 31.8 | AT18: 32.71 | AU18: 36.77 | AV18: 36.77 | AW18: 36.78 | AX18: 36.79 | AY18: 36.82 | AZ18: 36.85 | BA18: 36.85 | BB18: 36.85 | BC18: 37.87 | BD18: 39.27 | BE18: 48.24 | BF18: 49.07 | BG18: 49.07 | BH18: 36.98 | BI18: 33.42 | BJ18: 33.44 | BK18: 32.42
E19: aps2-commvault-backup-ltr-yearly-15y-01 | Y19: 0.06 | Z19: 0.01 | AA19: 0.01 | AB19: 0.02 | AC19: 0.39 | AD19: 1.33 | AE19: 3.83 | AF19: 1.93 | AG19: 0.26 | AH19: 0.55 | AI19: 0.13 | AJ19: 0.13 | AK19: 0.13 | AL19: 0.13 | AM19: 0.13 | AN19: 0.1178 | AO19: 0.12 | AP19: 0.12 | AQ19: 0.12 | AR19: 0.12 | AS19: 0.12 | AT19: 0.12 | AU19: 0.12 | AV19: 0.12 | AW19: 0.12 | AX19: 0.12 | AY19: 0.12 | AZ19: 0.12 | BA19: 0.12 | BB19: 0.12 | BC19: 0.12 | BD19: 0.11 | BE19: 0.11 | BF19: 0.11 | BG19: 0.11 | BH19: 0.03 | BI19: 0.01 | BJ19: 0.01 | BK19: 0.01
E20: aps2-commvault-backup-ltr-yearly-infinite-01 | Y20: 0.06 | Z20: 0.01 | AA20: 0.02 | AB20: 0.34 | AC20: 8.07 | AD20: 35.57 | AE20: 46.2 | AF20: 48.27 | AG20: 92.9 | AH20: 96.78 | AI20: 90.09 | AJ20: 111.09 | AK20: 111.93 | AL20: 121.03 | AM20: 116.57 | AN20: 120.4682 | AO20: 124.89 | AP20: 130.58 | AQ20: 131.96 | AR20: 132.82 | AS20: 147.3 | AT20: 150.12 | AU20: 151.68 | AV20: 151.72 | AW20: 151.88 | AX20: 151.94 | AY20: 182.38 | AZ20: 185.71 | BA20: 185.76 | BB20: 185.76 | BC20: 185.8 | BD20: 186.89 | BE20: 214.32 | BF20: 227.17 | BG20: 234.98 | BH20: 241.75 | BI20: 241.66 | BJ20: 241.82 | BK20: 232.95
G22: TOTAL cost | I22: =SUM(I10:I21) -> 0 | J22: =SUM(J10:J21) -> 0 | K22: =SUM(K10:K21) -> 0 | L22: =SUM(L10:L21) -> 0 | M22: =SUM(M10:M21) -> 0 | N22: =SUM(N10:N21) -> 0 | O22: =SUM(O10:O21) -> 0 | P22: =SUM(P10:P21) -> 0 | ... BP22: =SUM(BP10:BP21) -> 0
B25: ap-east-1 | C25: Hong Kong | E25: ap-east-1-backup-commvault-01 | AC25: 0 | AD25: 0 | AE25: 0 | AF25: 0 | AG25: 0 | AH25: 0 | AI25: 0 | AJ25: 0 | AK25: 0 | AL25: 0 | AM25: 0 | AN25: 0 | AO25: 0 | AP25: 0 | AQ25: 0 | AR25: 0 | AS25: 0 | AT25: 0 | AU25: 0 | AV25: 0 | AW25: 0 | AX25: 0 | AY25: 0 | AZ25: 0 | BA25: 0 | BB25: 0 | BC25: 0 | BD25: 0 | BE25: 0 | BF25: 0 | BG25: 0 | BH25: 0 | BI25: 0 | BJ25: 0 | BK25: 0
E26: cnc-backup-commvault-01 | AD26: 2.55 | AE26: 8.57 | AF26: 21.65 | AG26: 26.35 | AH26: 30.84 | AI26: 35.64 | AJ26: 42.96 | AK26: 52.97 | AL26: 57.4 | AM26: 57.6 | AN26: 61.9132 | AO26: 64.68 | AP26: 64.07 | AQ26: 66.07 | AR26: 68.68 | AS26: 68.99 | AT26: 70.78 | AU26: 73.51 | AV26: 76.56 | AW26: 81.49 | AX26: 85.08 | AY26: 89.13 | AZ26: 91.5 | BA26: 94.77 | BB26: 97.39 | BC26: 99.05 | BD26: 101.32 | BE26: 104.05 | BF26: 109.1 | BG26: 112.6 | BH26: 113.98 | BI26: 118.77 | BJ26: 123.27 | BK26: 124.86
G28: TOTAL cost | I28: =SUM(I25:I27) -> 0 | J28: =SUM(J25:J27) -> 0 | K28: =SUM(K25:K27) -> 0 | L28: =SUM(L25:L27) -> 0 | M28: =SUM(M25:M27) -> 0 | N28: =SUM(N25:N27) -> 0 | O28: =SUM(O25:O27) -> 0 | P28: =SUM(P25:P27) -> 0 | ... BP28: =SUM(BP25:BP27) -> 0
B31: ap-southeast-1 | C31: Singapore | E31: myk-backup-commvault-01 | AC31: 0 | AD31: 1.56 | AE31: 10.56 | AF31: 27.28 | AG31: 35.74 | AH31: 43.44 | AI31: 50.25 | AJ31: 53.31 | AK31: 62.8 | AL31: 64.3 | AM31: 69.89 | AN31: 79.49 | AO31: 81.97 | AP31: 84.77 | AQ31: 87.34 | AR31: 90.1 | AS31: 89.21 | AT31: 90.06 | AU31: 91.43 | AV31: 91.51 | AW31: 95.06 | AX31: 97.77 | AY31: 102.32 | AZ31: 106.9 | BA31: 110.4 | BB31: 115.75 | BC31: 120.17 | BD31: 122.69 | BE31: 124.66 | BF31: 129.79 | BG31: 131.93 | BH31: 136.68 | BI31: 145.68 | BJ31: 146.77 | BK31: 145.89
G33: TOTAL cost | I33: =SUM(I31:I32) -> 0 | J33: =SUM(J31:J32) -> 0 | K33: =SUM(K31:K32) -> 0 | L33: =SUM(L31:L32) -> 0 | M33: =SUM(M31:M32) -> 0 | N33: =SUM(N31:N32) -> 0 | O33: =SUM(O31:O32) -> 0 | P33: =SUM(P31:P32) -> 0 | ... BP33: =SUM(BP31:BP32) -> 0
B36: eu-west-3 | C36: Paris | E36: bem-backup-commvault-01 | U36: 911.21 | V36: 834.57 | W36: 859.3 | X36: 900.62 | Y36: 939.49 | Z36: 960.97 | AA36: 1021.04 | AB36: 1051.98 | AC36: 1105.19 | AD36: 1132.94 | AE36: 1173.35 | AF36: 1188.92 | AG36: 1196.62 | AH36: 1265.97 | AI36: 1260.39 | AJ36: 1294.3 | AK36: 1283.65 | AL36: 1156.34 | AM36: 1100.87 | AN36: 1190.28 | AO36: 1217.84 | AP36: 1254.64 | AQ36: 1250.92 | AR36: 1305.88 | AS36: 1508.6 | AT36: 1557.29 | AU36: 1602.01 | AV36: 1628.54 | AW36: 1666.73 | AX36: 1692.25 | AY36: 1703.01 | AZ36: 1725.51 | BA36: 1753.81 | BB36: 1779.92 | BC36: 1745.62 | BD36: 1675.2 | BE36: 1666.1 | BF36: 1695.27 | BG36: 1715.43 | BH36: 1732.14 | BI36: 1790.81 | BJ36: 1831.46 | BK36: 1832.31
G38: TOTAL cost | I38: =SUM(I36:I37) -> 0 | J38: =SUM(J36:J37) -> 0 | K38: =SUM(K36:K37) -> 0 | L38: =SUM(L36:L37) -> 0 | M38: =SUM(M36:M37) -> 0 | N38: =SUM(N36:N37) -> 0 | O38: =SUM(O36:O37) -> 0 | P38: =SUM(P36:P37) -> 0 | ... BP38: =SUM(BP36:BP37) -> 0
B41: eu-north-1 | C41: Stockholm | E41: seg-backup-commvault-01 | U41: 693.15 | V41: 702.44 | W41: 719.39 | X41: 735.08 | Y41: 745.9 | Z41: 726.59 | AA41: 717.57 | AB41: 707.82 | AC41: 698.75 | AD41: 702.08 | AE41: 705.08 | AF41: 713.07 | AG41: 712.51 | AH41: 708.1 | AI41: 713.68 | AJ41: 713.53 | AK41: 708.16 | AL41: 834.47 | AM41: 1040.45 | AN41: 1063.91 | AO41: 871.32 | AP41: 513.16 | AQ41: 460.24 | AR41: 465.07 | AS41: 466.66 | AT41: 470.2 | AU41: 492.12 | AV41: 559.08 | AW41: 565.78 | AX41: 566.9 | AY41: 597.53 | AZ41: 588.05 | BA41: 578.7 | BB41: 588.16 | BC41: 579.91 | BD41: 486.45 | BE41: 482.13 | BF41: 467.48 | BG41: 462.82 | BH41: 463.77 | BI41: 478.57 | BJ41: 493.83 | BK41: 484.62
G43: TOTAL cost | I43: =SUM(I41:I41) -> 0 | J43: =SUM(J41:J41) -> 0 | K43: =SUM(K41:K41) -> 0 | L43: =SUM(L41:L41) -> 0 | M43: =SUM(M41:M41) -> 0 | N43: =SUM(N41:N41) -> 0 | O43: =SUM(O41:O41) -> 0 | P43: =SUM(P41:P41) -> 0 | ... BP43: =SUM(BP41:BP41) -> 0
B46: eu-central-1 | C46: Frankfurt | E46: euc1-commvault-backup-sf-01 | U46: 0 | V46: 0.3 | W46: 0.06 | X46: 0.05 | Y46: 0.95 | Z46: 0.06 | AA46: 0.1 | AB46: 0.43 | AC46: 0.84 | AD46: 2.11 | AE46: 4.26 | AF46: 6.58 | AG46: 7.5 | AH46: 7.3 | AI46: 3.99 | AJ46: 4.71 | AK46: 5.57 | AL46: 6.34 | AM46: 7.47 | AN46: 8.53 | AO46: 8.63 | AP46: 9.39 | AQ46: 9.87 | AR46: 10.55 | AS46: 11.04 | AT46: 11.7 | AU46: 11.65 | AV46: 12.93 | AW46: 13.34 | AX46: 13.78 | AY46: 13.64 | AZ46: 14.32 | BA46: 15.06 | BB46: 15 | BC46: 15.12 | BD46: 16.05 | BE46: 15.2 | BF46: 15.79 | BG46: 15.68 | BH46: 16.26 | BI46: 18.4 | BJ46: 23 | BK46: 25.9
E47: euc1-commvault-backup-ltr-im-01 | U47: 0 | V47: 0 | W47: 0 | X47: 0 | Y47: 0 | Z47: 0 | AA47: 0 | AB47: 0 | AC47: 0 | AD47: 0 | AE47: 0 | AF47: 0 | AG47: 0 | AH47: 0 | AI47: 0 | AJ47: 0 | AK47: 0.05 | AL47: 21.53 | AM47: 118.01 | AN47: 187.29 | AO47: 259.77 | AP47: 301.85 | AQ47: 349.24 | AR47: 410 | AS47: 475.83 | AT47: 576.19 | AU47: 586.1 | AV47: 601.77 | AW47: 665.61 | AX47: 756.12 | AY47: 833.98 | AZ47: 920.54 | BA47: 986.41 | BB47: 1063.58 | BC47: 1167.16 | BD47: 1238.5 | BE47: 1319.98 | BF47: 1372.92 | BG47: 1391.47 | BH47: 1472.86 | BI47: 1573.5 | BJ47: 1654.43 | BK47: 1723.57
E48: euc1-commvault-backup-ltr-quarterly-2y-01 | U48: 0 | V48: 0 | W48: 0 | X48: 0 | Y48: 0 | Z48: 0 | AA48: 0 | AB48: 0 | AC48: 0 | AD48: 0 | AE48: 0 | AF48: 0 | AG48: 0 | AH48: 0 | AI48: 0 | AJ48: 0 | AK48: 0 | AL48: 0.12 | AM48: 0.1 | AN48: 0.1 | AO48: 0.11 | AP48: 0.14 | AQ48: 0.14 | AR48: 0.15 | AS48: 0.18 | AT48: 0.18 | AU48: 0.19 | AV48: 0.23 | AW48: 0.22 | AX48: 0.22 | AY48: 0.36 | AZ48: 0.37 | BA48: 0.37 | BB48: 0.58 | BC48: 0.59 | BD48: 0.63 | BE48: 1.51 | BF48: 1.55 | BG48: 1.59 | BH48: 2.07 | BI48: 1.99 | BJ48: 1.92 | BK48: 5.85
E49: euc1-commvault-backup-ltr-yearly-7y-01 | U49: 0 | V49: 0 | W49: 0 | X49: 0 | Y49: 0 | Z49: 0 | AA49: 0 | AB49: 0 | AC49: 0 | AD49: 0 | AE49: 0 | AF49: 0 | AG49: 0 | AH49: 0 | AI49: 0 | AJ49: 0 | AK49: 0 | AL49: 0 | AM49: 0 | AN49: 0 | AO49: 0 | AP49: 0 | AQ49: 0 | AR49: 0 | AS49: 0.099 | AT49: 0.098 | AU49: 0.099 | AV49: 0.099 | AW49: 0.096 | AX49: 0.1 | AY49: 0.1 | AZ49: 0.1 | BA49: 0.1 | BB49: 0.1 | BC49: 0.1 | BD49: 0.11 | BE49: 1.04 | BF49: 1.04 | BG49: 1.04 | BH49: 1.04 | BI49: 1.04 | BJ49: 1.05 | BK49: 1.03
E50: euc1-commvault-backup-ltr-yearly-infinite-01 | U50: 0 | V50: 0 | W50: 0 | X50: 0 | Y50: 0 | Z50: 0 | AA50: 0 | AB50: 0 | AC50: 0 | AD50: 0 | AE50: 0 | AF50: 0 | AG50: 0 | AH50: 0 | AI50: 0 | AJ50: 0 | AK50: 0 | AL50: 0 | AM50: 0 | AN50: 0 | AO50: 0 | AP50: 0 | AQ50: 0 | AR50: 0 | AS50: 0 | AT50: 0 | AU50: 0 | AV50: 0 | AW50: 0 | AX50: 0 | AY50: 0 | AZ50: 0 | BA50: 0 | BB50: 0 | BC50: 0 | BD50: 0 | BE50: 0.11 | BF50: 0.11 | BG50: 0.11 | BH50: 0.11 | BI50: 0.11 | BJ50: 0.11 | BK50: 0.11
E51: euc1-commvault-backup-ltr-yearly-15y-01 | U51: 0 | V51: 0 | W51: 0 | X51: 0 | Y51: 0 | Z51: 0 | AA51: 0 | AB51: 0 | AC51: 0 | AD51: 0 | AE51: 0 | AF51: 0 | AG51: 0 | AH51: 0 | AI51: 0 | AJ51: 0 | AK51: 0 | AL51: 0 | AM51: 0 | AN51: 0 | AO51: 0 | AP51: 0 | AQ51: 0 | AR51: 0 | AS51: 0 | AT51: 0 | AU51: 0 | AV51: 0 | AW51: 0 | AX51: 0 | AY51: 0 | AZ51: 0 | BA51: 0 | BB51: 0 | BC51: 0 | BD51: 0 | BE51: 0 | BF51: 0 | BG51: 0 | BH51: 0 | BI51: 0 | BJ51: 0 | BK51: 0
E52: eur-backup-commvault-sf-01 | U52: 17.44 | V52: 17.21 | W52: 17.55 | X52: 17.78 | Y52: 18.2 | Z52: 18.58 | AA52: 18.7 | AB52: 19 | AC52: 19.24 | AD52: 19.6 | AE52: 20.14 | AF52: 21.29 | AG52: 21.23 | AH52: 26.34 | AI52: 19.77 | AJ52: 20.04 | AK52: 20.39 | AL52: 20.66 | AM52: 23.77 | AN52: 25.61 | AO52: 26.11 | AP52: 26.55 | AQ52: 25.86 | AR52: 25.8 | AS52: 25.28 | AT52: 25.16 | AU52: 24.73 | AV52: 24.52 | AW52: 24.29 | AX52: 24.04 | AY52: 23.76 | AZ52: 23.28 | BA52: 22.69 | BB52: 21.8 | BC52: 20.97 | BD52: 19.28 | BE52: 17.76 | BF52: 17.77 | BG52: 17.77 | BH52: 17.77 | BI52: 17.77 | BJ52: 17.77 | BK52: 17.2
G54: TOTAL cost | I54: =SUM(I46:I53) -> 0 | J54: =SUM(J46:J53) -> 0 | K54: =SUM(K46:K53) -> 0 | L54: =SUM(L46:L53) -> 0 | M54: =SUM(M46:M53) -> 0 | N54: =SUM(N46:N53) -> 0 | O54: =SUM(O46:O53) -> 0 | P54: =SUM(P46:P53) -> 0 | ... BP54: =SUM(BP46:BP53) -> 0
B57: us-west-2 | C57: Oregon | E57: usd-backup-commvault-01 | U57: 759.02 | V57: 754.34 | W57: 765.22 | X57: 852.67 | Y57: 1538.09 | Z57: 1155.5 | AA57: 723.58 | AB57: 655.01 | AC57: 575.24 | AD57: 599.14 | AE57: 659.14 | AF57: 685.01 | AG57: 697.8 | AH57: 687.54 | AI57: 703.84 | AJ57: 714.22 | AK57: 760.51 | AL57: 744.89 | AM57: 723.32 | AN57: 757.59 | AO57: 798.36 | AP57: 788.97 | AQ57: 796.55 | AR57: 806.4 | AS57: 764.9 | AT57: 777.86 | AU57: 788.56 | AV57: 796.26 | AW57: 811.68 | AX57: 800.14 | AY57: 798.77 | AZ57: 811.19 | BA57: 819.55 | BB57: 826.48 | BC57: 837.63 | BD57: 847.37 | BE57: 857.81 | BF57: 884.33 | BG57: 910.5 | BH57: 939.23 | BI57: 977.73 | BJ57: 1011.85 | BK57: 1000.53
E58: usd-backup-commvault-laptops-01 | U58: 0 | V58: 0 | W58: 0 | X58: 0 | Y58: 0 | Z58: 0 | AA58: 0 | AB58: 0 | AC58: 0 | AD58: 0 | AE58: 0 | AF58: 0 | AG58: 0 | AH58: 0 | AI58: 0 | AJ58: 0 | AK58: 0 | AL58: 0 | AM58: 0 | AN58: 0 | AO58: 0 | AP58: 0 | AQ58: 0 | AR58: 0 | AS58: 0 | AT58: 0 | AU58: 0 | AV58: 0 | AW58: 0 | AX58: 0 | AY58: 0 | AZ58: 0 | BA58: 0 | BB58: 0 | BC58: 0 | BD58: 0 | BE58: 0 | BF58: 0 | BG58: 0 | BH58: 0 | BI58: 0 | BJ58: 0 | BK58: 0
E59: usd-backup-commvault-usd-fps-prd01 | U59: 41.48 | V59: 41.09 | W59: 41.35 | X59: 43.55 | Y59: 43.83 | Z59: 44.9 | AA59: 46.05 | AB59: 46.73 | AC59: 47 | AD59: 612.84 | AE59: 46.35 | AF59: 46.11 | AG59: 45.86 | AH59: 45.62 | AI59: 45.41 | AJ59: 45.34 | AK59: 45.35 | AL59: 45.35 | AM59: 51.39 | AN59: 53.1 | AO59: 53.1 | AP59: 53.1 | AQ59: 53.1 | AR59: 53.1 | AS59: 53.1 | AT59: 53.1 | AU59: 53.1 | AV59: 21.24 | AW59: 0 | AX59: 0 | AY59: 0 | AZ59: 0 | BA59: 0 | BB59: 0 | BC59: 0 | BD59: 0 | BE59: 0 | BF59: 0 | BG59: 0 | BH59: 0 | BI59: 0 | BJ59: 0 | BK59: 0
E60: usw2-commvault-backup-ltr-yearly-infinite-01 | U60: 0 | V60: 0 | W60: 0 | X60: 0 | Y60: 0 | Z60: 0 | AA60: 0 | AB60: 0 | AC60: 0 | AD60: 0 | AE60: 0 | AF60: 0 | AG60: 0 | AH60: 0 | AI60: 0 | AJ60: 0 | AK60: 0 | AL60: 0 | AM60: 0 | AN60: 0 | AO60: 0 | AP60: 0 | AQ60: 0 | AR60: 0 | AS60: 0 | AT60: 0 | AU60: 0 | AV60: 0 | AW60: 0 | AX60: 0 | AY60: 0 | AZ60: 0 | BA60: 0 | BB60: 0 | BC60: 0 | BD60: 0 | BE60: 0 | BF60: 0 | BG60: 0 | BH60: 0 | BI60: 0 | BJ60: 0 | BK60: 0
E61: usw2-commvault-backup-ltr-quarterly-2y-01 | U61: 0 | V61: 0 | W61: 0 | X61: 0 | Y61: 0 | Z61: 0 | AA61: 0 | AB61: 0 | AC61: 0 | AD61: 0 | AE61: 0 | AF61: 0 | AG61: 0 | AH61: 0 | AI61: 0 | AJ61: 0 | AK61: 0 | AL61: 0 | AM61: 0 | AN61: 1.01 | AO61: 2.45 | AP61: 3.1 | AQ61: 3.37 | AR61: 3.53 | AS61: 3.99 | AT61: 4.18 | AU61: 4.3 | AV61: 4.73 | AW61: 4.83 | AX61: 4.93 | AY61: 5.36 | AZ61: 5.46 | BA61: 5.62 | BB61: 8.4 | BC61: 8.51 | BD61: 8.6 | BE61: 8.88 | BF61: 8.94 | BG61: 9.02 | BH61: 9.28 | BI61: 9.33 | BJ61: 9.4 | BK61: 9.32
E62: usw2-commvault-backup-ltr-yearly-15y-01 | U62: 0 | V62: 0 | W62: 0 | X62: 0 | Y62: 0 | Z62: 0 | AA62: 0 | AB62: 0 | AC62: 0 | AD62: 0 | AE62: 0 | AF62: 0 | AG62: 0 | AH62: 0 | AI62: 0 | AJ62: 0 | AK62: 0 | AL62: 0 | AM62: 0 | AN62: 0 | AO62: 0 | AP62: 0 | AQ62: 0 | AR62: 0 | AS62: 0 | AT62: 0 | AU62: 0 | AV62: 0 | AW62: 0 | AX62: 0 | AY62: 0 | AZ62: 0 | BA62: 0 | BB62: 0 | BC62: 0 | BD62: 0 | BE62: 0 | BF62: 0 | BG62: 0 | BH62: 0 | BI62: 0 | BJ62: 0 | BK62: 0
E63: usw2-commvault-backup-ltr-yearly-7y-01 | U63: 0 | V63: 0 | W63: 0 | X63: 0 | Y63: 0 | Z63: 0 | AA63: 0 | AB63: 0 | AC63: 0 | AD63: 0 | AE63: 0 | AF63: 0 | AG63: 0 | AH63: 0 | AI63: 0 | AJ63: 0 | AK63: 0 | AL63: 0 | AM63: 0 | AN63: 0.98 | AO63: 2.21 | AP63: 2.28 | AQ63: 2.28 | AR63: 2.28 | AS63: 2.73 | AT63: 2.78 | AU63: 2.78 | AV63: 2.88 | AW63: 2.9 | AX63: 2.9 | AY63: 2.9 | AZ63: 2.9 | BA63: 2.9 | BB63: 2.9 | BC63: 2.9 | BD63: 3.09 | BE63: 5.11 | BF63: 5.13 | BG63: 5.26 | BH63: 5.29 | BI63: 5.29 | BJ63: 5.29 | BK63: 5.12
E64: usw2-commvault-backup-ltr-im-01 | U64: 0 | V64: 0 | W64: 0 | X64: 0 | Y64: 0 | Z64: 0 | AA64: 0 | AB64: 0 | AC64: 0 | AD64: 0 | AE64: 0 | AF64: 0 | AG64: 0 | AH64: 0 | AI64: 0 | AJ64: 0 | AK64: 0 | AL64: 0 | AM64: 0 | AN64: 9.36 | AO64: 64.27 | AP64: 173.02 | AQ64: 252.99 | AR64: 331.68 | AS64: 400 | AT64: 450 | AU64: 513.5 | AV64: 595.16 | AW64: 662.91 | AX64: 747.55 | AY64: 820.66 | AZ64: 885.11 | BA64: 943 | BB64: 1010.72 | BC64: 1054.74 | BD64: 1143.55 | BE64: 1184.31 | BF64: 1269.59 | BG64: 1301.84 | BH64: 1392.4 | BI64: 1432.17 | BJ64: 1535.36 | BK64: 1543.89
G66: TOTAL cost | I66: =SUM(I57:I65) -> 0 | J66: =SUM(J57:J65) -> 0 | K66: =SUM(K57:K65) -> 0 | L66: =SUM(L57:L65) -> 0 | M66: =SUM(M57:M65) -> 0 | N66: =SUM(N57:N65) -> 0 | O66: =SUM(O57:O65) -> 0 | P66: =SUM(P57:P65) -> 0 | ... BP66: =SUM(BP57:BP65) -> 0

Sheet Commvault S3 All Regions
A1: S3 All Regions (10% YoY) | B1: Total Storage | C1: Month | D1: Cost ($) | E1: Change ($) | F1: Growth (%) | G1: Forecast ($)
B2: 45 | C2: 44927 | D2: =('Commvault S3 Data Collection'!U3) -> 7250.59
B3: 45 | C3: 44958 | D3: =('Commvault S3 Data Collection'!V3) -> 6874.04
B4: 45 | C4: 44986 | D4: ='Commvault S3 Data Collection'!W3 -> 7082.67
B5: 45 | C5: 45017 | D5: ='Commvault S3 Data Collection'!X3 -> 7374.99
B6: 45 | C6: 45047 | D6: ='Commvault S3 Data Collection'!Y3 -> 8099.07
B7: 45 | C7: 45078 | D7: ='Commvault S3 Data Collection'!Z3 -> 7791.51
B8: 45 | C8: 45108 | D8: ='Commvault S3 Data Collection'!AA3 -> 7448.46
B9: 45 | C9: 45139 | D9: ='Commvault S3 Data Collection'!AB3 -> 8091.27
B10: 45 | C10: 45170 | D10: ='Commvault S3 Data Collection'!AC3 -> 8709.11
B11: 45 | C11: 45200 | D11: ='Commvault S3 Data Collection'!AD3 -> 10345.69
